Workbook
Name _Hlk156828105: Distribution!#REF!

Sheet Summary-WI
B1: Date | C1: 45808 | G1: 5 | H1: =G1+1 -> 6 | I1: =H1+1 -> 7 | J1: =I1+1 -> 8 | K1: =J1+1 -> 9 | L1: =K1+1 -> 10 | M1: =L1+1 -> 11 | N1: =M1+1 -> 12 | O1: =N1+1 -> 13 | ... AA1: =Z1+1 -> 25
J2: YTD | K2: 1 | L2: =K2+1 -> 2 | M2: =L2+1 -> 3 | N2: =M2+1 -> 4 | O2: =N2+1 -> 5 | P2: =O2+1 -> 6 | Q2: =P2+1 -> 7 | R2: =Q2+1 -> 8 | S2: =R2+1 -> 9 | ... AA2: =Z2+1 -> 17
A3: Ordering | B3: Columns | C3: Inception Date | D3: 2025 | E3: Tickers | F3: Fund Name | G3: 1 | H3: 3 | I3: 6 | J3: 5 | K3: 12 | L3: =K3+12 -> 24 | M3: =L3+12 -> 36 | N3: =M3+12 -> 48 | O3: =N3+12 -> 60 | P3: =O3+12 -> 72 | Q3: =P3+12 -> 84 | R3: =Q3+12 -> 96 | S3: =R3+12 -> 108 | ... Y3: =X3+12 -> 180 | Z3: Since Inception Annualized | AA3: Since Inception Cumulative Returns
A4: =VLOOKUP(E4,Rank!A:B,2,FALSE) -> 1 | B4: 31 | C4: 43982 | D4: HHL_A | E4: HHL | F4: =VLOOKUP(D4,Mapping!C:D,2,FALSE) -> Harvest Healthcare Leaders Income ETF | G4: =VLOOKUP($B4,Summary!$A:$X,'Summary-WI'!G$1,FALSE) -> Harvest Global REIT Leaders Income ETF | H4: =VLOOKUP($B4,Summary!$A:$X,'Summary-WI'!H$1,FALSE) -> 0.024899083 | I4: =VLOOKUP($B4,Summary!$A:$X,'Summary-WI'!I$1,FALSE) -> 0.014768331 | J4: =VLOOKUP($B4,Summary!$A:$X,'Summary-WI'!J$1,FALSE) -> 0.00074045823 | K4: =VLOOKUP($B4,Summary!$A:$X,'Summary-WI'!K$1,FALSE) -> 0.024899083 | L4: =VLOOKUP($B4,Summary!$A:$X,'Summary-WI'!L$1,FALSE) -> 0.007734841 | M4: =VLOOKUP($B4,Summary!$A:$X,'Summary-WI'!M$1,FALSE) -> 0.04351792 | N4: =VLOOKUP($B4,Summary!$A:$X,'Summary-WI'!N$1,FALSE) -> 0.0018639034 | ... Y4: =VLOOKUP($B4,Summary!$A:$X,'Summary-WI'!Y$1,FALSE)
A5: =VLOOKUP(E5,Rank!A:B,2,FALSE) -> 1 | B5: 32 | D5: HHL_B | E5: HHL | F5: =VLOOKUP(D5,Mapping!C:D,2,FALSE) -> Harvest Healthcare Leaders Income ETF | G5: =VLOOKUP($B5,Summary!$A:$X,'Summary-WI'!G$1,FALSE) -> Harvest Healthcare Leaders Income ETF | H5: =VLOOKUP($B5,Summary!$A:$X,'Summary-WI'!H$1,FALSE) -> -0.0058851041 | I5: =VLOOKUP($B5,Summary!$A:$X,'Summary-WI'!I$1,FALSE) -> 0.051257079 | J5: =VLOOKUP($B5,Summary!$A:$X,'Summary-WI'!J$1,FALSE) -> 0.15224509 | K5: =VLOOKUP($B5,Summary!$A:$X,'Summary-WI'!K$1,FALSE) -> -0.0058851041 | L5: =VLOOKUP($B5,Summary!$A:$X,'Summary-WI'!L$1,FALSE) -> 0.031648917 | M5: =VLOOKUP($B5,Summary!$A:$X,'Summary-WI'!M$1,FALSE) -> 0.050047008 | N5: =VLOOKUP($B5,Summary!$A:$X,'Summary-WI'!N$1,FALSE) -> 0.071538588 | ... Y5: =VLOOKUP($B5,Summary!$A:$X,'Summary-WI'!Y$1,FALSE)
A6: =VLOOKUP(E6,Rank!A:B,2,FALSE) -> 1 | B6: 33 | D6: HHL_U | E6: HHL | F6: =VLOOKUP(D6,Mapping!C:D,2,FALSE) -> Harvest Healthcare Leaders Income ETF | G6: =VLOOKUP($B6,Summary!$A:$X,'Summary-WI'!G$1,FALSE) -> Harvest Healthcare Leaders Income ETF | H6: =VLOOKUP($B6,Summary!$A:$X,'Summary-WI'!H$1,FALSE) -> -0.012635319 | I6: =VLOOKUP($B6,Summary!$A:$X,'Summary-WI'!I$1,FALSE) -> 0.025626558 | J6: =VLOOKUP($B6,Summary!$A:$X,'Summary-WI'!J$1,FALSE) -> 0.14239215 | K6: =VLOOKUP($B6,Summary!$A:$X,'Summary-WI'!K$1,FALSE) -> -0.012635319 | L6: =VLOOKUP($B6,Summary!$A:$X,'Summary-WI'!L$1,FALSE) -> -0.0151065 | M6: =VLOOKUP($B6,Summary!$A:$X,'Summary-WI'!M$1,FALSE) -> 0.071658577 | N6: =VLOOKUP($B6,Summary!$A:$X,'Summary-WI'!N$1,FALSE) -> 0.09218425 | ... Y6: =VLOOKUP($B6,Summary!$A:$X,'Summary-WI'!Y$1,FALSE)
A8: =VLOOKUP(E8,Rank!A:B,2,FALSE) -> 2 | B8: 26 | D8: HBL_A | E8: HBF | F8: =VLOOKUP(D8,Mapping!C:D,2,FALSE) -> Harvest Brand Leaders Plus Income ETF | G8: =VLOOKUP($B8,Summary!$A:$X,'Summary-WI'!G$1,FALSE) -> Harvest Canadian Income & Growth Fund | H8: =VLOOKUP($B8,Summary!$A:$X,'Summary-WI'!H$1,FALSE) | I8: =VLOOKUP($B8,Summary!$A:$X,'Summary-WI'!I$1,FALSE) | J8: =VLOOKUP($B8,Summary!$A:$X,'Summary-WI'!J$1,FALSE) | K8: =VLOOKUP($B8,Summary!$A:$X,'Summary-WI'!K$1,FALSE) | L8: =VLOOKUP($B8,Summary!$A:$X,'Summary-WI'!L$1,FALSE) | M8: =VLOOKUP($B8,Summary!$A:$X,'Summary-WI'!M$1,FALSE) | N8: =VLOOKUP($B8,Summary!$A:$X,'Summary-WI'!N$1,FALSE) | ... Y8: =VLOOKUP($B8,Summary!$A:$X,'Summary-WI'!Y$1,FALSE)
A9: =VLOOKUP(E9,Rank!A:B,2,FALSE) -> 2 | B9: 27 | D9: HBL_B | E9: HBF | F9: =VLOOKUP(D9,Mapping!C:D,2,FALSE) -> Harvest Brand Leaders Plus Income ETF | G9: =VLOOKUP($B9,Summary!$A:$X,'Summary-WI'!G$1,FALSE) -> Harvest Brand Leaders Plus Income ETF | H9: =VLOOKUP($B9,Summary!$A:$X,'Summary-WI'!H$1,FALSE) -> 9.3395099e-05 | I9: =VLOOKUP($B9,Summary!$A:$X,'Summary-WI'!I$1,FALSE) -> 0.0056333597 | J9: =VLOOKUP($B9,Summary!$A:$X,'Summary-WI'!J$1,FALSE) -> 0.097949563 | K9: =VLOOKUP($B9,Summary!$A:$X,'Summary-WI'!K$1,FALSE) -> 9.3395099e-05 | L9: =VLOOKUP($B9,Summary!$A:$X,'Summary-WI'!L$1,FALSE) -> 0.11805251 | M9: =VLOOKUP($B9,Summary!$A:$X,'Summary-WI'!M$1,FALSE) -> 0.14072633 | N9: =VLOOKUP($B9,Summary!$A:$X,'Summary-WI'!N$1,FALSE) -> 0.11458161 | ... Y9: =VLOOKUP($B9,Summary!$A:$X,'Summary-WI'!Y$1,FALSE)
A10: =VLOOKUP(E10,Rank!A:B,2,FALSE) -> 2 | B10: 28 | D10: HBL_U | E10: HBF | F10: =VLOOKUP(D10,Mapping!C:D,2,FALSE) -> Harvest Brand Leaders Plus Income ETF | G10: =VLOOKUP($B10,Summary!$A:$X,'Summary-WI'!G$1,FALSE) -> Harvest Brand Leaders Plus Income ETF | H10: =VLOOKUP($B10,Summary!$A:$X,'Summary-WI'!H$1,FALSE) -> -0.0063588058 | I10: =VLOOKUP($B10,Summary!$A:$X,'Summary-WI'!I$1,FALSE) -> -0.018144478 | J10: =VLOOKUP($B10,Summary!$A:$X,'Summary-WI'!J$1,FALSE) -> 0.089896494 | K10: =VLOOKUP($B10,Summary!$A:$X,'Summary-WI'!K$1,FALSE) -> -0.0063588058 | L10: =VLOOKUP($B10,Summary!$A:$X,'Summary-WI'!L$1,FALSE) -> 0.068016147 | M10: =VLOOKUP($B10,Summary!$A:$X,'Summary-WI'!M$1,FALSE) -> 0.1644338 | N10: =VLOOKUP($B10,Summary!$A:$X,'Summary-WI'!N$1,FALSE) -> 0.1368241 | ... Y10: =VLOOKUP($B10,Summary!$A:$X,'Summary-WI'!Y$1,FALSE)
A12: =VLOOKUP(E12,Rank!A:B,2,FALSE) -> 3 | B12: 3 | D12: HTA_A | E12: HTA | F12: =VLOOKUP(D12,Mapping!C:D,2,FALSE) -> Harvest Tech Achievers Growth & Income ETF | G12: =VLOOKUP($B12,Summary!$A:$X,'Summary-WI'!G$1,FALSE) -> Harvest Tech Achievers Growth & Income ETF | H12: =VLOOKUP($B12,Summary!$A:$X,'Summary-WI'!H$1,FALSE) -> 0.0039345121 | I12: =VLOOKUP($B12,Summary!$A:$X,'Summary-WI'!I$1,FALSE) -> -0.014066587 | J12: =VLOOKUP($B12,Summary!$A:$X,'Summary-WI'!J$1,FALSE) -> 0.070391771 | K12: =VLOOKUP($B12,Summary!$A:$X,'Summary-WI'!K$1,FALSE) -> 0.0039345121 | L12: =VLOOKUP($B12,Summary!$A:$X,'Summary-WI'!L$1,FALSE) -> 0.10909706 | M12: =VLOOKUP($B12,Summary!$A:$X,'Summary-WI'!M$1,FALSE) -> 0.15546626 | N12: =VLOOKUP($B12,Summary!$A:$X,'Summary-WI'!N$1,FALSE) -> 0.24714413 | ... Y12: =VLOOKUP($B12,Summary!$A:$X,'Summary-WI'!Y$1,FALSE)
A13: =VLOOKUP(E13,Rank!A:B,2,FALSE) -> 3 | B13: 4 | D13: HTA_B | E13: HTA | F13: =VLOOKUP(D13,Mapping!C:D,2,FALSE) -> Harvest Tech Achievers Growth & Income ETF | G13: =VLOOKUP($B13,Summary!$A:$X,'Summary-WI'!G$1,FALSE) -> Harvest Tech Achievers Growth & Income ETF | H13: =VLOOKUP($B13,Summary!$A:$X,'Summary-WI'!H$1,FALSE) -> -0.0022723097 | I13: =VLOOKUP($B13,Summary!$A:$X,'Summary-WI'!I$1,FALSE) -> -0.037067326 | J13: =VLOOKUP($B13,Summary!$A:$X,'Summary-WI'!J$1,FALSE) -> 0.063093209 | K13: =VLOOKUP($B13,Summary!$A:$X,'Summary-WI'!K$1,FALSE) -> -0.0022723097 | L13: =VLOOKUP($B13,Summary!$A:$X,'Summary-WI'!L$1,FALSE) -> 0.061444906 | M13: =VLOOKUP($B13,Summary!$A:$X,'Summary-WI'!M$1,FALSE) -> 0.18054652 | N13: =VLOOKUP($B13,Summary!$A:$X,'Summary-WI'!N$1,FALSE) -> 0.27238535 | ... Y13: =VLOOKUP($B13,Summary!$A:$X,'Summary-WI'!Y$1,FALSE)
A14: =VLOOKUP(E14,Rank!A:B,2,FALSE) -> 3 | B14: 5 | D14: HTA_U | E14: HTA | F14: =VLOOKUP(D14,Mapping!C:D,2,FALSE) -> Harvest Tech Achievers Growth & Income ETF | G14: =VLOOKUP($B14,Summary!$A:$X,'Summary-WI'!G$1,FALSE) -> Harvest Tech Achievers Growth & Income ETF | H14: =VLOOKUP($B14,Summary!$A:$X,'Summary-WI'!H$1,FALSE) -> 0.0057282875 | I14: =VLOOKUP($B14,Summary!$A:$X,'Summary-WI'!I$1,FALSE) -> -0.0081060304 | J14: =VLOOKUP($B14,Summary!$A:$X,'Summary-WI'!J$1,FALSE) -> 0.081823556 | K14: =VLOOKUP($B14,Summary!$A:$X,'Summary-WI'!K$1,FALSE) -> 0.0057282875 | L14: =VLOOKUP($B14,Summary!$A:$X,'Summary-WI'!L$1,FALSE) -> 0.13297781 | M14: =VLOOKUP($B14,Summary!$A:$X,'Summary-WI'!M$1,FALSE) -> 0.17310314 | N14: =VLOOKUP($B14,Summary!$A:$X,'Summary-WI'!N$1,FALSE) -> 0.26269149 | ... Y14: =VLOOKUP($B14,Summary!$A:$X,'Summary-WI'!Y$1,FALSE)
A16: =VLOOKUP(E16,Rank!A:B,2,FALSE) -> 4 | B16: 30 | D16: HGR | E16: HGR | F16: =VLOOKUP(D16,Mapping!C:D,2,FALSE) -> Harvest Global REIT Leaders Income ETF | G16: =VLOOKUP($B16,Summary!$A:$X,'Summary-WI'!G$1,FALSE) -> Harvest Global Gold Giants Index ETF | H16: =VLOOKUP($B16,Summary!$A:$X,'Summary-WI'!H$1,FALSE) -> 0.079774346 | I16: =VLOOKUP($B16,Summary!$A:$X,'Summary-WI'!I$1,FALSE) -> 0.31394586 | J16: =VLOOKUP($B16,Summary!$A:$X,'Summary-WI'!J$1,FALSE) -> 0.97695586 | K16: =VLOOKUP($B16,Summary!$A:$X,'Summary-WI'!K$1,FALSE) -> 0.079774346 | L16: =VLOOKUP($B16,Summary!$A:$X,'Summary-WI'!L$1,FALSE) -> 1.4919783 | M16: =VLOOKUP($B16,Summary!$A:$X,'Summary-WI'!M$1,FALSE) -> 1.012678 | N16: =VLOOKUP($B16,Summary!$A:$X,'Summary-WI'!N$1,FALSE) -> 0.51632314 | ... Y16: =VLOOKUP($B16,Summary!$A:$X,'Summary-WI'!Y$1,FALSE)
A18: =VLOOKUP(E18,Rank!A:B,2,FALSE) -> 5 | B18: 35 | D18: HRTM | E18: HUTL | F18: =VLOOKUP(D18,Mapping!C:D,2,FALSE) -> Harvest Equal Weight Global Utilities Income ETF | G18: =VLOOKUP($B18,Summary!$A:$X,'Summary-WI'!G$1,FALSE) -> Blockchain Technologies ETF | H18: =VLOOKUP($B18,Summary!$A:$X,'Summary-WI'!H$1,FALSE) -> 0.026827919 | I18: =VLOOKUP($B18,Summary!$A:$X,'Summary-WI'!I$1,FALSE) -> -0.26466677 | J18: =VLOOKUP($B18,Summary!$A:$X,'Summary-WI'!J$1,FALSE) -> 0.064522088 | K18: =VLOOKUP($B18,Summary!$A:$X,'Summary-WI'!K$1,FALSE) -> 0.026827919 | L18: =VLOOKUP($B18,Summary!$A:$X,'Summary-WI'!L$1,FALSE) -> 0.089636537 | M18: =VLOOKUP($B18,Summary!$A:$X,'Summary-WI'!M$1,FALSE) -> 0.28919705 | N18: =VLOOKUP($B18,Summary!$A:$X,'Summary-WI'!N$1,FALSE) -> 0.29566078 | ... Y18: =VLOOKUP($B18,Summary!$A:$X,'Summary-WI'!Y$1,FALSE)
A20: =VLOOKUP(E20,Rank!A:B,2,FALSE) -> 6 | B20: 14 | D20: HEN_A | E20: HPF | F20: =VLOOKUP(D20,Mapping!C:D,2,FALSE) -> Harvest Energy Leaders Plus Income ETF | G20: =VLOOKUP($B20,Summary!$A:$X,'Summary-WI'!G$1,FALSE) -> Harvest Canadian Equity Income Leaders ETF | H20: =VLOOKUP($B20,Summary!$A:$X,'Summary-WI'!H$1,FALSE) -> 0.020251296 | I20: =VLOOKUP($B20,Summary!$A:$X,'Summary-WI'!I$1,FALSE) -> 0.076356686 | J20: =VLOOKUP($B20,Summary!$A:$X,'Summary-WI'!J$1,FALSE) -> 0.1593143 | K20: =VLOOKUP($B20,Summary!$A:$X,'Summary-WI'!K$1,FALSE) -> 0.020251296 | L20: =VLOOKUP($B20,Summary!$A:$X,'Summary-WI'!L$1,FALSE) -> 0.27459501 | M20: =VLOOKUP($B20,Summary!$A:$X,'Summary-WI'!M$1,FALSE) -> 0.22089754 | N20: =VLOOKUP($B20,Summary!$A:$X,'Summary-WI'!N$1,FALSE) -> 0.1430029 | ... Y20: =VLOOKUP($B20,Summary!$A:$X,'Summary-WI'!Y$1,FALSE)
A21: =VLOOKUP(E21,Rank!A:B,2,FALSE) -> 6 | B21: 15 | D21: HEN_U | E21: HPF | F21: =VLOOKUP(D21,Mapping!C:D,2,FALSE) -> Harvest Energy Leaders Plus Income ETF | G21: =VLOOKUP($B21,Summary!$A:$X,'Summary-WI'!G$1,FALSE) -> Harvest Energy Leaders Plus Income ETF | H21: =VLOOKUP($B21,Summary!$A:$X,'Summary-WI'!H$1,FALSE) -> 0.090752117 | I21: =VLOOKUP($B21,Summary!$A:$X,'Summary-WI'!I$1,FALSE) -> 0.11611086 | J21: =VLOOKUP($B21,Summary!$A:$X,'Summary-WI'!J$1,FALSE) -> 0.15758369 | K21: =VLOOKUP($B21,Summary!$A:$X,'Summary-WI'!K$1,FALSE) -> 0.090752117 | L21: =VLOOKUP($B21,Summary!$A:$X,'Summary-WI'!L$1,FALSE) -> 0.1705267 | M21: =VLOOKUP($B21,Summary!$A:$X,'Summary-WI'!M$1,FALSE) -> 0.084394419 | N21: =VLOOKUP($B21,Summary!$A:$X,'Summary-WI'!N$1,FALSE) -> 0.051229043 | ... Y21: =VLOOKUP($B21,Summary!$A:$X,'Summary-WI'!Y$1,FALSE)
... A35: =VLOOKUP(E35,Rank!A:B,2,FALSE) -> 14 | B35: 43 | D35: HRVJ | E35: TBIL | F35: =VLOOKUP(D35,Mapping!C:D,2,FALSE) -> Harvest Canadian T-Bill ETF | G35: =VLOOKUP($B35,Summary!$A:$X,'Summary-WI'!G$1,FALSE) -> Harvest Travel & Leisure Income ETF | H35: =VLOOKUP($B35,Summary!$A:$X,'Summary-WI'!H$1,FALSE) -> -0.012912482 | I35: =VLOOKUP($B35,Summary!$A:$X,'Summary-WI'!I$1,FALSE) -> 0.068988412 | J35: =VLOOKUP($B35,Summary!$A:$X,'Summary-WI'!J$1,FALSE) -> 0.055809793 | K35: =VLOOKUP($B35,Summary!$A:$X,'Summary-WI'!K$1,FALSE) -> -0.012912482 | L35: =VLOOKUP($B35,Summary!$A:$X,'Summary-WI'!L$1,FALSE) -> 0.020381643 | M35: =VLOOKUP($B35,Summary!$A:$X,'Summary-WI'!M$1,FALSE) -> 0.11938376 | N35: =VLOOKUP($B35,Summary!$A:$X,'Summary-WI'!N$1,FALSE) | ... Y35: =VLOOKUP($B35,Summary!$A:$X,'Summary-WI'!Y$1,FALSE)
A37: =VLOOKUP(E37,Rank!A:B,2,FALSE) -> 28 | B37: 48 | D37: HRVL_A | E37: HPYM_A | F37: Harvest Premium Yield Treasury 7-10 Year Treasury ETF | G37: =VLOOKUP($B37,Summary!$A:$X,'Summary-WI'!G$1,FALSE) -> Big Pharma Split Corp | H37: =VLOOKUP($B37,Summary!$A:$X,'Summary-WI'!H$1,FALSE) -> 0.032924749 | I37: =VLOOKUP($B37,Summary!$A:$X,'Summary-WI'!I$1,FALSE) -> 0.1940638 | J37: =VLOOKUP($B37,Summary!$A:$X,'Summary-WI'!J$1,FALSE) -> 0.43562679 | K37: =VLOOKUP($B37,Summary!$A:$X,'Summary-WI'!K$1,FALSE) -> 0.032924749 | L37: =VLOOKUP($B37,Summary!$A:$X,'Summary-WI'!L$1,FALSE) -> 0.24952377 | M37: =VLOOKUP($B37,Summary!$A:$X,'Summary-WI'!M$1,FALSE) -> 0.11862177 | N37: =VLOOKUP($B37,Summary!$A:$X,'Summary-WI'!N$1,FALSE) -> 0.092630211 | ... Y37: =VLOOKUP($B37,Summary!$A:$X,'Summary-WI'!Y$1,FALSE)
A38: =VLOOKUP(E38,Rank!A:B,2,FALSE) -> 29 | B38: 49 | D38: HRVL_U | E38: HPYM_U | F38: Harvest Premium Yield Treasury 7-10 Year Treasury ETF | G38: =VLOOKUP($B38,Summary!$A:$X,'Summary-WI'!G$1,FALSE) -> Harvest Premium Yield Treasury 7-10 Year Treasury ETF | H38: =VLOOKUP($B38,Summary!$A:$X,'Summary-WI'!H$1,FALSE) -> -0.0021237408 | I38: =VLOOKUP($B38,Summary!$A:$X,'Summary-WI'!I$1,FALSE) -> -0.00050712575 | J38: =VLOOKUP($B38,Summary!$A:$X,'Summary-WI'!J$1,FALSE) -> 0.025946831 | K38: =VLOOKUP($B38,Summary!$A:$X,'Summary-WI'!K$1,FALSE) -> -0.0021237408 | L38: =VLOOKUP($B38,Summary!$A:$X,'Summary-WI'!L$1,FALSE) -> 0.057875352 | M38: =VLOOKUP($B38,Summary!$A:$X,'Summary-WI'!M$1,FALSE) -> 0.02137388 | N38: =VLOOKUP($B38,Summary!$A:$X,'Summary-WI'!N$1,FALSE) | ... Y38: =VLOOKUP($B38,Summary!$A:$X,'Summary-WI'!Y$1,FALSE)
A40: =VLOOKUP(E40,Rank!A:B,2,FALSE) -> 15 | B40: 6 | D40: HRA1 | E40: HHLE | F40: =VLOOKUP(D40,Mapping!C:D,2,FALSE) -> Harvest Healthcare Leaders Enhanced Income ETF | G40: =VLOOKUP($B40,Summary!$A:$X,'Summary-WI'!G$1,FALSE) -> Harvest Healthcare Leaders Enhanced Income ETF | H40: =VLOOKUP($B40,Summary!$A:$X,'Summary-WI'!H$1,FALSE) -> -0.0056687754 | I40: =VLOOKUP($B40,Summary!$A:$X,'Summary-WI'!I$1,FALSE) -> 0.059216365 | J40: =VLOOKUP($B40,Summary!$A:$X,'Summary-WI'!J$1,FALSE) -> 0.1865493 | K40: =VLOOKUP($B40,Summary!$A:$X,'Summary-WI'!K$1,FALSE) -> -0.0056687754 | L40: =VLOOKUP($B40,Summary!$A:$X,'Summary-WI'!L$1,FALSE) -> 0.023311142 | M40: =VLOOKUP($B40,Summary!$A:$X,'Summary-WI'!M$1,FALSE) -> 0.04942619 | N40: =VLOOKUP($B40,Summary!$A:$X,'Summary-WI'!N$1,FALSE) -> 0.074077154 | ... Y40: =VLOOKUP($B40,Summary!$A:$X,'Summary-WI'!Y$1,FALSE)
A42: =VLOOKUP(E42,Rank!A:B,2,FALSE) -> 16 | B42: 8 | D42: HRA3 | E42: HTAE | F42: =VLOOKUP(D42,Mapping!C:D,2,FALSE) -> Harvest Tech Achievers Enhanced Income ETF | G42: =VLOOKUP($B42,Summary!$A:$X,'Summary-WI'!G$1,FALSE) -> Harvest Tech Achievers Enhanced Income ETF | H42: =VLOOKUP($B42,Summary!$A:$X,'Summary-WI'!H$1,FALSE) -> 0.0031615072 | I42: =VLOOKUP($B42,Summary!$A:$X,'Summary-WI'!I$1,FALSE) -> -0.024408773 | J42: =VLOOKUP($B42,Summary!$A:$X,'Summary-WI'!J$1,FALSE) -> 0.082765228 | K42: =VLOOKUP($B42,Summary!$A:$X,'Summary-WI'!K$1,FALSE) -> 0.0031615072 | L42: =VLOOKUP($B42,Summary!$A:$X,'Summary-WI'!L$1,FALSE) -> 0.11535956 | M42: =VLOOKUP($B42,Summary!$A:$X,'Summary-WI'!M$1,FALSE) -> 0.17588542 | N42: =VLOOKUP($B42,Summary!$A:$X,'Summary-WI'!N$1,FALSE) -> 0.29370095 | ... Y42: =VLOOKUP($B42,Summary!$A:$X,'Summary-WI'!Y$1,FALSE)
A44: =VLOOKUP(E44,Rank!A:B,2,FALSE) -> 17 | B44: 9 | D44: HRA4 | E44: HUTE | F44: =VLOOKUP(D44,Mapping!C:D,2,FALSE) -> Harvest Equal Weight Global Utilities Enhanced Income ETF | G44: =VLOOKUP($B44,Summary!$A:$X,'Summary-WI'!G$1,FALSE) -> Harvest Equal Weight Global Utilities Enhanced Income ETF | H44: =VLOOKUP($B44,Summary!$A:$X,'Summary-WI'!H$1,FALSE) -> 0.048062951 | I44: =VLOOKUP($B44,Summary!$A:$X,'Summary-WI'!I$1,FALSE) -> 0.042974764 | J44: =VLOOKUP($B44,Summary!$A:$X,'Summary-WI'!J$1,FALSE) -> 0.082931167 | K44: =VLOOKUP($B44,Summary!$A:$X,'Summary-WI'!K$1,FALSE) -> 0.048062951 | L44: =VLOOKUP($B44,Summary!$A:$X,'Summary-WI'!L$1,FALSE) -> 0.22661672 | M44: =VLOOKUP($B44,Summary!$A:$X,'Summary-WI'!M$1,FALSE) -> 0.21329325 | N44: =VLOOKUP($B44,Summary!$A:$X,'Summary-WI'!N$1,FALSE) -> 0.1249266 | ... Y44: =VLOOKUP($B44,Summary!$A:$X,'Summary-WI'!Y$1,FALSE)
A46: =VLOOKUP(E46,Rank!A:B,2,FALSE) -> 18 | B46: 44 | D46: HRAX | E46: HDIF | F46: Harvest Diversified Monthly Income ETF | G46: =VLOOKUP($B46,Summary!$A:$X,'Summary-WI'!G$1,FALSE) -> Harvest Canadian T-Bill ETF | H46: =VLOOKUP($B46,Summary!$A:$X,'Summary-WI'!H$1,FALSE) -> 0.0017040034 | I46: =VLOOKUP($B46,Summary!$A:$X,'Summary-WI'!I$1,FALSE) -> 0.0053896465 | J46: =VLOOKUP($B46,Summary!$A:$X,'Summary-WI'!J$1,FALSE) -> 0.011726823 | K46: =VLOOKUP($B46,Summary!$A:$X,'Summary-WI'!K$1,FALSE) -> 0.0017040034 | L46: =VLOOKUP($B46,Summary!$A:$X,'Summary-WI'!L$1,FALSE) -> 0.02499132 | M46: =VLOOKUP($B46,Summary!$A:$X,'Summary-WI'!M$1,FALSE) -> 0.034299526 | N46: =VLOOKUP($B46,Summary!$A:$X,'Summary-WI'!N$1,FALSE) | ... Y46: =VLOOKUP($B46,Summary!$A:$X,'Summary-WI'!Y$1,FALSE)
A48: =VLOOKUP(E48,Rank!A:B,2,FALSE) -> 19 | B48: 29 | D48: HRTF | E48: HGGG | F48: =VLOOKUP(D48,Mapping!C:D,2,FALSE) -> Harvest Global Gold Giants Index ETF | G48: =VLOOKUP($B48,Summary!$A:$X,'Summary-WI'!G$1,FALSE) -> Harvest Brand Leaders Plus Income ETF | H48: =VLOOKUP($B48,Summary!$A:$X,'Summary-WI'!H$1,FALSE) -> 0.001602704 | I48: =VLOOKUP($B48,Summary!$A:$X,'Summary-WI'!I$1,FALSE) -> 0.011367886 | J48: =VLOOKUP($B48,Summary!$A:$X,'Summary-WI'!J$1,FALSE) -> 0.10907983 | K48: =VLOOKUP($B48,Summary!$A:$X,'Summary-WI'!K$1,FALSE) -> 0.001602704 | L48: =VLOOKUP($B48,Summary!$A:$X,'Summary-WI'!L$1,FALSE) -> 0.13998044 | M48: =VLOOKUP($B48,Summary!$A:$X,'Summary-WI'!M$1,FALSE) -> 0.15707 | N48: =VLOOKUP($B48,Summary!$A:$X,'Summary-WI'!N$1,FALSE) -> 0.12812934 | ... Y48: =VLOOKUP($B48,Summary!$A:$X,'Summary-WI'!Y$1,FALSE)
A50: =VLOOKUP(E50,Rank!A:B,2,FALSE) -> 20 | B50: 34 | D50: HRTJ | E50: HBLK | F50: =VLOOKUP(D50,Mapping!C:D,2,FALSE) -> Blockchain Technologies ETF | G50: =VLOOKUP($B50,Summary!$A:$X,'Summary-WI'!G$1,FALSE) -> Harvest Healthcare Leaders Income ETF | H50: =VLOOKUP($B50,Summary!$A:$X,'Summary-WI'!H$1,FALSE) -> -0.0047183756 | I50: =VLOOKUP($B50,Summary!$A:$X,'Summary-WI'!I$1,FALSE) -> 0.056457457 | J50: =VLOOKUP($B50,Summary!$A:$X,'Summary-WI'!J$1,FALSE) -> 0.16250828 | K50: =VLOOKUP($B50,Summary!$A:$X,'Summary-WI'!K$1,FALSE) -> -0.0047183756 | L50: =VLOOKUP($B50,Summary!$A:$X,'Summary-WI'!L$1,FALSE) -> 0.051243733 | M50: =VLOOKUP($B50,Summary!$A:$X,'Summary-WI'!M$1,FALSE) -> 0.064894941 | N50: =VLOOKUP($B50,Summary!$A:$X,'Summary-WI'!N$1,FALSE) -> 0.083843658 | ... Y50: =VLOOKUP($B50,Summary!$A:$X,'Summary-WI'!Y$1,FALSE)
A52: =VLOOKUP(E52,Rank!A:B,2,FALSE) -> 21 | B52: 39 | D52: HRTY_A | E52: TRVL | F52: =VLOOKUP(D52,Mapping!C:D,2,FALSE) -> Harvest Travel Leisure Index ETF | G52: =VLOOKUP($B52,Summary!$A:$X,'Summary-WI'!G$1,FALSE) -> Harvest Clean Energy ETF | H52: =VLOOKUP($B52,Summary!$A:$X,'Summary-WI'!H$1,FALSE) -> 0.095312438 | I52: =VLOOKUP($B52,Summary!$A:$X,'Summary-WI'!I$1,FALSE) -> 0.037057611 | J52: =VLOOKUP($B52,Summary!$A:$X,'Summary-WI'!J$1,FALSE) -> 0.27397324 | K52: =VLOOKUP($B52,Summary!$A:$X,'Summary-WI'!K$1,FALSE) -> 0.095312438 | L52: =VLOOKUP($B52,Summary!$A:$X,'Summary-WI'!L$1,FALSE) -> 0.45095172 | M52: =VLOOKUP($B52,Summary!$A:$X,'Summary-WI'!M$1,FALSE) -> 0.13229166 | N52: =VLOOKUP($B52,Summary!$A:$X,'Summary-WI'!N$1,FALSE) -> -0.054581089 | ... Y52: =VLOOKUP($B52,Summary!$A:$X,'Summary-WI'!Y$1,FALSE)
A53: =VLOOKUP(E53,Rank!A:B,2,FALSE) -> 21 | B53: 40 | D53: HRTY_U | E53: TRVL | F53: =VLOOKUP(D53,Mapping!C:D,2,FALSE) -> Harvest Travel Leisure Index ETF | G53: =VLOOKUP($B53,Summary!$A:$X,'Summary-WI'!G$1,FALSE) -> Harvest Travel Leisure Index ETF | H53: =VLOOKUP($B53,Summary!$A:$X,'Summary-WI'!H$1,FALSE) -> -0.017052328 | I53: =VLOOKUP($B53,Summary!$A:$X,'Summary-WI'!I$1,FALSE) -> 0.060401468 | J53: =VLOOKUP($B53,Summary!$A:$X,'Summary-WI'!J$1,FALSE) -> 0.050944171 | K53: =VLOOKUP($B53,Summary!$A:$X,'Summary-WI'!K$1,FALSE) -> -0.017052328 | L53: =VLOOKUP($B53,Summary!$A:$X,'Summary-WI'!L$1,FALSE) -> 0.01562815 | M53: =VLOOKUP($B53,Summary!$A:$X,'Summary-WI'!M$1,FALSE) -> 0.18006236 | N53: =VLOOKUP($B53,Summary!$A:$X,'Summary-WI'!N$1,FALSE) -> 0.17031418 | ... Y53: =VLOOKUP($B53,Summary!$A:$X,'Summary-WI'!Y$1,FALSE)
A55: =VLOOKUP(E55,Rank!A:B,2,FALSE) -> 22 | B55: 38 | D55: HRTX | E55: HCLN | F55: =VLOOKUP(D55,Mapping!C:D,2,FALSE) -> Harvest Clean Energy ETF | G55: =VLOOKUP($B55,Summary!$A:$X,'Summary-WI'!G$1,FALSE) -> Harvest US Bank Leaders Income ETF | H55: =VLOOKUP($B55,Summary!$A:$X,'Summary-WI'!H$1,FALSE) -> 0.025618787 | I55: =VLOOKUP($B55,Summary!$A:$X,'Summary-WI'!I$1,FALSE) -> 0.12575425 | J55: =VLOOKUP($B55,Summary!$A:$X,'Summary-WI'!J$1,FALSE) -> 0.15961469 | K55: =VLOOKUP($B55,Summary!$A:$X,'Summary-WI'!K$1,FALSE) -> 0.025618787 | L55: =VLOOKUP($B55,Summary!$A:$X,'Summary-WI'!L$1,FALSE) -> 0.14431258 | M55: =VLOOKUP($B55,Summary!$A:$X,'Summary-WI'!M$1,FALSE) -> 0.26661566 | N55: =VLOOKUP($B55,Summary!$A:$X,'Summary-WI'!N$1,FALSE) -> 0.10791511 | ... Y55: =VLOOKUP($B55,Summary!$A:$X,'Summary-WI'!Y$1,FALSE)
A57: =VLOOKUP(E57,Rank!A:B,2,FALSE) -> 23 | B57: 45 | D57: PRM unit | E57: PRM | F57: Big Pharm Fund | G57: =VLOOKUP($B57,Summary!$A:$X,'Summary-WI'!G$1,FALSE) -> Harvest Diversified Monthly Income ETF | H57: =VLOOKUP($B57,Summary!$A:$X,'Summary-WI'!H$1,FALSE) -> 0.0045624315 | I57: =VLOOKUP($B57,Summary!$A:$X,'Summary-WI'!I$1,FALSE) -> 0.037776627 | J57: =VLOOKUP($B57,Summary!$A:$X,'Summary-WI'!J$1,FALSE) -> 0.10627477 | K57: =VLOOKUP($B57,Summary!$A:$X,'Summary-WI'!K$1,FALSE) -> 0.0045624315 | L57: =VLOOKUP($B57,Summary!$A:$X,'Summary-WI'!L$1,FALSE) -> 0.11712546 | M57: =VLOOKUP($B57,Summary!$A:$X,'Summary-WI'!M$1,FALSE) -> 0.16619934 | N57: =VLOOKUP($B57,Summary!$A:$X,'Summary-WI'!N$1,FALSE) -> 0.13332449 | ... Y57: =VLOOKUP($B57,Summary!$A:$X,'Summary-WI'!Y$1,FALSE)
A58: =VLOOKUP(E58,Rank!A:B,2,FALSE) -> 23 | B58: 46 | D58: PRM Pref | E58: PRM | F58: Big Pharma Split Corp | G58: =VLOOKUP($B58,Summary!$A:$X,'Summary-WI'!G$1,FALSE) -> Big Pharm Fund | H58: =VLOOKUP($B58,Summary!$A:$X,'Summary-WI'!H$1,FALSE) -> 0.019210503 | I58: =VLOOKUP($B58,Summary!$A:$X,'Summary-WI'!I$1,FALSE) -> 0.11263726 | J58: =VLOOKUP($B58,Summary!$A:$X,'Summary-WI'!J$1,FALSE) -> 0.23458446 | K58: =VLOOKUP($B58,Summary!$A:$X,'Summary-WI'!K$1,FALSE) -> 0.019210503 | L58: =VLOOKUP($B58,Summary!$A:$X,'Summary-WI'!L$1,FALSE) -> 0.15934471 | M58: =VLOOKUP($B58,Summary!$A:$X,'Summary-WI'!M$1,FALSE) -> 0.088925156 | N58: =VLOOKUP($B58,Summary!$A:$X,'Summary-WI'!N$1,FALSE) -> 0.074282224 | ... Y58: =VLOOKUP($B58,Summary!$A:$X,'Summary-WI'!Y$1,FALSE)
A59: =VLOOKUP(E59,Rank!A:B,2,FALSE) -> 23 | B59: 47 | D59: PRM Class A | E59: PRM | F59: Big Pharma Split Corp Preferred class | G59: =VLOOKUP($B59,Summary!$A:$X,'Summary-WI'!G$1,FALSE) -> Big Pharma Split Corp Preferred class | H59: =VLOOKUP($B59,Summary!$A:$X,'Summary-WI'!H$1,FALSE) -> 0 | I59: =VLOOKUP($B59,Summary!$A:$X,'Summary-WI'!I$1,FALSE) -> 0.0125 | J59: =VLOOKUP($B59,Summary!$A:$X,'Summary-WI'!J$1,FALSE) -> 0.02515625 | K59: =VLOOKUP($B59,Summary!$A:$X,'Summary-WI'!K$1,FALSE) -> 0 | L59: =VLOOKUP($B59,Summary!$A:$X,'Summary-WI'!L$1,FALSE) -> 0.050945337 | M59: =VLOOKUP($B59,Summary!$A:$X,'Summary-WI'!M$1,FALSE) -> 0.050945337 | N59: =VLOOKUP($B59,Summary!$A:$X,'Summary-WI'!N$1,FALSE) -> 0.050945337 | ... Y59: =VLOOKUP($B59,Summary!$A:$X,'Summary-WI'!Y$1,FALSE)
A61: =VLOOKUP(E61,Rank!A:B,2,FALSE) -> 24 | B61: 21 | D61: HCF_I | E61: HCF | F61: =VLOOKUP(D61,Mapping!C:D,2,FALSE) -> Harvest Canadian Income & Growth Fund | G61: =VLOOKUP($B61,Summary!$A:$X,'Summary-WI'!G$1,FALSE) -> Harvest Banks & Buildings Income Fund | H61: =VLOOKUP($B61,Summary!$A:$X,'Summary-WI'!H$1,FALSE) | I61: =VLOOKUP($B61,Summary!$A:$X,'Summary-WI'!I$1,FALSE) | J61: =VLOOKUP($B61,Summary!$A:$X,'Summary-WI'!J$1,FALSE) | K61: =VLOOKUP($B61,Summary!$A:$X,'Summary-WI'!K$1,FALSE) | L61: =VLOOKUP($B61,Summary!$A:$X,'Summary-WI'!L$1,FALSE) | M61: =VLOOKUP($B61,Summary!$A:$X,'Summary-WI'!M$1,FALSE) | N61: =VLOOKUP($B61,Summary!$A:$X,'Summary-WI'!N$1,FALSE) | ... Y61: =VLOOKUP($B61,Summary!$A:$X,'Summary-WI'!Y$1,FALSE)
A62: =VLOOKUP(E62,Rank!A:B,2,FALSE) -> 24 | B62: 22 | D62: HCF_R | E62: HCF | F62: =VLOOKUP(D62,Mapping!C:D,2,FALSE) -> Harvest Canadian Income & Growth Fund | G62: =VLOOKUP($B62,Summary!$A:$X,'Summary-WI'!G$1,FALSE) -> Harvest Canadian Income & Growth Fund | H62: =VLOOKUP($B62,Summary!$A:$X,'Summary-WI'!H$1,FALSE) | I62: =VLOOKUP($B62,Summary!$A:$X,'Summary-WI'!I$1,FALSE) | J62: =VLOOKUP($B62,Summary!$A:$X,'Summary-WI'!J$1,FALSE) | K62: =VLOOKUP($B62,Summary!$A:$X,'Summary-WI'!K$1,FALSE) | L62: =VLOOKUP($B62,Summary!$A:$X,'Summary-WI'!L$1,FALSE) | M62: =VLOOKUP($B62,Summary!$A:$X,'Summary-WI'!M$1,FALSE) | N62: =VLOOKUP($B62,Summary!$A:$X,'Summary-WI'!N$1,FALSE) | ... Y62: =VLOOKUP($B62,Summary!$A:$X,'Summary-WI'!Y$1,FALSE)
A63: =VLOOKUP(E63,Rank!A:B,2,FALSE) -> 24 | B63: 23 | D63: HCF_A | E63: HCF | F63: =VLOOKUP(D63,Mapping!C:D,2,FALSE) -> Harvest Canadian Income & Growth Fund | G63: =VLOOKUP($B63,Summary!$A:$X,'Summary-WI'!G$1,FALSE) -> Harvest Canadian Income & Growth Fund | H63: =VLOOKUP($B63,Summary!$A:$X,'Summary-WI'!H$1,FALSE) | I63: =VLOOKUP($B63,Summary!$A:$X,'Summary-WI'!I$1,FALSE) | J63: =VLOOKUP($B63,Summary!$A:$X,'Summary-WI'!J$1,FALSE) | K63: =VLOOKUP($B63,Summary!$A:$X,'Summary-WI'!K$1,FALSE) | L63: =VLOOKUP($B63,Summary!$A:$X,'Summary-WI'!L$1,FALSE) | M63: =VLOOKUP($B63,Summary!$A:$X,'Summary-WI'!M$1,FALSE) | N63: =VLOOKUP($B63,Summary!$A:$X,'Summary-WI'!N$1,FALSE) | ... Y63: =VLOOKUP($B63,Summary!$A:$X,'Summary-WI'!Y$1,FALSE)
A64: =VLOOKUP(E64,Rank!A:B,2,FALSE) -> 24 | B64: 24 | D64: HCF_F | E64: HCF | F64: =VLOOKUP(D64,Mapping!C:D,2,FALSE) -> Harvest Canadian Income & Growth Fund | G64: =VLOOKUP($B64,Summary!$A:$X,'Summary-WI'!G$1,FALSE) -> Harvest Canadian Income & Growth Fund | H64: =VLOOKUP($B64,Summary!$A:$X,'Summary-WI'!H$1,FALSE) | I64: =VLOOKUP($B64,Summary!$A:$X,'Summary-WI'!I$1,FALSE) | J64: =VLOOKUP($B64,Summary!$A:$X,'Summary-WI'!J$1,FALSE) | K64: =VLOOKUP($B64,Summary!$A:$X,'Summary-WI'!K$1,FALSE) | L64: =VLOOKUP($B64,Summary!$A:$X,'Summary-WI'!L$1,FALSE) | M64: =VLOOKUP($B64,Summary!$A:$X,'Summary-WI'!M$1,FALSE) | N64: =VLOOKUP($B64,Summary!$A:$X,'Summary-WI'!N$1,FALSE) | ... Y64: =VLOOKUP($B64,Summary!$A:$X,'Summary-WI'!Y$1,FALSE)
A65: =VLOOKUP(E65,Rank!A:B,2,FALSE) -> 24 | B65: 25 | D65: HCF_D | E65: HCF | F65: =VLOOKUP(D65,Mapping!C:D,2,FALSE) -> Harvest Canadian Income & Growth Fund | G65: =VLOOKUP($B65,Summary!$A:$X,'Summary-WI'!G$1,FALSE) -> Harvest Canadian Income & Growth Fund | H65: =VLOOKUP($B65,Summary!$A:$X,'Summary-WI'!H$1,FALSE) | I65: =VLOOKUP($B65,Summary!$A:$X,'Summary-WI'!I$1,FALSE) | J65: =VLOOKUP($B65,Summary!$A:$X,'Summary-WI'!J$1,FALSE) | K65: =VLOOKUP($B65,Summary!$A:$X,'Summary-WI'!K$1,FALSE) | L65: =VLOOKUP($B65,Summary!$A:$X,'Summary-WI'!L$1,FALSE) | M65: =VLOOKUP($B65,Summary!$A:$X,'Summary-WI'!M$1,FALSE) | N65: =VLOOKUP($B65,Summary!$A:$X,'Summary-WI'!N$1,FALSE) | ... Y65: =VLOOKUP($B65,Summary!$A:$X,'Summary-WI'!Y$1,FALSE)
A67: =VLOOKUP(E67,Rank!A:B,2,FALSE) -> 25 | B67: 16 | D67: HBB_I | E67: HBB | F67: =VLOOKUP(D67,Mapping!C:D,2,FALSE) -> Harvest Banks & Buildings Income Fund | G67: =VLOOKUP($B67,Summary!$A:$X,'Summary-WI'!G$1,FALSE) -> Harvest Energy Leaders Plus Income ETF | H67: =VLOOKUP($B67,Summary!$A:$X,'Summary-WI'!H$1,FALSE) -> 0.093785781 | I67: =VLOOKUP($B67,Summary!$A:$X,'Summary-WI'!I$1,FALSE) -> 0.12866759 | J67: =VLOOKUP($B67,Summary!$A:$X,'Summary-WI'!J$1,FALSE) -> 0.16994772 | K67: =VLOOKUP($B67,Summary!$A:$X,'Summary-WI'!K$1,FALSE) -> 0.093785781 | L67: =VLOOKUP($B67,Summary!$A:$X,'Summary-WI'!L$1,FALSE) -> 0.20507303 | M67: =VLOOKUP($B67,Summary!$A:$X,'Summary-WI'!M$1,FALSE) -> 0.093110684 | N67: =VLOOKUP($B67,Summary!$A:$X,'Summary-WI'!N$1,FALSE) -> 0.058172842 | ... Y67: =VLOOKUP($B67,Summary!$A:$X,'Summary-WI'!Y$1,FALSE)
A68: =VLOOKUP(E68,Rank!A:B,2,FALSE) -> 25 | B68: 17 | D68: HBB_R | E68: HBB | F68: =VLOOKUP(D68,Mapping!C:D,2,FALSE) -> Harvest Banks & Buildings Income Fund | G68: =VLOOKUP($B68,Summary!$A:$X,'Summary-WI'!G$1,FALSE) -> Harvest Banks & Buildings Income Fund | H68: =VLOOKUP($B68,Summary!$A:$X,'Summary-WI'!H$1,FALSE) | I68: =VLOOKUP($B68,Summary!$A:$X,'Summary-WI'!I$1,FALSE) | J68: =VLOOKUP($B68,Summary!$A:$X,'Summary-WI'!J$1,FALSE) | K68: =VLOOKUP($B68,Summary!$A:$X,'Summary-WI'!K$1,FALSE) | L68: =VLOOKUP($B68,Summary!$A:$X,'Summary-WI'!L$1,FALSE) | M68: =VLOOKUP($B68,Summary!$A:$X,'Summary-WI'!M$1,FALSE) | N68: =VLOOKUP($B68,Summary!$A:$X,'Summary-WI'!N$1,FALSE) | ... Y68: =VLOOKUP($B68,Summary!$A:$X,'Summary-WI'!Y$1,FALSE)
A69: =VLOOKUP(E69,Rank!A:B,2,FALSE) -> 25 | B69: 18 | D69: HBB_A | E69: HBB | F69: =VLOOKUP(D69,Mapping!C:D,2,FALSE) -> Harvest Banks & Buildings Income Fund | G69: =VLOOKUP($B69,Summary!$A:$X,'Summary-WI'!G$1,FALSE) -> Harvest Banks & Buildings Income Fund | H69: =VLOOKUP($B69,Summary!$A:$X,'Summary-WI'!H$1,FALSE) | I69: =VLOOKUP($B69,Summary!$A:$X,'Summary-WI'!I$1,FALSE) | J69: =VLOOKUP($B69,Summary!$A:$X,'Summary-WI'!J$1,FALSE) | K69: =VLOOKUP($B69,Summary!$A:$X,'Summary-WI'!K$1,FALSE) | L69: =VLOOKUP($B69,Summary!$A:$X,'Summary-WI'!L$1,FALSE) | M69: =VLOOKUP($B69,Summary!$A:$X,'Summary-WI'!M$1,FALSE) | N69: =VLOOKUP($B69,Summary!$A:$X,'Summary-WI'!N$1,FALSE) | ... Y69: =VLOOKUP($B69,Summary!$A:$X,'Summary-WI'!Y$1,FALSE)
A70: =VLOOKUP(E70,Rank!A:B,2,FALSE) -> 25 | B70: 19 | D70: HBB_F | E70: HBB | F70: =VLOOKUP(D70,Mapping!C:D,2,FALSE) -> Harvest Banks & Buildings Income Fund | G70: =VLOOKUP($B70,Summary!$A:$X,'Summary-WI'!G$1,FALSE) -> Harvest Banks & Buildings Income Fund | H70: =VLOOKUP($B70,Summary!$A:$X,'Summary-WI'!H$1,FALSE) | I70: =VLOOKUP($B70,Summary!$A:$X,'Summary-WI'!I$1,FALSE) | J70: =VLOOKUP($B70,Summary!$A:$X,'Summary-WI'!J$1,FALSE) | K70: =VLOOKUP($B70,Summary!$A:$X,'Summary-WI'!K$1,FALSE) | L70: =VLOOKUP($B70,Summary!$A:$X,'Summary-WI'!L$1,FALSE) | M70: =VLOOKUP($B70,Summary!$A:$X,'Summary-WI'!M$1,FALSE) | N70: =VLOOKUP($B70,Summary!$A:$X,'Summary-WI'!N$1,FALSE) | ... Y70: =VLOOKUP($B70,Summary!$A:$X,'Summary-WI'!Y$1,FALSE)
A71: =VLOOKUP(E71,Rank!A:B,2,FALSE) -> 25 | B71: 20 | D71: HBB_D | E71: HBB | F71: =VLOOKUP(D71,Mapping!C:D,2,FALSE) -> Harvest Banks & Buildings Income Fund | G71: =VLOOKUP($B71,Summary!$A:$X,'Summary-WI'!G$1,FALSE) -> Harvest Banks & Buildings Income Fund | H71: =VLOOKUP($B71,Summary!$A:$X,'Summary-WI'!H$1,FALSE) | I71: =VLOOKUP($B71,Summary!$A:$X,'Summary-WI'!I$1,FALSE) | J71: =VLOOKUP($B71,Summary!$A:$X,'Summary-WI'!J$1,FALSE) | K71: =VLOOKUP($B71,Summary!$A:$X,'Summary-WI'!K$1,FALSE) | L71: =VLOOKUP($B71,Summary!$A:$X,'Summary-WI'!L$1,FALSE) | M71: =VLOOKUP($B71,Summary!$A:$X,'Summary-WI'!M$1,FALSE) | N71: =VLOOKUP($B71,Summary!$A:$X,'Summary-WI'!N$1,FALSE) | ... Y71: =VLOOKUP($B71,Summary!$A:$X,'Summary-WI'!Y$1,FALSE)
A73: =VLOOKUP(E73,Rank!A:B,2,FALSE) -> 30 | B73: 7 | D73: HRA2 | E73: HBFE | F73: =VLOOKUP(D73,Mapping!C:D,2,FALSE) -> Harvest Brand Leaders Enhanced Income ETF | G73: =VLOOKUP($B73,Summary!$A:$X,'Summary-WI'!G$1,FALSE) -> Harvest Brand Leaders Enhanced Income ETF | H73: =VLOOKUP($B73,Summary!$A:$X,'Summary-WI'!H$1,FALSE) | I73: =VLOOKUP($B73,Summary!$A:$X,'Summary-WI'!I$1,FALSE) | J73: =VLOOKUP($B73,Summary!$A:$X,'Summary-WI'!J$1,FALSE) | K73: =VLOOKUP($B73,Summary!$A:$X,'Summary-WI'!K$1,FALSE) | L73: =VLOOKUP($B73,Summary!$A:$X,'Summary-WI'!L$1,FALSE) | M73: =VLOOKUP($B73,Summary!$A:$X,'Summary-WI'!M$1,FALSE) | N73: =VLOOKUP($B73,Summary!$A:$X,'Summary-WI'!N$1,FALSE) | ... Y73: =VLOOKUP($B73,Summary!$A:$X,'Summary-WI'!Y$1,FALSE)
A75: =VLOOKUP(E75,Rank!A:B,2,FALSE) -> 31 | B75: 10 | D75: HRA5 | E75: HLFE | F75: =VLOOKUP(D75,Mapping!C:D,2,FALSE) -> Harvest Canadian Equity Enhanced Income Leaders ETF | G75: =VLOOKUP($B75,Summary!$A:$X,'Summary-WI'!G$1,FALSE) -> Harvest Canadian Equity Enhanced Income Leaders ETF | H75: =VLOOKUP($B75,Summary!$A:$X,'Summary-WI'!H$1,FALSE) | I75: =VLOOKUP($B75,Summary!$A:$X,'Summary-WI'!I$1,FALSE) | J75: =VLOOKUP($B75,Summary!$A:$X,'Summary-WI'!J$1,FALSE) | K75: =VLOOKUP($B75,Summary!$A:$X,'Summary-WI'!K$1,FALSE) | L75: =VLOOKUP($B75,Summary!$A:$X,'Summary-WI'!L$1,FALSE) | M75: =VLOOKUP($B75,Summary!$A:$X,'Summary-WI'!M$1,FALSE) | N75: =VLOOKUP($B75,Summary!$A:$X,'Summary-WI'!N$1,FALSE) | ... Y75: =VLOOKUP($B75,Summary!$A:$X,'Summary-WI'!Y$1,FALSE)
... A80: =VLOOKUP(E80,Rank!A:B,2,FALSE) -> 11 | B80: 52 | D80: HIND | E80: HIND | F80: =VLOOKUP(D80,Mapping!C:D,2,FALSE) -> Harvest Industrial Leaders Income ETF | G80: =VLOOKUP($B80,Summary!$A:$X,'Summary-WI'!G$1,FALSE) -> Harvest Balanced Income & Growth Enhanced ETF | H80: =VLOOKUP($B80,Summary!$A:$X,'Summary-WI'!H$1,FALSE) -> 0.002614495 | I80: =VLOOKUP($B80,Summary!$A:$X,'Summary-WI'!I$1,FALSE) -> 0.018054439 | J80: =VLOOKUP($B80,Summary!$A:$X,'Summary-WI'!J$1,FALSE) -> 0.071722246 | K80: =VLOOKUP($B80,Summary!$A:$X,'Summary-WI'!K$1,FALSE) -> 0.002614495 | L80: =VLOOKUP($B80,Summary!$A:$X,'Summary-WI'!L$1,FALSE) -> 0.088394264 | M80: =VLOOKUP($B80,Summary!$A:$X,'Summary-WI'!M$1,FALSE) | N80: =VLOOKUP($B80,Summary!$A:$X,'Summary-WI'!N$1,FALSE) | ... Y80: =VLOOKUP($B80,Summary!$A:$X,'Summary-WI'!Y$1,FALSE)

Sheet Rank
A1: HHL | B1: 1
A2: HBF | B2: =B1+1 -> 2
A3: HTA | B3: =B2+1 -> 3
A4: HGR | B4: =B3+1 -> 4
A5: HUTL | B5: =B4+1 -> 5
A6: HPF | B6: =B5+1 -> 6
A7: HUBL | B7: =B6+1 -> 7
A8: HLIF | B8: =B7+1 -> 8
A9: TRVI | B9: =B8+1 -> 9
A10: HRIF | B10: =B9+1 -> 10
A11: HIND | B11: =B10+1 -> 11
A12: HPYT | B12: =B11+1 -> 12
A13: HPYM | B13: =B12+1 -> 13
... A31: HLFE | B31: =B30+1 -> 31

Sheet Summary
I1: YTD | J1: 1 | K1: =J1+1 -> 2 | L1: =K1+1 -> 3 | M1: =L1+1 -> 4 | N1: =M1+1 -> 5 | O1: =N1+1 -> 6 | P1: =O1+1 -> 7 | Q1: =P1+1 -> 8 | R1: =Q1+1 -> 9 | ... X1: =W1+1 -> 15
A2: Columns | B2: Helper column for Benchmark | C2: 2026 | D2: Tickers | E2: Fund Name | F2: 1 | G2: 3 | H2: 6 | I2: 1 | J2: 12 | K2: =J2+12 -> 24 | L2: =K2+12 -> 36 | M2: =L2+12 -> 48 | N2: =M2+12 -> 60 | O2: =N2+12 -> 72 | P2: =O2+12 -> 84 | Q2: =P2+12 -> 96 | R2: =Q2+12 -> 108 | ... X2: =W2+12 -> 180 | Y2: Since Inception Return Cumulative | Z2: Since Inception Return Annualized
A3: 3 | C3: HR21_A | D3: HTA | E3: Harvest Tech Achievers Growth & Income ETF | F3: =IFERROR(VLOOKUP(F$2,'R.WEALTH-Cummulative'!$A:$FG,$A3,FALSE)-1,"") -> 0.0039345121 | G3: =IFERROR(VLOOKUP(G$2,'R.WEALTH-Cummulative'!$A:$FG,$A3,FALSE)-1,"") -> -0.014066587 | H3: =IFERROR(VLOOKUP(H$2,'R.WEALTH-Cummulative'!$A:$FG,$A3,FALSE)-1,"") -> 0.070391771 | I3: =IFERROR(VLOOKUP(I$2,'R.WEALTH-Cummulative'!$A:$FG,$A3,FALSE)-1,"") -> 0.0039345121 | J3: =IFERROR(VLOOKUP(J$2,'R.WEALTH-Cummulative'!$A:$FG,$A3,FALSE)-1,"") -> 0.10909706 | K3: =IFERROR((VLOOKUP(K$2,'R.WEALTH-Cummulative'!$A:$FG,$A3,FALSE)^(1/(K$2/12)))-1,"") -> 0.15546626 | L3: =IFERROR((VLOOKUP(L$2,'R.WEALTH-Cummulative'!$A:$FG,$A3,FALSE)^(1/(L$2/12)))-1,"") -> 0.24714413 | M3: =IFERROR((VLOOKUP(M$2,'R.WEALTH-Cummulative'!$A:$FG,$A3,FALSE)^(1/(M$2/12)))-1,"") -> 0.12274083 | N3: =IFERROR((VLOOKUP(N$2,'R.WEALTH-Cummulative'!$A:$FG,$A3,FALSE)^(1/(N$2/12)))-1,"") -> 0.1564718 | O3: =IFERROR((VLOOKUP(O$2,'R.WEALTH-Cummulative'!$A:$FG,$A3,FALSE)^(1/(O$2/12)))-1,"") -> 0.173751 | P3: =IFERROR((VLOOKUP(P$2,'R.WEALTH-Cummulative'!$A:$FG,$A3,FALSE)^(1/(P$2/12)))-1,"") -> 0.1885161 | Q3: =IFERROR((VLOOKUP(Q$2,'R.WEALTH-Cummulative'!$A:$FG,$A3,FALSE)^(1/(Q$2/12)))-1,"") -> 0.16206241 | R3: =IFERROR((VLOOKUP(R$2,'R.WEALTH-Cummulative'!$A:$FG,$A3,FALSE)^(1/(R$2/12)))-1,"") -> 0.18055081 | ... X3: =IFERROR((VLOOKUP(X$2,'R.WEALTH-Cummulative'!$A:$FG,$A3,FALSE)^(1/(X$2/12)))-1,"") | Y3: =VLOOKUP(Y$2,'Since Inception Returns'!$B:$AAB,Summary!A3-1,FALSE) -> 3.6241408 | Z3: =VLOOKUP(Z$2,'Since Inception Returns'!$B:$AAB,Summary!A3-1,FALSE) -> 0.15416579
B4: 3 | C4: HR21_A | D4: HTA | E4: Solactive US Large & Mid Cap Technology Index NTR | F4: =IFERROR(VLOOKUP(F$2,'R.WEALTH-Cummulative (BM)'!$A:$FH,$B4,FALSE)-1,"") -> -0.0092134294 | G4: =IFERROR(VLOOKUP(G$2,'R.WEALTH-Cummulative (BM)'!$A:$FH,$B4,FALSE)-1,"") -> -0.040381701 | H4: =IFERROR(VLOOKUP(H$2,'R.WEALTH-Cummulative (BM)'!$A:$FH,$B4,FALSE)-1,"") -> 0.081863367 | I4: =IFERROR(VLOOKUP(I$2,'R.WEALTH-Cummulative (BM)'!$A:$FH,$B4,FALSE)-1,"") -> -0.0092134294 | J4: =IFERROR(VLOOKUP(J$2,'R.WEALTH-Cummulative (BM)'!$A:$FH,$B4,FALSE)-1,"") -> 0.22829774 | K4: =IFERROR((VLOOKUP(K$2,'R.WEALTH-Cummulative (BM)'!$A:$FH,$B4,FALSE)^(1/(K$2/12)))-1,"") -> 0.27251111 | L4: =IFERROR((VLOOKUP(L$2,'R.WEALTH-Cummulative (BM)'!$A:$FH,$B4,FALSE)^(1/(L$2/12)))-1,"") -> 0.33824538 | M4: =IFERROR((VLOOKUP(M$2,'R.WEALTH-Cummulative (BM)'!$A:$FH,$B4,FALSE)^(1/(M$2/12)))-1,"") -> 0.17552657 | N4: =IFERROR((VLOOKUP(N$2,'R.WEALTH-Cummulative (BM)'!$A:$FH,$B4,FALSE)^(1/(N$2/12)))-1,"") -> 0.18267576 | O4: =IFERROR((VLOOKUP(O$2,'R.WEALTH-Cummulative (BM)'!$A:$FH,$B4,FALSE)^(1/(O$2/12)))-1,"") -> 0.21648671 | P4: =IFERROR((VLOOKUP(P$2,'R.WEALTH-Cummulative (BM)'!$A:$FH,$B4,FALSE)^(1/(P$2/12)))-1,"") -> 0.2402506 | Q4: =IFERROR((VLOOKUP(Q$2,'R.WEALTH-Cummulative (BM)'!$A:$FH,$B4,FALSE)^(1/(Q$2/12)))-1,"") -> 0.2095893 | R4: =IFERROR((VLOOKUP(R$2,'R.WEALTH-Cummulative (BM)'!$A:$FH,$B4,FALSE)^(1/(R$2/12)))-1,"") -> 0.23284223 | ... X4: =IFERROR((VLOOKUP(X$2,'R.WEALTH-Cummulative (BM)'!$A:$FH,$B4,FALSE)^(1/(X$2/12)))-1,"") | Y4: =VLOOKUP(Y$2,'Since Inception (BM)'!$B:$AAC,Summary!B4-1,FALSE) -> 6.8725103 | Z4: =VLOOKUP(Z$2,'Since Inception (BM)'!$B:$AAC,Summary!B4-1,FALSE) -> 0.21312315
A5: 4 | C5: HR21_B | D5: HTA.B | E5: Harvest Tech Achievers Growth & Income ETF | F5: =IFERROR(VLOOKUP(F$2,'R.WEALTH-Cummulative'!$A:$FG,$A5,FALSE)-1,"") -> -0.0022723097 | G5: =IFERROR(VLOOKUP(G$2,'R.WEALTH-Cummulative'!$A:$FG,$A5,FALSE)-1,"") -> -0.037067326 | H5: =IFERROR(VLOOKUP(H$2,'R.WEALTH-Cummulative'!$A:$FG,$A5,FALSE)-1,"") -> 0.063093209 | I5: =IFERROR(VLOOKUP(I$2,'R.WEALTH-Cummulative'!$A:$FG,$A5,FALSE)-1,"") -> -0.0022723097 | J5: =IFERROR(VLOOKUP(J$2,'R.WEALTH-Cummulative'!$A:$FG,$A5,FALSE)-1,"") -> 0.061444906 | K5: =IFERROR((VLOOKUP(K$2,'R.WEALTH-Cummulative'!$A:$FG,$A5,FALSE)^(1/(K$2/12)))-1,"") -> 0.18054652 | L5: =IFERROR((VLOOKUP(L$2,'R.WEALTH-Cummulative'!$A:$FG,$A5,FALSE)^(1/(L$2/12)))-1,"") -> 0.27238535 | M5: =IFERROR((VLOOKUP(M$2,'R.WEALTH-Cummulative'!$A:$FG,$A5,FALSE)^(1/(M$2/12)))-1,"") -> 0.15736247 | N5: =IFERROR((VLOOKUP(N$2,'R.WEALTH-Cummulative'!$A:$FG,$A5,FALSE)^(1/(N$2/12)))-1,"") -> 0.18413194 | O5: =IFERROR((VLOOKUP(O$2,'R.WEALTH-Cummulative'!$A:$FG,$A5,FALSE)^(1/(O$2/12)))-1,"") | P5: =IFERROR((VLOOKUP(P$2,'R.WEALTH-Cummulative'!$A:$FG,$A5,FALSE)^(1/(P$2/12)))-1,"") | Q5: =IFERROR((VLOOKUP(Q$2,'R.WEALTH-Cummulative'!$A:$FG,$A5,FALSE)^(1/(Q$2/12)))-1,"") | R5: =IFERROR((VLOOKUP(R$2,'R.WEALTH-Cummulative'!$A:$FG,$A5,FALSE)^(1/(R$2/12)))-1,"") | ... X5: =IFERROR((VLOOKUP(X$2,'R.WEALTH-Cummulative'!$A:$FG,$A5,FALSE)^(1/(X$2/12)))-1,"") | Y5: =VLOOKUP(Y$2,'Since Inception Returns'!$B:$AAB,Summary!A5-1,FALSE) -> 2.0543982 | Z5: =VLOOKUP(Z$2,'Since Inception Returns'!$B:$AAB,Summary!A5-1,FALSE) -> 0.20874123
B6: 4 | C6: HR21_B | D6: HTA.B | E6: Solactive US Large & Mid Cap Technology Index NTR | F6: =IFERROR(VLOOKUP(F$2,'R.WEALTH-Cummulative (BM)'!$A:$FH,$B6,FALSE)-1,"") -> -0.0092134294 | G6: =IFERROR(VLOOKUP(G$2,'R.WEALTH-Cummulative (BM)'!$A:$FH,$B6,FALSE)-1,"") -> -0.040381701 | H6: =IFERROR(VLOOKUP(H$2,'R.WEALTH-Cummulative (BM)'!$A:$FH,$B6,FALSE)-1,"") -> 0.081863367 | I6: =IFERROR(VLOOKUP(I$2,'R.WEALTH-Cummulative (BM)'!$A:$FH,$B6,FALSE)-1,"") -> -0.0092134294 | J6: =IFERROR(VLOOKUP(J$2,'R.WEALTH-Cummulative (BM)'!$A:$FH,$B6,FALSE)-1,"") -> 0.22829774 | K6: =IFERROR((VLOOKUP(K$2,'R.WEALTH-Cummulative (BM)'!$A:$FH,$B6,FALSE)^(1/(K$2/12)))-1,"") -> 0.27251111 | L6: =IFERROR((VLOOKUP(L$2,'R.WEALTH-Cummulative (BM)'!$A:$FH,$B6,FALSE)^(1/(L$2/12)))-1,"") -> 0.33824538 | M6: =IFERROR((VLOOKUP(M$2,'R.WEALTH-Cummulative (BM)'!$A:$FH,$B6,FALSE)^(1/(M$2/12)))-1,"") -> 0.17552657 | N6: =IFERROR((VLOOKUP(N$2,'R.WEALTH-Cummulative (BM)'!$A:$FH,$B6,FALSE)^(1/(N$2/12)))-1,"") -> 0.18267576 | O6: =IFERROR((VLOOKUP(O$2,'R.WEALTH-Cummulative (BM)'!$A:$FH,$B6,FALSE)^(1/(O$2/12)))-1,"") | P6: =IFERROR((VLOOKUP(P$2,'R.WEALTH-Cummulative (BM)'!$A:$FH,$B6,FALSE)^(1/(P$2/12)))-1,"") | Q6: =IFERROR((VLOOKUP(Q$2,'R.WEALTH-Cummulative (BM)'!$A:$FH,$B6,FALSE)^(1/(Q$2/12)))-1,"") | R6: =IFERROR((VLOOKUP(R$2,'R.WEALTH-Cummulative (BM)'!$A:$FH,$B6,FALSE)^(1/(R$2/12)))-1,"") | ... X6: =IFERROR((VLOOKUP(X$2,'R.WEALTH-Cummulative (BM)'!$A:$FH,$B6,FALSE)^(1/(X$2/12)))-1,"") | Y6: =VLOOKUP(Y$2,'Since Inception (BM)'!$B:$AAC,Summary!B6-1,FALSE) -> 2.539619 | Z6: =VLOOKUP(Z$2,'Since Inception (BM)'!$B:$AAC,Summary!B6-1,FALSE) -> 0.23938104
A7: 5 | C7: HR21_U | D7: HTA.U | E7: Harvest Tech Achievers Growth & Income ETF | F7: =IFERROR(VLOOKUP(F$2,'R.WEALTH-Cummulative'!$A:$FG,$A7,FALSE)-1,"") -> 0.0057282875 | G7: =IFERROR(VLOOKUP(G$2,'R.WEALTH-Cummulative'!$A:$FG,$A7,FALSE)-1,"") -> -0.0081060304 | H7: =IFERROR(VLOOKUP(H$2,'R.WEALTH-Cummulative'!$A:$FG,$A7,FALSE)-1,"") -> 0.081823556 | I7: =IFERROR(VLOOKUP(I$2,'R.WEALTH-Cummulative'!$A:$FG,$A7,FALSE)-1,"") -> 0.0057282875 | J7: =IFERROR(VLOOKUP(J$2,'R.WEALTH-Cummulative'!$A:$FG,$A7,FALSE)-1,"") -> 0.13297781 | K7: =IFERROR((VLOOKUP(K$2,'R.WEALTH-Cummulative'!$A:$FG,$A7,FALSE)^(1/(K$2/12)))-1,"") -> 0.17310314 | L7: =IFERROR((VLOOKUP(L$2,'R.WEALTH-Cummulative'!$A:$FG,$A7,FALSE)^(1/(L$2/12)))-1,"") -> 0.26269149 | M7: =IFERROR((VLOOKUP(M$2,'R.WEALTH-Cummulative'!$A:$FG,$A7,FALSE)^(1/(M$2/12)))-1,"") -> 0.13764182 | N7: =IFERROR((VLOOKUP(N$2,'R.WEALTH-Cummulative'!$A:$FG,$A7,FALSE)^(1/(N$2/12)))-1,"") -> 0.16936137 | O7: =IFERROR((VLOOKUP(O$2,'R.WEALTH-Cummulative'!$A:$FG,$A7,FALSE)^(1/(O$2/12)))-1,"") -> 0.18965347 | P7: =IFERROR((VLOOKUP(P$2,'R.WEALTH-Cummulative'!$A:$FG,$A7,FALSE)^(1/(P$2/12)))-1,"") -> 0.2036496 | Q7: =IFERROR((VLOOKUP(Q$2,'R.WEALTH-Cummulative'!$A:$FG,$A7,FALSE)^(1/(Q$2/12)))-1,"") -> 0.1759251 | R7: =IFERROR((VLOOKUP(R$2,'R.WEALTH-Cummulative'!$A:$FG,$A7,FALSE)^(1/(R$2/12)))-1,"") | ... X7: =IFERROR((VLOOKUP(X$2,'R.WEALTH-Cummulative'!$A:$FG,$A7,FALSE)^(1/(X$2/12)))-1,"") | Y7: =VLOOKUP(Y$2,'Since Inception Returns'!$B:$AAB,Summary!A7-1,FALSE) -> 3.3673596 | Z7: =VLOOKUP(Z$2,'Since Inception Returns'!$B:$AAB,Summary!A7-1,FALSE) -> 0.18665379
B8: 5 | C8: HR21_U | D8: HTA.U | E8: Solactive US Large & Mid Cap Technology Index NTR | F8: =IFERROR(VLOOKUP(F$2,'R.WEALTH-Cummulative (BM)'!$A:$FH,$B8,FALSE)-1,"") -> -0.0092134294 | G8: =IFERROR(VLOOKUP(G$2,'R.WEALTH-Cummulative (BM)'!$A:$FH,$B8,FALSE)-1,"") -> -0.040381701 | H8: =IFERROR(VLOOKUP(H$2,'R.WEALTH-Cummulative (BM)'!$A:$FH,$B8,FALSE)-1,"") -> 0.081863367 | I8: =IFERROR(VLOOKUP(I$2,'R.WEALTH-Cummulative (BM)'!$A:$FH,$B8,FALSE)-1,"") -> -0.0092134294 | J8: =IFERROR(VLOOKUP(J$2,'R.WEALTH-Cummulative (BM)'!$A:$FH,$B8,FALSE)-1,"") -> 0.22829774 | K8: =IFERROR((VLOOKUP(K$2,'R.WEALTH-Cummulative (BM)'!$A:$FH,$B8,FALSE)^(1/(K$2/12)))-1,"") -> 0.27251111 | L8: =IFERROR((VLOOKUP(L$2,'R.WEALTH-Cummulative (BM)'!$A:$FH,$B8,FALSE)^(1/(L$2/12)))-1,"") -> 0.33824538 | M8: =IFERROR((VLOOKUP(M$2,'R.WEALTH-Cummulative (BM)'!$A:$FH,$B8,FALSE)^(1/(M$2/12)))-1,"") -> 0.17552657 | N8: =IFERROR((VLOOKUP(N$2,'R.WEALTH-Cummulative (BM)'!$A:$FH,$B8,FALSE)^(1/(N$2/12)))-1,"") -> 0.18267576 | O8: =IFERROR((VLOOKUP(O$2,'R.WEALTH-Cummulative (BM)'!$A:$FH,$B8,FALSE)^(1/(O$2/12)))-1,"") -> 0.21648671 | P8: =IFERROR((VLOOKUP(P$2,'R.WEALTH-Cummulative (BM)'!$A:$FH,$B8,FALSE)^(1/(P$2/12)))-1,"") -> 0.2402506 | Q8: =IFERROR((VLOOKUP(Q$2,'R.WEALTH-Cummulative (BM)'!$A:$FH,$B8,FALSE)^(1/(Q$2/12)))-1,"") -> 0.2095893 | R8: =IFERROR((VLOOKUP(R$2,'R.WEALTH-Cummulative (BM)'!$A:$FH,$B8,FALSE)^(1/(R$2/12)))-1,"") | ... X8: =IFERROR((VLOOKUP(X$2,'R.WEALTH-Cummulative (BM)'!$A:$FH,$B8,FALSE)^(1/(X$2/12)))-1,"") | Y8: =VLOOKUP(Y$2,'Since Inception (BM)'!$B:$AAC,Summary!B8-1,FALSE) -> 4.7405742 | Z8: =VLOOKUP(Z$2,'Since Inception (BM)'!$B:$AAC,Summary!B8-1,FALSE) -> 0.22492169
A9: 6 | C9: HRA1 | D9: HHLE | E9: Harvest Healthcare Leaders Enhanced Income ETF | F9: =IFERROR(VLOOKUP(F$2,'R.WEALTH-Cummulative'!$A:$FG,$A9,FALSE)-1,"") -> -0.0056687754 | G9: =IFERROR(VLOOKUP(G$2,'R.WEALTH-Cummulative'!$A:$FG,$A9,FALSE)-1,"") -> 0.059216365 | H9: =IFERROR(VLOOKUP(H$2,'R.WEALTH-Cummulative'!$A:$FG,$A9,FALSE)-1,"") -> 0.1865493 | I9: =IFERROR(VLOOKUP(I$2,'R.WEALTH-Cummulative'!$A:$FG,$A9,FALSE)-1,"") -> -0.0056687754 | J9: =IFERROR(VLOOKUP(J$2,'R.WEALTH-Cummulative'!$A:$FG,$A9,FALSE)-1,"") -> 0.023311142 | K9: =IFERROR((VLOOKUP(K$2,'R.WEALTH-Cummulative'!$A:$FG,$A9,FALSE)^(1/(K$2/12)))-1,"") -> 0.04942619 | L9: =IFERROR((VLOOKUP(L$2,'R.WEALTH-Cummulative'!$A:$FG,$A9,FALSE)^(1/(L$2/12)))-1,"") -> 0.074077154 | M9: =IFERROR((VLOOKUP(M$2,'R.WEALTH-Cummulative'!$A:$FG,$A9,FALSE)^(1/(M$2/12)))-1,"") | N9: =IFERROR((VLOOKUP(N$2,'R.WEALTH-Cummulative'!$A:$FG,$A9,FALSE)^(1/(N$2/12)))-1,"") | O9: =IFERROR((VLOOKUP(O$2,'R.WEALTH-Cummulative'!$A:$FG,$A9,FALSE)^(1/(O$2/12)))-1,"") | P9: =IFERROR((VLOOKUP(P$2,'R.WEALTH-Cummulative'!$A:$FG,$A9,FALSE)^(1/(P$2/12)))-1,"") | Q9: =IFERROR((VLOOKUP(Q$2,'R.WEALTH-Cummulative'!$A:$FG,$A9,FALSE)^(1/(Q$2/12)))-1,"") | R9: =IFERROR((VLOOKUP(R$2,'R.WEALTH-Cummulative'!$A:$FG,$A9,FALSE)^(1/(R$2/12)))-1,"") | ... X9: =IFERROR((VLOOKUP(X$2,'R.WEALTH-Cummulative'!$A:$FG,$A9,FALSE)^(1/(X$2/12)))-1,"") | Y9: =VLOOKUP(Y$2,'Since Inception Returns'!$B:$AAB,Summary!A9-1,FALSE) -> 0.31530969 | Z9: =VLOOKUP(Z$2,'Since Inception Returns'!$B:$AAB,Summary!A9-1,FALSE) -> 0.087145106
B10: 6 | C10: HRA1 | D10: HHLE | E10: MSCI World Health Care Net Total Return USD Index | F10: =IFERROR(VLOOKUP(F$2,'R.WEALTH-Cummulative (BM)'!$A:$FH,$B10,FALSE)-1,"") -> 0.010953014 | G10: =IFERROR(VLOOKUP(G$2,'R.WEALTH-Cummulative (BM)'!$A:$FH,$B10,FALSE)-1,"") -> 0.084428037 | H10: =IFERROR(VLOOKUP(H$2,'R.WEALTH-Cummulative (BM)'!$A:$FH,$B10,FALSE)-1,"") -> 0.18692932 | I10: =IFERROR(VLOOKUP(I$2,'R.WEALTH-Cummulative (BM)'!$A:$FH,$B10,FALSE)-1,"") -> 0.010953014 | J10: =IFERROR(VLOOKUP(J$2,'R.WEALTH-Cummulative (BM)'!$A:$FH,$B10,FALSE)-1,"") -> 0.091091301 | K10: =IFERROR((VLOOKUP(K$2,'R.WEALTH-Cummulative (BM)'!$A:$FH,$B10,FALSE)^(1/(K$2/12)))-1,"") -> 0.069243604 | L10: =IFERROR((VLOOKUP(L$2,'R.WEALTH-Cummulative (BM)'!$A:$FH,$B10,FALSE)^(1/(L$2/12)))-1,"") -> 0.0702882 | M10: =IFERROR((VLOOKUP(M$2,'R.WEALTH-Cummulative (BM)'!$A:$FH,$B10,FALSE)^(1/(M$2/12)))-1,"") | N10: =IFERROR((VLOOKUP(N$2,'R.WEALTH-Cummulative (BM)'!$A:$FH,$B10,FALSE)^(1/(N$2/12)))-1,"") | O10: =IFERROR((VLOOKUP(O$2,'R.WEALTH-Cummulative (BM)'!$A:$FH,$B10,FALSE)^(1/(O$2/12)))-1,"") | P10: =IFERROR((VLOOKUP(P$2,'R.WEALTH-Cummulative (BM)'!$A:$FH,$B10,FALSE)^(1/(P$2/12)))-1,"") | Q10: =IFERROR((VLOOKUP(Q$2,'R.WEALTH-Cummulative (BM)'!$A:$FH,$B10,FALSE)^(1/(Q$2/12)))-1,"") | R10: =IFERROR((VLOOKUP(R$2,'R.WEALTH-Cummulative (BM)'!$A:$FH,$B10,FALSE)^(1/(R$2/12)))-1,"") | ... X10: =IFERROR((VLOOKUP(X$2,'R.WEALTH-Cummulative (BM)'!$A:$FH,$B10,FALSE)^(1/(X$2/12)))-1,"") | Y10: =VLOOKUP(Y$2,'Since Inception (BM)'!$B:$AAC,Summary!B10-1,FALSE) -> 0.35399402 | Z10: =VLOOKUP(Z$2,'Since Inception (BM)'!$B:$AAC,Summary!B10-1,FALSE) -> 0.096794795
A11: 7 | C11: #N/A | D11: #N/A | E11: Harvest Brand Leaders Enhanced Income ETF | F11: =IFERROR(VLOOKUP(F$2,'R.WEALTH-Cummulative'!$A:$FG,$A11,FALSE)-1,"") | G11: =IFERROR(VLOOKUP(G$2,'R.WEALTH-Cummulative'!$A:$FG,$A11,FALSE)-1,"") | H11: =IFERROR(VLOOKUP(H$2,'R.WEALTH-Cummulative'!$A:$FG,$A11,FALSE)-1,"") | I11: =IFERROR(VLOOKUP(I$2,'R.WEALTH-Cummulative'!$A:$FG,$A11,FALSE)-1,"") | J11: =IFERROR(VLOOKUP(J$2,'R.WEALTH-Cummulative'!$A:$FG,$A11,FALSE)-1,"") | K11: =IFERROR((VLOOKUP(K$2,'R.WEALTH-Cummulative'!$A:$FG,$A11,FALSE)^(1/(K$2/12)))-1,"") | L11: =IFERROR((VLOOKUP(L$2,'R.WEALTH-Cummulative'!$A:$FG,$A11,FALSE)^(1/(L$2/12)))-1,"") | M11: =IFERROR((VLOOKUP(M$2,'R.WEALTH-Cummulative'!$A:$FG,$A11,FALSE)^(1/(M$2/12)))-1,"") | N11: =IFERROR((VLOOKUP(N$2,'R.WEALTH-Cummulative'!$A:$FG,$A11,FALSE)^(1/(N$2/12)))-1,"") | O11: =IFERROR((VLOOKUP(O$2,'R.WEALTH-Cummulative'!$A:$FG,$A11,FALSE)^(1/(O$2/12)))-1,"") | P11: =IFERROR((VLOOKUP(P$2,'R.WEALTH-Cummulative'!$A:$FG,$A11,FALSE)^(1/(P$2/12)))-1,"") | Q11: =IFERROR((VLOOKUP(Q$2,'R.WEALTH-Cummulative'!$A:$FG,$A11,FALSE)^(1/(Q$2/12)))-1,"") | R11: =IFERROR((VLOOKUP(R$2,'R.WEALTH-Cummulative'!$A:$FG,$A11,FALSE)^(1/(R$2/12)))-1,"") | ... X11: =IFERROR((VLOOKUP(X$2,'R.WEALTH-Cummulative'!$A:$FG,$A11,FALSE)^(1/(X$2/12)))-1,"") | Y11: =VLOOKUP(Y$2,'Since Inception Returns'!$B:$AAB,Summary!A11-1,FALSE) -> 0.28924112 | Z11: =VLOOKUP(Z$2,'Since Inception Returns'!$B:$AAB,Summary!A11-1,FALSE) -> 0.1494006
A12: 8 | C12: HRA3 | D12: HTAE | E12: Harvest Tech Achievers Enhanced Income ETF | F12: =IFERROR(VLOOKUP(F$2,'R.WEALTH-Cummulative'!$A:$FG,$A12,FALSE)-1,"") -> 0.0031615072 | G12: =IFERROR(VLOOKUP(G$2,'R.WEALTH-Cummulative'!$A:$FG,$A12,FALSE)-1,"") -> -0.024408773 | H12: =IFERROR(VLOOKUP(H$2,'R.WEALTH-Cummulative'!$A:$FG,$A12,FALSE)-1,"") -> 0.082765228 | I12: =IFERROR(VLOOKUP(I$2,'R.WEALTH-Cummulative'!$A:$FG,$A12,FALSE)-1,"") -> 0.0031615072 | J12: =IFERROR(VLOOKUP(J$2,'R.WEALTH-Cummulative'!$A:$FG,$A12,FALSE)-1,"") -> 0.11535956 | K12: =IFERROR((VLOOKUP(K$2,'R.WEALTH-Cummulative'!$A:$FG,$A12,FALSE)^(1/(K$2/12)))-1,"") -> 0.17588542 | L12: =IFERROR((VLOOKUP(L$2,'R.WEALTH-Cummulative'!$A:$FG,$A12,FALSE)^(1/(L$2/12)))-1,"") -> 0.29370095 | M12: =IFERROR((VLOOKUP(M$2,'R.WEALTH-Cummulative'!$A:$FG,$A12,FALSE)^(1/(M$2/12)))-1,"") | N12: =IFERROR((VLOOKUP(N$2,'R.WEALTH-Cummulative'!$A:$FG,$A12,FALSE)^(1/(N$2/12)))-1,"") | O12: =IFERROR((VLOOKUP(O$2,'R.WEALTH-Cummulative'!$A:$FG,$A12,FALSE)^(1/(O$2/12)))-1,"") | P12: =IFERROR((VLOOKUP(P$2,'R.WEALTH-Cummulative'!$A:$FG,$A12,FALSE)^(1/(P$2/12)))-1,"") | Q12: =IFERROR((VLOOKUP(Q$2,'R.WEALTH-Cummulative'!$A:$FG,$A12,FALSE)^(1/(Q$2/12)))-1,"") | R12: =IFERROR((VLOOKUP(R$2,'R.WEALTH-Cummulative'!$A:$FG,$A12,FALSE)^(1/(R$2/12)))-1,"") | ... X12: =IFERROR((VLOOKUP(X$2,'R.WEALTH-Cummulative'!$A:$FG,$A12,FALSE)^(1/(X$2/12)))-1,"") | Y12: =VLOOKUP(Y$2,'Since Inception Returns'!$B:$AAB,Summary!A12-1,FALSE) -> 1.4200677 | Z12: =VLOOKUP(Z$2,'Since Inception Returns'!$B:$AAB,Summary!A12-1,FALSE) -> 0.30922925
B13: 8 | C13: HRA3 | D13: HTAE | E13: Solactive US Large & Mid Cap Technology Index NTR | F13: =IFERROR(VLOOKUP(F$2,'R.WEALTH-Cummulative (BM)'!$A:$FH,$B13,FALSE)-1,"") -> -0.0092134294 | G13: =IFERROR(VLOOKUP(G$2,'R.WEALTH-Cummulative (BM)'!$A:$FH,$B13,FALSE)-1,"") -> -0.040381701 | H13: =IFERROR(VLOOKUP(H$2,'R.WEALTH-Cummulative (BM)'!$A:$FH,$B13,FALSE)-1,"") -> 0.081863367 | I13: =IFERROR(VLOOKUP(I$2,'R.WEALTH-Cummulative (BM)'!$A:$FH,$B13,FALSE)-1,"") -> -0.0092134294 | J13: =IFERROR(VLOOKUP(J$2,'R.WEALTH-Cummulative (BM)'!$A:$FH,$B13,FALSE)-1,"") -> 0.22829774 | K13: =IFERROR((VLOOKUP(K$2,'R.WEALTH-Cummulative (BM)'!$A:$FH,$B13,FALSE)^(1/(K$2/12)))-1,"") -> 0.27251111 | L13: =IFERROR((VLOOKUP(L$2,'R.WEALTH-Cummulative (BM)'!$A:$FH,$B13,FALSE)^(1/(L$2/12)))-1,"") -> 0.33824538 | M13: =IFERROR((VLOOKUP(M$2,'R.WEALTH-Cummulative (BM)'!$A:$FH,$B13,FALSE)^(1/(M$2/12)))-1,"") | N13: =IFERROR((VLOOKUP(N$2,'R.WEALTH-Cummulative (BM)'!$A:$FH,$B13,FALSE)^(1/(N$2/12)))-1,"") | O13: =IFERROR((VLOOKUP(O$2,'R.WEALTH-Cummulative (BM)'!$A:$FH,$B13,FALSE)^(1/(O$2/12)))-1,"") | P13: =IFERROR((VLOOKUP(P$2,'R.WEALTH-Cummulative (BM)'!$A:$FH,$B13,FALSE)^(1/(P$2/12)))-1,"") | Q13: =IFERROR((VLOOKUP(Q$2,'R.WEALTH-Cummulative (BM)'!$A:$FH,$B13,FALSE)^(1/(Q$2/12)))-1,"") | R13: =IFERROR((VLOOKUP(R$2,'R.WEALTH-Cummulative (BM)'!$A:$FH,$B13,FALSE)^(1/(R$2/12)))-1,"") | ... X13: =IFERROR((VLOOKUP(X$2,'R.WEALTH-Cummulative (BM)'!$A:$FH,$B13,FALSE)^(1/(X$2/12)))-1,"") | Y13: =VLOOKUP(Y$2,'Since Inception (BM)'!$B:$AAC,Summary!B13-1,FALSE) -> 1.6486322 | Z13: =VLOOKUP(Z$2,'Since Inception (BM)'!$B:$AAC,Summary!B13-1,FALSE) -> 0.34575075
A14: 9 | C14: HRA4 | D14: HUTE | E14: Harvest Equal Weight Global Utilities Enhanced Income ETF | F14: =IFERROR(VLOOKUP(F$2,'R.WEALTH-Cummulative'!$A:$FG,$A14,FALSE)-1,"") -> 0.048062951 | G14: =IFERROR(VLOOKUP(G$2,'R.WEALTH-Cummulative'!$A:$FG,$A14,FALSE)-1,"") -> 0.042974764 | H14: =IFERROR(VLOOKUP(H$2,'R.WEALTH-Cummulative'!$A:$FG,$A14,FALSE)-1,"") -> 0.082931167 | I14: =IFERROR(VLOOKUP(I$2,'R.WEALTH-Cummulative'!$A:$FG,$A14,FALSE)-1,"") -> 0.048062951 | J14: =IFERROR(VLOOKUP(J$2,'R.WEALTH-Cummulative'!$A:$FG,$A14,FALSE)-1,"") -> 0.22661672 | K14: =IFERROR((VLOOKUP(K$2,'R.WEALTH-Cummulative'!$A:$FG,$A14,FALSE)^(1/(K$2/12)))-1,"") -> 0.21329325 | L14: =IFERROR((VLOOKUP(L$2,'R.WEALTH-Cummulative'!$A:$FG,$A14,FALSE)^(1/(L$2/12)))-1,"") -> 0.1249266 | M14: =IFERROR((VLOOKUP(M$2,'R.WEALTH-Cummulative'!$A:$FG,$A14,FALSE)^(1/(M$2/12)))-1,"") | N14: =IFERROR((VLOOKUP(N$2,'R.WEALTH-Cummulative'!$A:$FG,$A14,FALSE)^(1/(N$2/12)))-1,"") | O14: =IFERROR((VLOOKUP(O$2,'R.WEALTH-Cummulative'!$A:$FG,$A14,FALSE)^(1/(O$2/12)))-1,"") | P14: =IFERROR((VLOOKUP(P$2,'R.WEALTH-Cummulative'!$A:$FG,$A14,FALSE)^(1/(P$2/12)))-1,"") | Q14: =IFERROR((VLOOKUP(Q$2,'R.WEALTH-Cummulative'!$A:$FG,$A14,FALSE)^(1/(Q$2/12)))-1,"") | R14: =IFERROR((VLOOKUP(R$2,'R.WEALTH-Cummulative'!$A:$FG,$A14,FALSE)^(1/(R$2/12)))-1,"") | ... X14: =IFERROR((VLOOKUP(X$2,'R.WEALTH-Cummulative'!$A:$FG,$A14,FALSE)^(1/(X$2/12)))-1,"") | Y14: =VLOOKUP(Y$2,'Since Inception Returns'!$B:$AAB,Summary!A14-1,FALSE) -> 0.57573137 | Z14: =VLOOKUP(Z$2,'Since Inception Returns'!$B:$AAB,Summary!A14-1,FALSE) -> 0.14869695
B15: 9 | C15: HRA4 | D15: HUTE | E15: MSCI World Utilities GRTR Local Index | F15: =IFERROR(VLOOKUP(F$2,'R.WEALTH-Cummulative (BM)'!$A:$FH,$B15,FALSE)-1,"") -> 0.03314887 | G15: =IFERROR(VLOOKUP(G$2,'R.WEALTH-Cummulative (BM)'!$A:$FH,$B15,FALSE)-1,"") -> 0.021324403 | H15: =IFERROR(VLOOKUP(H$2,'R.WEALTH-Cummulative (BM)'!$A:$FH,$B15,FALSE)-1,"") -> 0.082156746 | I15: =IFERROR(VLOOKUP(I$2,'R.WEALTH-Cummulative (BM)'!$A:$FH,$B15,FALSE)-1,"") -> 0.03314887 | J15: =IFERROR(VLOOKUP(J$2,'R.WEALTH-Cummulative (BM)'!$A:$FH,$B15,FALSE)-1,"") -> 0.22844476 | K15: =IFERROR((VLOOKUP(K$2,'R.WEALTH-Cummulative (BM)'!$A:$FH,$B15,FALSE)^(1/(K$2/12)))-1,"") -> 0.22649441 | L15: =IFERROR((VLOOKUP(L$2,'R.WEALTH-Cummulative (BM)'!$A:$FH,$B15,FALSE)^(1/(L$2/12)))-1,"") -> 0.13749448 | M15: =IFERROR((VLOOKUP(M$2,'R.WEALTH-Cummulative (BM)'!$A:$FH,$B15,FALSE)^(1/(M$2/12)))-1,"") | N15: =IFERROR((VLOOKUP(N$2,'R.WEALTH-Cummulative (BM)'!$A:$FH,$B15,FALSE)^(1/(N$2/12)))-1,"") | O15: =IFERROR((VLOOKUP(O$2,'R.WEALTH-Cummulative (BM)'!$A:$FH,$B15,FALSE)^(1/(O$2/12)))-1,"") | P15: =IFERROR((VLOOKUP(P$2,'R.WEALTH-Cummulative (BM)'!$A:$FH,$B15,FALSE)^(1/(P$2/12)))-1,"") | Q15: =IFERROR((VLOOKUP(Q$2,'R.WEALTH-Cummulative (BM)'!$A:$FH,$B15,FALSE)^(1/(Q$2/12)))-1,"") | R15: =IFERROR((VLOOKUP(R$2,'R.WEALTH-Cummulative (BM)'!$A:$FH,$B15,FALSE)^(1/(R$2/12)))-1,"") | ... X15: =IFERROR((VLOOKUP(X$2,'R.WEALTH-Cummulative (BM)'!$A:$FH,$B15,FALSE)^(1/(X$2/12)))-1,"") | Y15: =VLOOKUP(Y$2,'Since Inception (BM)'!$B:$AAC,Summary!B15-1,FALSE) -> 0.6574588 | Z15: =VLOOKUP(Z$2,'Since Inception (BM)'!$B:$AAC,Summary!B15-1,FALSE) -> 0.16654227
A16: 10 | C16: #N/A | D16: #N/A | E16: Harvest Canadian Equity Enhanced Income Leaders ETF | F16: =IFERROR(VLOOKUP(F$2,'R.WEALTH-Cummulative'!$A:$FG,$A16,FALSE)-1,"") | G16: =IFERROR(VLOOKUP(G$2,'R.WEALTH-Cummulative'!$A:$FG,$A16,FALSE)-1,"") | H16: =IFERROR(VLOOKUP(H$2,'R.WEALTH-Cummulative'!$A:$FG,$A16,FALSE)-1,"") | I16: =IFERROR(VLOOKUP(I$2,'R.WEALTH-Cummulative'!$A:$FG,$A16,FALSE)-1,"") | J16: =IFERROR(VLOOKUP(J$2,'R.WEALTH-Cummulative'!$A:$FG,$A16,FALSE)-1,"") | K16: =IFERROR((VLOOKUP(K$2,'R.WEALTH-Cummulative'!$A:$FG,$A16,FALSE)^(1/(K$2/12)))-1,"") | L16: =IFERROR((VLOOKUP(L$2,'R.WEALTH-Cummulative'!$A:$FG,$A16,FALSE)^(1/(L$2/12)))-1,"") | M16: =IFERROR((VLOOKUP(M$2,'R.WEALTH-Cummulative'!$A:$FG,$A16,FALSE)^(1/(M$2/12)))-1,"") | N16: =IFERROR((VLOOKUP(N$2,'R.WEALTH-Cummulative'!$A:$FG,$A16,FALSE)^(1/(N$2/12)))-1,"") | O16: =IFERROR((VLOOKUP(O$2,'R.WEALTH-Cummulative'!$A:$FG,$A16,FALSE)^(1/(O$2/12)))-1,"") | P16: =IFERROR((VLOOKUP(P$2,'R.WEALTH-Cummulative'!$A:$FG,$A16,FALSE)^(1/(P$2/12)))-1,"") | Q16: =IFERROR((VLOOKUP(Q$2,'R.WEALTH-Cummulative'!$A:$FG,$A16,FALSE)^(1/(Q$2/12)))-1,"") | R16: =IFERROR((VLOOKUP(R$2,'R.WEALTH-Cummulative'!$A:$FG,$A16,FALSE)^(1/(R$2/12)))-1,"") | ... X16: =IFERROR((VLOOKUP(X$2,'R.WEALTH-Cummulative'!$A:$FG,$A16,FALSE)^(1/(X$2/12)))-1,"") | Y16: =VLOOKUP(Y$2,'Since Inception Returns'!$B:$AAB,Summary!A16-1,FALSE) -> 0.59264257 | Z16: =VLOOKUP(Z$2,'Since Inception Returns'!$B:$AAB,Summary!A16-1,FALSE) -> 0.30683702
A17: 11 | C17: HRAS_A | D17: HPYT | E17: Harvest Premium Yield Treasury ETF | F17: =IFERROR(VLOOKUP(F$2,'R.WEALTH-Cummulative'!$A:$FG,$A17,FALSE)-1,"") -> 0.000566365 | G17: =IFERROR(VLOOKUP(G$2,'R.WEALTH-Cummulative'!$A:$FG,$A17,FALSE)-1,"") -> -0.019413517 | H17: =IFERROR(VLOOKUP(H$2,'R.WEALTH-Cummulative'!$A:$FG,$A17,FALSE)-1,"") -> 0.024874894 | I17: =IFERROR(VLOOKUP(I$2,'R.WEALTH-Cummulative'!$A:$FG,$A17,FALSE)-1,"") -> 0.000566365 | J17: =IFERROR(VLOOKUP(J$2,'R.WEALTH-Cummulative'!$A:$FG,$A17,FALSE)-1,"") -> 0.040381713 | K17: =IFERROR((VLOOKUP(K$2,'R.WEALTH-Cummulative'!$A:$FG,$A17,FALSE)^(1/(K$2/12)))-1,"") -> -0.001758294 | L17: =IFERROR((VLOOKUP(L$2,'R.WEALTH-Cummulative'!$A:$FG,$A17,FALSE)^(1/(L$2/12)))-1,"") | M17: =IFERROR((VLOOKUP(M$2,'R.WEALTH-Cummulative'!$A:$FG,$A17,FALSE)^(1/(M$2/12)))-1,"") | N17: =IFERROR((VLOOKUP(N$2,'R.WEALTH-Cummulative'!$A:$FG,$A17,FALSE)^(1/(N$2/12)))-1,"") | O17: =IFERROR((VLOOKUP(O$2,'R.WEALTH-Cummulative'!$A:$FG,$A17,FALSE)^(1/(O$2/12)))-1,"") | P17: =IFERROR((VLOOKUP(P$2,'R.WEALTH-Cummulative'!$A:$FG,$A17,FALSE)^(1/(P$2/12)))-1,"") | Q17: =IFERROR((VLOOKUP(Q$2,'R.WEALTH-Cummulative'!$A:$FG,$A17,FALSE)^(1/(Q$2/12)))-1,"") | R17: =IFERROR((VLOOKUP(R$2,'R.WEALTH-Cummulative'!$A:$FG,$A17,FALSE)^(1/(R$2/12)))-1,"") | ... X17: =IFERROR((VLOOKUP(X$2,'R.WEALTH-Cummulative'!$A:$FG,$A17,FALSE)^(1/(X$2/12)))-1,"") | Y17: =VLOOKUP(Y$2,'Since Inception Returns'!$B:$AAB,Summary!A17-1,FALSE) -> 0.02998578 | Z17: =VLOOKUP(Z$2,'Since Inception Returns'!$B:$AAB,Summary!A17-1,FALSE) -> 0.012682701
B18: 11 | C18: HRAS_A | D18: HPYT | E18: Blended Benchmark | F18: =IFERROR(VLOOKUP(F$2,'R.WEALTH-Cummulative (BM)'!$A:$FH,$B18,FALSE)-1,"") -> -0.0030880429 | G18: =IFERROR(VLOOKUP(G$2,'R.WEALTH-Cummulative (BM)'!$A:$FH,$B18,FALSE)-1,"") -> -0.015273725 | H18: =IFERROR(VLOOKUP(H$2,'R.WEALTH-Cummulative (BM)'!$A:$FH,$B18,FALSE)-1,"") -> 0.016363147 | I18: =IFERROR(VLOOKUP(I$2,'R.WEALTH-Cummulative (BM)'!$A:$FH,$B18,FALSE)-1,"") -> -0.0030880429 | J18: =IFERROR(VLOOKUP(J$2,'R.WEALTH-Cummulative (BM)'!$A:$FH,$B18,FALSE)-1,"") -> 0.032995417 | K18: =IFERROR((VLOOKUP(K$2,'R.WEALTH-Cummulative (BM)'!$A:$FH,$B18,FALSE)^(1/(K$2/12)))-1,"") -> -0.0081200165 | L18: =IFERROR((VLOOKUP(L$2,'R.WEALTH-Cummulative (BM)'!$A:$FH,$B18,FALSE)^(1/(L$2/12)))-1,"") | M18: =IFERROR((VLOOKUP(M$2,'R.WEALTH-Cummulative (BM)'!$A:$FH,$B18,FALSE)^(1/(M$2/12)))-1,"") | N18: =IFERROR((VLOOKUP(N$2,'R.WEALTH-Cummulative (BM)'!$A:$FH,$B18,FALSE)^(1/(N$2/12)))-1,"") | O18: =IFERROR((VLOOKUP(O$2,'R.WEALTH-Cummulative (BM)'!$A:$FH,$B18,FALSE)^(1/(O$2/12)))-1,"") | P18: =IFERROR((VLOOKUP(P$2,'R.WEALTH-Cummulative (BM)'!$A:$FH,$B18,FALSE)^(1/(P$2/12)))-1,"") | Q18: =IFERROR((VLOOKUP(Q$2,'R.WEALTH-Cummulative (BM)'!$A:$FH,$B18,FALSE)^(1/(Q$2/12)))-1,"") | R18: =IFERROR((VLOOKUP(R$2,'R.WEALTH-Cummulative (BM)'!$A:$FH,$B18,FALSE)^(1/(R$2/12)))-1,"") | ... X18: =IFERROR((VLOOKUP(X$2,'R.WEALTH-Cummulative (BM)'!$A:$FH,$B18,FALSE)^(1/(X$2/12)))-1,"") | Y18: =VLOOKUP(Y$2,'Since Inception (BM)'!$B:$AAC,Summary!B18-1,FALSE) -> 0.052313757 | Z18: =VLOOKUP(Z$2,'Since Inception (BM)'!$B:$AAC,Summary!B18-1,FALSE) -> 0.021989546
A19: 12 | C19: HRAS_B | D19: HPYT.B | E19: Harvest Premium Yield Treasury ETF | F19: =IFERROR(VLOOKUP(F$2,'R.WEALTH-Cummulative'!$A:$FG,$A19,FALSE)-1,"") -> -0.0061671012 | G19: =IFERROR(VLOOKUP(G$2,'R.WEALTH-Cummulative'!$A:$FG,$A19,FALSE)-1,"") -> -0.04417953 | H19: =IFERROR(VLOOKUP(H$2,'R.WEALTH-Cummulative'!$A:$FG,$A19,FALSE)-1,"") -> 0.01610936 | I19: =IFERROR(VLOOKUP(I$2,'R.WEALTH-Cummulative'!$A:$FG,$A19,FALSE)-1,"") -> -0.0061671012 | J19: =IFERROR(VLOOKUP(J$2,'R.WEALTH-Cummulative'!$A:$FG,$A19,FALSE)-1,"") -> -0.0092368358 | K19: =IFERROR((VLOOKUP(K$2,'R.WEALTH-Cummulative'!$A:$FG,$A19,FALSE)^(1/(K$2/12)))-1,"") | L19: =IFERROR((VLOOKUP(L$2,'R.WEALTH-Cummulative'!$A:$FG,$A19,FALSE)^(1/(L$2/12)))-1,"") | M19: =IFERROR((VLOOKUP(M$2,'R.WEALTH-Cummulative'!$A:$FG,$A19,FALSE)^(1/(M$2/12)))-1,"") | N19: =IFERROR((VLOOKUP(N$2,'R.WEALTH-Cummulative'!$A:$FG,$A19,FALSE)^(1/(N$2/12)))-1,"") | O19: =IFERROR((VLOOKUP(O$2,'R.WEALTH-Cummulative'!$A:$FG,$A19,FALSE)^(1/(O$2/12)))-1,"") | P19: =IFERROR((VLOOKUP(P$2,'R.WEALTH-Cummulative'!$A:$FG,$A19,FALSE)^(1/(P$2/12)))-1,"") | Q19: =IFERROR((VLOOKUP(Q$2,'R.WEALTH-Cummulative'!$A:$FG,$A19,FALSE)^(1/(Q$2/12)))-1,"") | R19: =IFERROR((VLOOKUP(R$2,'R.WEALTH-Cummulative'!$A:$FG,$A19,FALSE)^(1/(R$2/12)))-1,"") | ... X19: =IFERROR((VLOOKUP(X$2,'R.WEALTH-Cummulative'!$A:$FG,$A19,FALSE)^(1/(X$2/12)))-1,"") | Y19: =VLOOKUP(Y$2,'Since Inception Returns'!$B:$AAB,Summary!A19-1,FALSE) -> 0.036365764 | Z19: =VLOOKUP(Z$2,'Since Inception Returns'!$B:$AAB,Summary!A19-1,FALSE) -> 0.022044939
B20: 12 | C20: HRAS_B | D20: HPYT.B | E20: Blended Benchmark | F20: =IFERROR(VLOOKUP(F$2,'R.WEALTH-Cummulative (BM)'!$A:$FH,$B20,FALSE)-1,"") -> -0.0030880429 | G20: =IFERROR(VLOOKUP(G$2,'R.WEALTH-Cummulative (BM)'!$A:$FH,$B20,FALSE)-1,"") -> -0.015273725 | H20: =IFERROR(VLOOKUP(H$2,'R.WEALTH-Cummulative (BM)'!$A:$FH,$B20,FALSE)-1,"") -> 0.016363147 | I20: =IFERROR(VLOOKUP(I$2,'R.WEALTH-Cummulative (BM)'!$A:$FH,$B20,FALSE)-1,"") -> -0.0030880429 | J20: =IFERROR(VLOOKUP(J$2,'R.WEALTH-Cummulative (BM)'!$A:$FH,$B20,FALSE)-1,"") -> 0.032995417 | K20: =IFERROR((VLOOKUP(K$2,'R.WEALTH-Cummulative (BM)'!$A:$FH,$B20,FALSE)^(1/(K$2/12)))-1,"") | L20: =IFERROR((VLOOKUP(L$2,'R.WEALTH-Cummulative (BM)'!$A:$FH,$B20,FALSE)^(1/(L$2/12)))-1,"") | M20: =IFERROR((VLOOKUP(M$2,'R.WEALTH-Cummulative (BM)'!$A:$FH,$B20,FALSE)^(1/(M$2/12)))-1,"") | N20: =IFERROR((VLOOKUP(N$2,'R.WEALTH-Cummulative (BM)'!$A:$FH,$B20,FALSE)^(1/(N$2/12)))-1,"") | O20: =IFERROR((VLOOKUP(O$2,'R.WEALTH-Cummulative (BM)'!$A:$FH,$B20,FALSE)^(1/(O$2/12)))-1,"") | P20: =IFERROR((VLOOKUP(P$2,'R.WEALTH-Cummulative (BM)'!$A:$FH,$B20,FALSE)^(1/(P$2/12)))-1,"") | Q20: =IFERROR((VLOOKUP(Q$2,'R.WEALTH-Cummulative (BM)'!$A:$FH,$B20,FALSE)^(1/(Q$2/12)))-1,"") | R20: =IFERROR((VLOOKUP(R$2,'R.WEALTH-Cummulative (BM)'!$A:$FH,$B20,FALSE)^(1/(R$2/12)))-1,"") | ... X20: =IFERROR((VLOOKUP(X$2,'R.WEALTH-Cummulative (BM)'!$A:$FH,$B20,FALSE)^(1/(X$2/12)))-1,"") | Y20: =VLOOKUP(Y$2,'Since Inception (BM)'!$B:$AAC,Summary!B20-1,FALSE) -> 0.009516776 | Z20: =VLOOKUP(Z$2,'Since Inception (BM)'!$B:$AAC,Summary!B20-1,FALSE) -> 0.0057988226
A21: 13 | C21: HRAS_U | D21: HPYT.U | E21: Harvest Premium Yield Treasury ETF | F21: =IFERROR(VLOOKUP(F$2,'R.WEALTH-Cummulative'!$A:$FG,$A21,FALSE)-1,"") -> 0.0017969452 | G21: =IFERROR(VLOOKUP(G$2,'R.WEALTH-Cummulative'!$A:$FG,$A21,FALSE)-1,"") -> -0.015450145 | H21: =IFERROR(VLOOKUP(H$2,'R.WEALTH-Cummulative'!$A:$FG,$A21,FALSE)-1,"") -> 0.033986942 | I21: =IFERROR(VLOOKUP(I$2,'R.WEALTH-Cummulative'!$A:$FG,$A21,FALSE)-1,"") -> 0.0017969452 | J21: =IFERROR(VLOOKUP(J$2,'R.WEALTH-Cummulative'!$A:$FG,$A21,FALSE)-1,"") -> 0.057528553 | K21: =IFERROR((VLOOKUP(K$2,'R.WEALTH-Cummulative'!$A:$FG,$A21,FALSE)^(1/(K$2/12)))-1,"") -> 0.011094583 | L21: =IFERROR((VLOOKUP(L$2,'R.WEALTH-Cummulative'!$A:$FG,$A21,FALSE)^(1/(L$2/12)))-1,"") | M21: =IFERROR((VLOOKUP(M$2,'R.WEALTH-Cummulative'!$A:$FG,$A21,FALSE)^(1/(M$2/12)))-1,"") | N21: =IFERROR((VLOOKUP(N$2,'R.WEALTH-Cummulative'!$A:$FG,$A21,FALSE)^(1/(N$2/12)))-1,"") | O21: =IFERROR((VLOOKUP(O$2,'R.WEALTH-Cummulative'!$A:$FG,$A21,FALSE)^(1/(O$2/12)))-1,"") | P21: =IFERROR((VLOOKUP(P$2,'R.WEALTH-Cummulative'!$A:$FG,$A21,FALSE)^(1/(P$2/12)))-1,"") | Q21: =IFERROR((VLOOKUP(Q$2,'R.WEALTH-Cummulative'!$A:$FG,$A21,FALSE)^(1/(Q$2/12)))-1,"") | R21: =IFERROR((VLOOKUP(R$2,'R.WEALTH-Cummulative'!$A:$FG,$A21,FALSE)^(1/(R$2/12)))-1,"") | ... X21: =IFERROR((VLOOKUP(X$2,'R.WEALTH-Cummulative'!$A:$FG,$A21,FALSE)^(1/(X$2/12)))-1,"") | Y21: =VLOOKUP(Y$2,'Since Inception Returns'!$B:$AAB,Summary!A21-1,FALSE) -> 0.020148362 | Z21: =VLOOKUP(Z$2,'Since Inception Returns'!$B:$AAB,Summary!A21-1,FALSE) -> 0.0097553368
B22: 13 | C22: HRAS_U | D22: HPYT.U | E22: Blended Benchmark | F22: =IFERROR(VLOOKUP(F$2,'R.WEALTH-Cummulative (BM)'!$A:$FH,$B22,FALSE)-1,"") -> -0.0030880429 | G22: =IFERROR(VLOOKUP(G$2,'R.WEALTH-Cummulative (BM)'!$A:$FH,$B22,FALSE)-1,"") -> -0.015273725 | H22: =IFERROR(VLOOKUP(H$2,'R.WEALTH-Cummulative (BM)'!$A:$FH,$B22,FALSE)-1,"") -> 0.016363147 | I22: =IFERROR(VLOOKUP(I$2,'R.WEALTH-Cummulative (BM)'!$A:$FH,$B22,FALSE)-1,"") -> -0.0030880429 | J22: =IFERROR(VLOOKUP(J$2,'R.WEALTH-Cummulative (BM)'!$A:$FH,$B22,FALSE)-1,"") -> 0.032995417 | K22: =IFERROR((VLOOKUP(K$2,'R.WEALTH-Cummulative (BM)'!$A:$FH,$B22,FALSE)^(1/(K$2/12)))-1,"") -> -0.0081200165 | L22: =IFERROR((VLOOKUP(L$2,'R.WEALTH-Cummulative (BM)'!$A:$FH,$B22,FALSE)^(1/(L$2/12)))-1,"") | M22: =IFERROR((VLOOKUP(M$2,'R.WEALTH-Cummulative (BM)'!$A:$FH,$B22,FALSE)^(1/(M$2/12)))-1,"") | N22: =IFERROR((VLOOKUP(N$2,'R.WEALTH-Cummulative (BM)'!$A:$FH,$B22,FALSE)^(1/(N$2/12)))-1,"") | O22: =IFERROR((VLOOKUP(O$2,'R.WEALTH-Cummulative (BM)'!$A:$FH,$B22,FALSE)^(1/(O$2/12)))-1,"") | P22: =IFERROR((VLOOKUP(P$2,'R.WEALTH-Cummulative (BM)'!$A:$FH,$B22,FALSE)^(1/(P$2/12)))-1,"") | Q22: =IFERROR((VLOOKUP(Q$2,'R.WEALTH-Cummulative (BM)'!$A:$FH,$B22,FALSE)^(1/(Q$2/12)))-1,"") | R22: =IFERROR((VLOOKUP(R$2,'R.WEALTH-Cummulative (BM)'!$A:$FH,$B22,FALSE)^(1/(R$2/12)))-1,"") | ... X22: =IFERROR((VLOOKUP(X$2,'R.WEALTH-Cummulative (BM)'!$A:$FH,$B22,FALSE)^(1/(X$2/12)))-1,"") | Y22: =VLOOKUP(Y$2,'Since Inception (BM)'!$B:$AAC,Summary!B22-1,FALSE) -> -0.016584579 | Z22: =VLOOKUP(Z$2,'Since Inception (BM)'!$B:$AAC,Summary!B22-1,FALSE) -> -0.008105809
A23: 14 | C23: HRQA | D23: HLIF | E23: Harvest Canadian Equity Income Leaders ETF | F23: =IFERROR(VLOOKUP(F$2,'R.WEALTH-Cummulative'!$A:$FG,$A23,FALSE)-1,"") -> 0.020251296 | G23: =IFERROR(VLOOKUP(G$2,'R.WEALTH-Cummulative'!$A:$FG,$A23,FALSE)-1,"") -> 0.076356686 | H23: =IFERROR(VLOOKUP(H$2,'R.WEALTH-Cummulative'!$A:$FG,$A23,FALSE)-1,"") -> 0.1593143 | I23: =IFERROR(VLOOKUP(I$2,'R.WEALTH-Cummulative'!$A:$FG,$A23,FALSE)-1,"") -> 0.020251296 | J23: =IFERROR(VLOOKUP(J$2,'R.WEALTH-Cummulative'!$A:$FG,$A23,FALSE)-1,"") -> 0.27459501 | K23: =IFERROR((VLOOKUP(K$2,'R.WEALTH-Cummulative'!$A:$FG,$A23,FALSE)^(1/(K$2/12)))-1,"") -> 0.22089754 | L23: =IFERROR((VLOOKUP(L$2,'R.WEALTH-Cummulative'!$A:$FG,$A23,FALSE)^(1/(L$2/12)))-1,"") -> 0.1430029 | M23: =IFERROR((VLOOKUP(M$2,'R.WEALTH-Cummulative'!$A:$FG,$A23,FALSE)^(1/(M$2/12)))-1,"") | N23: =IFERROR((VLOOKUP(N$2,'R.WEALTH-Cummulative'!$A:$FG,$A23,FALSE)^(1/(N$2/12)))-1,"") | O23: =IFERROR((VLOOKUP(O$2,'R.WEALTH-Cummulative'!$A:$FG,$A23,FALSE)^(1/(O$2/12)))-1,"") | P23: =IFERROR((VLOOKUP(P$2,'R.WEALTH-Cummulative'!$A:$FG,$A23,FALSE)^(1/(P$2/12)))-1,"") | Q23: =IFERROR((VLOOKUP(Q$2,'R.WEALTH-Cummulative'!$A:$FG,$A23,FALSE)^(1/(Q$2/12)))-1,"") | R23: =IFERROR((VLOOKUP(R$2,'R.WEALTH-Cummulative'!$A:$FG,$A23,FALSE)^(1/(R$2/12)))-1,"") | ... X23: =IFERROR((VLOOKUP(X$2,'R.WEALTH-Cummulative'!$A:$FG,$A23,FALSE)^(1/(X$2/12)))-1,"") | Y23: =VLOOKUP(Y$2,'Since Inception Returns'!$B:$AAB,Summary!A23-1,FALSE) -> 0.47477545 | Z23: =VLOOKUP(Z$2,'Since Inception Returns'!$B:$AAB,Summary!A23-1,FALSE) -> 0.11251885
B24: 14 | C24: HRQA | D24: HLIF | E24: Solactive Canada Large Cap Index (CA NTR) | F24: =IFERROR(VLOOKUP(F$2,'R.WEALTH-Cummulative (BM)'!$A:$FH,$B24,FALSE)-1,"") -> -0.00041784691 | G24: =IFERROR(VLOOKUP(G$2,'R.WEALTH-Cummulative (BM)'!$A:$FH,$B24,FALSE)-1,"") -> 0.048150452 | H24: =IFERROR(VLOOKUP(H$2,'R.WEALTH-Cummulative (BM)'!$A:$FH,$B24,FALSE)-1,"") -> 0.16061554 | I24: =IFERROR(VLOOKUP(I$2,'R.WEALTH-Cummulative (BM)'!$A:$FH,$B24,FALSE)-1,"") -> -0.00041784691 | J24: =IFERROR(VLOOKUP(J$2,'R.WEALTH-Cummulative (BM)'!$A:$FH,$B24,FALSE)-1,"") -> 0.24253033 | K24: =IFERROR((VLOOKUP(K$2,'R.WEALTH-Cummulative (BM)'!$A:$FH,$B24,FALSE)^(1/(K$2/12)))-1,"") -> 0.24877011 | L24: =IFERROR((VLOOKUP(L$2,'R.WEALTH-Cummulative (BM)'!$A:$FH,$B24,FALSE)^(1/(L$2/12)))-1,"") -> 0.18299168 | M24: =IFERROR((VLOOKUP(M$2,'R.WEALTH-Cummulative (BM)'!$A:$FH,$B24,FALSE)^(1/(M$2/12)))-1,"") | N24: =IFERROR((VLOOKUP(N$2,'R.WEALTH-Cummulative (BM)'!$A:$FH,$B24,FALSE)^(1/(N$2/12)))-1,"") | O24: =IFERROR((VLOOKUP(O$2,'R.WEALTH-Cummulative (BM)'!$A:$FH,$B24,FALSE)^(1/(O$2/12)))-1,"") | P24: =IFERROR((VLOOKUP(P$2,'R.WEALTH-Cummulative (BM)'!$A:$FH,$B24,FALSE)^(1/(P$2/12)))-1,"") | Q24: =IFERROR((VLOOKUP(Q$2,'R.WEALTH-Cummulative (BM)'!$A:$FH,$B24,FALSE)^(1/(Q$2/12)))-1,"") | R24: =IFERROR((VLOOKUP(R$2,'R.WEALTH-Cummulative (BM)'!$A:$FH,$B24,FALSE)^(1/(R$2/12)))-1,"") | ... X24: =IFERROR((VLOOKUP(X$2,'R.WEALTH-Cummulative (BM)'!$A:$FH,$B24,FALSE)^(1/(X$2/12)))-1,"") | Y24: =VLOOKUP(Y$2,'Since Inception (BM)'!$B:$AAC,Summary!B24-1,FALSE) -> 0.69156662 | Z24: =VLOOKUP(Z$2,'Since Inception (BM)'!$B:$AAC,Summary!B24-1,FALSE) -> 0.15519339
A25: 15 | C25: HRT0_A | D25: HPF | E25: Harvest Energy Leaders Plus Income ETF | F25: =IFERROR(VLOOKUP(F$2,'R.WEALTH-Cummulative'!$A:$FG,$A25,FALSE)-1,"") -> 0.090752117 | G25: =IFERROR(VLOOKUP(G$2,'R.WEALTH-Cummulative'!$A:$FG,$A25,FALSE)-1,"") -> 0.11611086 | H25: =IFERROR(VLOOKUP(H$2,'R.WEALTH-Cummulative'!$A:$FG,$A25,FALSE)-1,"") -> 0.15758369 | I25: =IFERROR(VLOOKUP(I$2,'R.WEALTH-Cummulative'!$A:$FG,$A25,FALSE)-1,"") -> 0.090752117 | J25: =IFERROR(VLOOKUP(J$2,'R.WEALTH-Cummulative'!$A:$FG,$A25,FALSE)-1,"") -> 0.1705267 | K25: =IFERROR((VLOOKUP(K$2,'R.WEALTH-Cummulative'!$A:$FG,$A25,FALSE)^(1/(K$2/12)))-1,"") -> 0.084394419 | L25: =IFERROR((VLOOKUP(L$2,'R.WEALTH-Cummulative'!$A:$FG,$A25,FALSE)^(1/(L$2/12)))-1,"") -> 0.051229043 | M25: =IFERROR((VLOOKUP(M$2,'R.WEALTH-Cummulative'!$A:$FG,$A25,FALSE)^(1/(M$2/12)))-1,"") -> 0.098330611 | N25: =IFERROR((VLOOKUP(N$2,'R.WEALTH-Cummulative'!$A:$FG,$A25,FALSE)^(1/(N$2/12)))-1,"") -> 0.16395559 | O25: =IFERROR((VLOOKUP(O$2,'R.WEALTH-Cummulative'!$A:$FG,$A25,FALSE)^(1/(O$2/12)))-1,"") -> 0.069067844 | P25: =IFERROR((VLOOKUP(P$2,'R.WEALTH-Cummulative'!$A:$FG,$A25,FALSE)^(1/(P$2/12)))-1,"") -> 0.045758118 | Q25: =IFERROR((VLOOKUP(Q$2,'R.WEALTH-Cummulative'!$A:$FG,$A25,FALSE)^(1/(Q$2/12)))-1,"") -> 0.022361646 | R25: =IFERROR((VLOOKUP(R$2,'R.WEALTH-Cummulative'!$A:$FG,$A25,FALSE)^(1/(R$2/12)))-1,"") -> 0.024383487 | ... X25: =IFERROR((VLOOKUP(X$2,'R.WEALTH-Cummulative'!$A:$FG,$A25,FALSE)^(1/(X$2/12)))-1,"") | Y25: =VLOOKUP(Y$2,'Since Inception Returns'!$B:$AAB,Summary!A25-1,FALSE) -> 0.019890993 | Z25: =VLOOKUP(Z$2,'Since Inception Returns'!$B:$AAB,Summary!A25-1,FALSE) -> 0.0017480862
B26: 15 | C26: HRT0_A | D26: HPF | E26: MSCI ACW Energy Index CAD$ | F26: =IFERROR(VLOOKUP(F$2,'R.WEALTH-Cummulative (BM)'!$A:$FH,$B26,FALSE)-1,"") -> 0.10824198 | G26: =IFERROR(VLOOKUP(G$2,'R.WEALTH-Cummulative (BM)'!$A:$FH,$B26,FALSE)-1,"") -> 0.11096252 | H26: =IFERROR(VLOOKUP(H$2,'R.WEALTH-Cummulative (BM)'!$A:$FH,$B26,FALSE)-1,"") -> 0.16383361 | I26: =IFERROR(VLOOKUP(I$2,'R.WEALTH-Cummulative (BM)'!$A:$FH,$B26,FALSE)-1,"") -> 0.10824198 | J26: =IFERROR(VLOOKUP(J$2,'R.WEALTH-Cummulative (BM)'!$A:$FH,$B26,FALSE)-1,"") -> 0.15993514 | K26: =IFERROR((VLOOKUP(K$2,'R.WEALTH-Cummulative (BM)'!$A:$FH,$B26,FALSE)^(1/(K$2/12)))-1,"") -> 0.14597965 | L26: =IFERROR((VLOOKUP(L$2,'R.WEALTH-Cummulative (BM)'!$A:$FH,$B26,FALSE)^(1/(L$2/12)))-1,"") -> 0.10429963 | M26: =IFERROR((VLOOKUP(M$2,'R.WEALTH-Cummulative (BM)'!$A:$FH,$B26,FALSE)^(1/(M$2/12)))-1,"") -> 0.14351715 | N26: =IFERROR((VLOOKUP(N$2,'R.WEALTH-Cummulative (BM)'!$A:$FH,$B26,FALSE)^(1/(N$2/12)))-1,"") -> 0.20784067 | O26: =IFERROR((VLOOKUP(O$2,'R.WEALTH-Cummulative (BM)'!$A:$FH,$B26,FALSE)^(1/(O$2/12)))-1,"") -> 0.12063681 | P26: =IFERROR((VLOOKUP(P$2,'R.WEALTH-Cummulative (BM)'!$A:$FH,$B26,FALSE)^(1/(P$2/12)))-1,"") -> 0.092536771 | Q26: =IFERROR((VLOOKUP(Q$2,'R.WEALTH-Cummulative (BM)'!$A:$FH,$B26,FALSE)^(1/(Q$2/12)))-1,"") -> 0.077849069 | R26: =IFERROR((VLOOKUP(R$2,'R.WEALTH-Cummulative (BM)'!$A:$FH,$B26,FALSE)^(1/(R$2/12)))-1,"") -> 0.077520126 | ... X26: =IFERROR((VLOOKUP(X$2,'R.WEALTH-Cummulative (BM)'!$A:$FH,$B26,FALSE)^(1/(X$2/12)))-1,"") | Y26: =VLOOKUP(Y$2,'Since Inception (BM)'!$B:$AAC,Summary!B26-1,FALSE) -> 0.98822266 | Z26: =VLOOKUP(Z$2,'Since Inception (BM)'!$B:$AAC,Summary!B26-1,FALSE) -> 0.062837775
A27: 16 | C27: HRT0_U | D27: HPF.U | E27: Harvest Energy Leaders Plus Income ETF | F27: =IFERROR(VLOOKUP(F$2,'R.WEALTH-Cummulative'!$A:$FG,$A27,FALSE)-1,"") -> 0.093785781 | G27: =IFERROR(VLOOKUP(G$2,'R.WEALTH-Cummulative'!$A:$FG,$A27,FALSE)-1,"") -> 0.12866759 | H27: =IFERROR(VLOOKUP(H$2,'R.WEALTH-Cummulative'!$A:$FG,$A27,FALSE)-1,"") -> 0.16994772 | I27: =IFERROR(VLOOKUP(I$2,'R.WEALTH-Cummulative'!$A:$FG,$A27,FALSE)-1,"") -> 0.093785781 | J27: =IFERROR(VLOOKUP(J$2,'R.WEALTH-Cummulative'!$A:$FG,$A27,FALSE)-1,"") -> 0.20507303 | K27: =IFERROR((VLOOKUP(K$2,'R.WEALTH-Cummulative'!$A:$FG,$A27,FALSE)^(1/(K$2/12)))-1,"") -> 0.093110684 | L27: =IFERROR((VLOOKUP(L$2,'R.WEALTH-Cummulative'!$A:$FG,$A27,FALSE)^(1/(L$2/12)))-1,"") -> 0.058172842 | M27: =IFERROR((VLOOKUP(M$2,'R.WEALTH-Cummulative'!$A:$FG,$A27,FALSE)^(1/(M$2/12)))-1,"") -> 0.10229063 | N27: =IFERROR((VLOOKUP(N$2,'R.WEALTH-Cummulative'!$A:$FG,$A27,FALSE)^(1/(N$2/12)))-1,"") -> 0.17009034 | O27: =IFERROR((VLOOKUP(O$2,'R.WEALTH-Cummulative'!$A:$FG,$A27,FALSE)^(1/(O$2/12)))-1,"") -> 0.081252597 | P27: =IFERROR((VLOOKUP(P$2,'R.WEALTH-Cummulative'!$A:$FG,$A27,FALSE)^(1/(P$2/12)))-1,"") -> 0.05742797 | Q27: =IFERROR((VLOOKUP(Q$2,'R.WEALTH-Cummulative'!$A:$FG,$A27,FALSE)^(1/(Q$2/12)))-1,"") -> 0.033444608 | R27: =IFERROR((VLOOKUP(R$2,'R.WEALTH-Cummulative'!$A:$FG,$A27,FALSE)^(1/(R$2/12)))-1,"") -> 0.036328927 | ... X27: =IFERROR((VLOOKUP(X$2,'R.WEALTH-Cummulative'!$A:$FG,$A27,FALSE)^(1/(X$2/12)))-1,"") | Y27: =VLOOKUP(Y$2,'Since Inception Returns'!$B:$AAB,Summary!A27-1,FALSE) -> 0.1730281 | Z27: =VLOOKUP(Z$2,'Since Inception Returns'!$B:$AAB,Summary!A27-1,FALSE) -> 0.014252443
B28: 16 | C28: HRT0_U | D28: HPF.U | E28: MSCI ACWI Energy Daily Net TR USD | F28: =IFERROR(VLOOKUP(F$2,'R.WEALTH-Cummulative (BM)'!$A:$FH,$B28,FALSE)-1,"") -> 0.11727855 | G28: =IFERROR(VLOOKUP(G$2,'R.WEALTH-Cummulative (BM)'!$A:$FH,$B28,FALSE)-1,"") -> 0.14336185 | H28: =IFERROR(VLOOKUP(H$2,'R.WEALTH-Cummulative (BM)'!$A:$FH,$B28,FALSE)-1,"") -> 0.18460872 | I28: =IFERROR(VLOOKUP(I$2,'R.WEALTH-Cummulative (BM)'!$A:$FH,$B28,FALSE)-1,"") -> 0.11727855 | J28: =IFERROR(VLOOKUP(J$2,'R.WEALTH-Cummulative (BM)'!$A:$FH,$B28,FALSE)-1,"") -> 0.23900807 | K28: =IFERROR((VLOOKUP(K$2,'R.WEALTH-Cummulative (BM)'!$A:$FH,$B28,FALSE)^(1/(K$2/12)))-1,"") -> 0.13846273 | L28: =IFERROR((VLOOKUP(L$2,'R.WEALTH-Cummulative (BM)'!$A:$FH,$B28,FALSE)^(1/(L$2/12)))-1,"") -> 0.095935058 | M28: =IFERROR((VLOOKUP(M$2,'R.WEALTH-Cummulative (BM)'!$A:$FH,$B28,FALSE)^(1/(M$2/12)))-1,"") -> 0.12401866 | N28: =IFERROR((VLOOKUP(N$2,'R.WEALTH-Cummulative (BM)'!$A:$FH,$B28,FALSE)^(1/(N$2/12)))-1,"") -> 0.19262706 | O28: =IFERROR((VLOOKUP(O$2,'R.WEALTH-Cummulative (BM)'!$A:$FH,$B28,FALSE)^(1/(O$2/12)))-1,"") -> 0.11541763 | P28: =IFERROR((VLOOKUP(P$2,'R.WEALTH-Cummulative (BM)'!$A:$FH,$B28,FALSE)^(1/(P$2/12)))-1,"") -> 0.086853803 | Q28: =IFERROR((VLOOKUP(Q$2,'R.WEALTH-Cummulative (BM)'!$A:$FH,$B28,FALSE)^(1/(Q$2/12)))-1,"") -> 0.064432245 | R28: =IFERROR((VLOOKUP(R$2,'R.WEALTH-Cummulative (BM)'!$A:$FH,$B28,FALSE)^(1/(R$2/12)))-1,"") -> 0.07229241 | ... X28: =IFERROR((VLOOKUP(X$2,'R.WEALTH-Cummulative (BM)'!$A:$FH,$B28,FALSE)^(1/(X$2/12)))-1,"") | Y28: =VLOOKUP(Y$2,'Since Inception (BM)'!$B:$AAC,Summary!B28-1,FALSE) -> 0.63900938 | Z28: =VLOOKUP(Z$2,'Since Inception (BM)'!$B:$AAC,Summary!B28-1,FALSE) -> 0.04478863
A29: 17 | C29: HRT1_I | D29: HBB.I | E29: Harvest Banks & Buildings Income Fund | F29: =IFERROR(VLOOKUP(F$2,'R.WEALTH-Cummulative'!$A:$FG,$A29,FALSE)-1,"") | G29: =IFERROR(VLOOKUP(G$2,'R.WEALTH-Cummulative'!$A:$FG,$A29,FALSE)-1,"") | H29: =IFERROR(VLOOKUP(H$2,'R.WEALTH-Cummulative'!$A:$FG,$A29,FALSE)-1,"") | I29: =IFERROR(VLOOKUP(I$2,'R.WEALTH-Cummulative'!$A:$FG,$A29,FALSE)-1,"") | J29: =IFERROR(VLOOKUP(J$2,'R.WEALTH-Cummulative'!$A:$FG,$A29,FALSE)-1,"") | K29: =IFERROR((VLOOKUP(K$2,'R.WEALTH-Cummulative'!$A:$FG,$A29,FALSE)^(1/(K$2/12)))-1,"") | L29: =IFERROR((VLOOKUP(L$2,'R.WEALTH-Cummulative'!$A:$FG,$A29,FALSE)^(1/(L$2/12)))-1,"") | M29: =IFERROR((VLOOKUP(M$2,'R.WEALTH-Cummulative'!$A:$FG,$A29,FALSE)^(1/(M$2/12)))-1,"") | N29: =IFERROR((VLOOKUP(N$2,'R.WEALTH-Cummulative'!$A:$FG,$A29,FALSE)^(1/(N$2/12)))-1,"") | O29: =IFERROR((VLOOKUP(O$2,'R.WEALTH-Cummulative'!$A:$FG,$A29,FALSE)^(1/(O$2/12)))-1,"") | P29: =IFERROR((VLOOKUP(P$2,'R.WEALTH-Cummulative'!$A:$FG,$A29,FALSE)^(1/(P$2/12)))-1,"") | Q29: =IFERROR((VLOOKUP(Q$2,'R.WEALTH-Cummulative'!$A:$FG,$A29,FALSE)^(1/(Q$2/12)))-1,"") | R29: =IFERROR((VLOOKUP(R$2,'R.WEALTH-Cummulative'!$A:$FG,$A29,FALSE)^(1/(R$2/12)))-1,"") | ... X29: =IFERROR((VLOOKUP(X$2,'R.WEALTH-Cummulative'!$A:$FG,$A29,FALSE)^(1/(X$2/12)))-1,"") | Y29: =VLOOKUP(Y$2,'Since Inception Returns'!$B:$AAB,Summary!A29-1,FALSE) -> 2.0021169 | Z29: =VLOOKUP(Z$2,'Since Inception Returns'!$B:$AAB,Summary!A29-1,FALSE) -> 0.072585731
B30: 17 | C30: HRT1_I | D30: HBB.I | E30: Blended Benchmark | F30: =IFERROR(VLOOKUP(F$2,'R.WEALTH-Cummulative (BM)'!$A:$FH,$B30,FALSE)-1,"") -> 0.012654162 | G30: =IFERROR(VLOOKUP(G$2,'R.WEALTH-Cummulative (BM)'!$A:$FH,$B30,FALSE)-1,"") -> 0.023448526 | H30: =IFERROR(VLOOKUP(H$2,'R.WEALTH-Cummulative (BM)'!$A:$FH,$B30,FALSE)-1,"") -> 0.067329051 | I30: =IFERROR(VLOOKUP(I$2,'R.WEALTH-Cummulative (BM)'!$A:$FH,$B30,FALSE)-1,"") -> 0.012654162 | J30: =IFERROR(VLOOKUP(J$2,'R.WEALTH-Cummulative (BM)'!$A:$FH,$B30,FALSE)-1,"") -> 0.26334915 | K30: =IFERROR((VLOOKUP(K$2,'R.WEALTH-Cummulative (BM)'!$A:$FH,$B30,FALSE)^(1/(K$2/12)))-1,"") -> 0.21965793 | L30: =IFERROR((VLOOKUP(L$2,'R.WEALTH-Cummulative (BM)'!$A:$FH,$B30,FALSE)^(1/(L$2/12)))-1,"") -> 0.10407552 | M30: =IFERROR((VLOOKUP(M$2,'R.WEALTH-Cummulative (BM)'!$A:$FH,$B30,FALSE)^(1/(M$2/12)))-1,"") -> 0.063878508 | N30: =IFERROR((VLOOKUP(N$2,'R.WEALTH-Cummulative (BM)'!$A:$FH,$B30,FALSE)^(1/(N$2/12)))-1,"") -> 0.11686847 | O30: =IFERROR((VLOOKUP(O$2,'R.WEALTH-Cummulative (BM)'!$A:$FH,$B30,FALSE)^(1/(O$2/12)))-1,"") -> 0.079766596 | P30: =IFERROR((VLOOKUP(P$2,'R.WEALTH-Cummulative (BM)'!$A:$FH,$B30,FALSE)^(1/(P$2/12)))-1,"") -> 0.092275655 | Q30: =IFERROR((VLOOKUP(Q$2,'R.WEALTH-Cummulative (BM)'!$A:$FH,$B30,FALSE)^(1/(Q$2/12)))-1,"") -> 0.087682421 | R30: =IFERROR((VLOOKUP(R$2,'R.WEALTH-Cummulative (BM)'!$A:$FH,$B30,FALSE)^(1/(R$2/12)))-1,"") -> 0.090022952 | ... X30: =IFERROR((VLOOKUP(X$2,'R.WEALTH-Cummulative (BM)'!$A:$FH,$B30,FALSE)^(1/(X$2/12)))-1,"") -> 0.095332584 | Y30: =VLOOKUP(Y$2,'Since Inception (BM)'!$B:$AAC,Summary!B30-1,FALSE) -> 4.0395811 | Z30: =VLOOKUP(Z$2,'Since Inception (BM)'!$B:$AAC,Summary!B30-1,FALSE) -> 0.10450254
A31: 18 | C31: HRT1_R | D31: HBB.R | E31: Harvest Banks & Buildings Income Fund | F31: =IFERROR(VLOOKUP(F$2,'R.WEALTH-Cummulative'!$A:$FG,$A31,FALSE)-1,"") | G31: =IFERROR(VLOOKUP(G$2,'R.WEALTH-Cummulative'!$A:$FG,$A31,FALSE)-1,"") | H31: =IFERROR(VLOOKUP(H$2,'R.WEALTH-Cummulative'!$A:$FG,$A31,FALSE)-1,"") | I31: =IFERROR(VLOOKUP(I$2,'R.WEALTH-Cummulative'!$A:$FG,$A31,FALSE)-1,"") | J31: =IFERROR(VLOOKUP(J$2,'R.WEALTH-Cummulative'!$A:$FG,$A31,FALSE)-1,"") | K31: =IFERROR((VLOOKUP(K$2,'R.WEALTH-Cummulative'!$A:$FG,$A31,FALSE)^(1/(K$2/12)))-1,"") | L31: =IFERROR((VLOOKUP(L$2,'R.WEALTH-Cummulative'!$A:$FG,$A31,FALSE)^(1/(L$2/12)))-1,"") | M31: =IFERROR((VLOOKUP(M$2,'R.WEALTH-Cummulative'!$A:$FG,$A31,FALSE)^(1/(M$2/12)))-1,"") | N31: =IFERROR((VLOOKUP(N$2,'R.WEALTH-Cummulative'!$A:$FG,$A31,FALSE)^(1/(N$2/12)))-1,"") | O31: =IFERROR((VLOOKUP(O$2,'R.WEALTH-Cummulative'!$A:$FG,$A31,FALSE)^(1/(O$2/12)))-1,"") | P31: =IFERROR((VLOOKUP(P$2,'R.WEALTH-Cummulative'!$A:$FG,$A31,FALSE)^(1/(P$2/12)))-1,"") | Q31: =IFERROR((VLOOKUP(Q$2,'R.WEALTH-Cummulative'!$A:$FG,$A31,FALSE)^(1/(Q$2/12)))-1,"") | R31: =IFERROR((VLOOKUP(R$2,'R.WEALTH-Cummulative'!$A:$FG,$A31,FALSE)^(1/(R$2/12)))-1,"") | ... X31: =IFERROR((VLOOKUP(X$2,'R.WEALTH-Cummulative'!$A:$FG,$A31,FALSE)^(1/(X$2/12)))-1,"") | Y31: =VLOOKUP(Y$2,'Since Inception Returns'!$B:$AAB,Summary!A31-1,FALSE) -> 1.6040805 | Z31: =VLOOKUP(Z$2,'Since Inception Returns'!$B:$AAB,Summary!A31-1,FALSE) -> 0.072349036
A32: 19 | C32: HRT1_A | D32: HBB.A | E32: Harvest Banks & Buildings Income Fund | F32: =IFERROR(VLOOKUP(F$2,'R.WEALTH-Cummulative'!$A:$FG,$A32,FALSE)-1,"") | G32: =IFERROR(VLOOKUP(G$2,'R.WEALTH-Cummulative'!$A:$FG,$A32,FALSE)-1,"") | H32: =IFERROR(VLOOKUP(H$2,'R.WEALTH-Cummulative'!$A:$FG,$A32,FALSE)-1,"") | I32: =IFERROR(VLOOKUP(I$2,'R.WEALTH-Cummulative'!$A:$FG,$A32,FALSE)-1,"") | J32: =IFERROR(VLOOKUP(J$2,'R.WEALTH-Cummulative'!$A:$FG,$A32,FALSE)-1,"") | K32: =IFERROR((VLOOKUP(K$2,'R.WEALTH-Cummulative'!$A:$FG,$A32,FALSE)^(1/(K$2/12)))-1,"") | L32: =IFERROR((VLOOKUP(L$2,'R.WEALTH-Cummulative'!$A:$FG,$A32,FALSE)^(1/(L$2/12)))-1,"") | M32: =IFERROR((VLOOKUP(M$2,'R.WEALTH-Cummulative'!$A:$FG,$A32,FALSE)^(1/(M$2/12)))-1,"") | N32: =IFERROR((VLOOKUP(N$2,'R.WEALTH-Cummulative'!$A:$FG,$A32,FALSE)^(1/(N$2/12)))-1,"") | O32: =IFERROR((VLOOKUP(O$2,'R.WEALTH-Cummulative'!$A:$FG,$A32,FALSE)^(1/(O$2/12)))-1,"") | P32: =IFERROR((VLOOKUP(P$2,'R.WEALTH-Cummulative'!$A:$FG,$A32,FALSE)^(1/(P$2/12)))-1,"") | Q32: =IFERROR((VLOOKUP(Q$2,'R.WEALTH-Cummulative'!$A:$FG,$A32,FALSE)^(1/(Q$2/12)))-1,"") | R32: =IFERROR((VLOOKUP(R$2,'R.WEALTH-Cummulative'!$A:$FG,$A32,FALSE)^(1/(R$2/12)))-1,"") | ... X32: =IFERROR((VLOOKUP(X$2,'R.WEALTH-Cummulative'!$A:$FG,$A32,FALSE)^(1/(X$2/12)))-1,"") | Y32: =VLOOKUP(Y$2,'Since Inception Returns'!$B:$AAB,Summary!A32-1,FALSE) -> 1.3178448 | Z32: =VLOOKUP(Z$2,'Since Inception Returns'!$B:$AAB,Summary!A32-1,FALSE) -> 0.063274396
A33: 20 | C33: HRT1_F | D33: HBB.F | E33: Harvest Banks & Buildings Income Fund | F33: =IFERROR(VLOOKUP(F$2,'R.WEALTH-Cummulative'!$A:$FG,$A33,FALSE)-1,"") | G33: =IFERROR(VLOOKUP(G$2,'R.WEALTH-Cummulative'!$A:$FG,$A33,FALSE)-1,"") | H33: =IFERROR(VLOOKUP(H$2,'R.WEALTH-Cummulative'!$A:$FG,$A33,FALSE)-1,"") | I33: =IFERROR(VLOOKUP(I$2,'R.WEALTH-Cummulative'!$A:$FG,$A33,FALSE)-1,"") | J33: =IFERROR(VLOOKUP(J$2,'R.WEALTH-Cummulative'!$A:$FG,$A33,FALSE)-1,"") | K33: =IFERROR((VLOOKUP(K$2,'R.WEALTH-Cummulative'!$A:$FG,$A33,FALSE)^(1/(K$2/12)))-1,"") | L33: =IFERROR((VLOOKUP(L$2,'R.WEALTH-Cummulative'!$A:$FG,$A33,FALSE)^(1/(L$2/12)))-1,"") | M33: =IFERROR((VLOOKUP(M$2,'R.WEALTH-Cummulative'!$A:$FG,$A33,FALSE)^(1/(M$2/12)))-1,"") | N33: =IFERROR((VLOOKUP(N$2,'R.WEALTH-Cummulative'!$A:$FG,$A33,FALSE)^(1/(N$2/12)))-1,"") | O33: =IFERROR((VLOOKUP(O$2,'R.WEALTH-Cummulative'!$A:$FG,$A33,FALSE)^(1/(O$2/12)))-1,"") | P33: =IFERROR((VLOOKUP(P$2,'R.WEALTH-Cummulative'!$A:$FG,$A33,FALSE)^(1/(P$2/12)))-1,"") | Q33: =IFERROR((VLOOKUP(Q$2,'R.WEALTH-Cummulative'!$A:$FG,$A33,FALSE)^(1/(Q$2/12)))-1,"") | R33: =IFERROR((VLOOKUP(R$2,'R.WEALTH-Cummulative'!$A:$FG,$A33,FALSE)^(1/(R$2/12)))-1,"") | ... X33: =IFERROR((VLOOKUP(X$2,'R.WEALTH-Cummulative'!$A:$FG,$A33,FALSE)^(1/(X$2/12)))-1,"") | Y33: =VLOOKUP(Y$2,'Since Inception Returns'!$B:$AAB,Summary!A33-1,FALSE) -> 1.8256985 | Z33: =VLOOKUP(Z$2,'Since Inception Returns'!$B:$AAB,Summary!A33-1,FALSE) -> 0.078760451
B34: 20 | C34: HRT1_I | D34: HBB R.A.F. | E34: Blended Benchmark | F34: =IFERROR(VLOOKUP(F$2,'R.WEALTH-Cummulative (BM)'!$A:$FH,$B34,FALSE)-1,"") -> 0.012654162 | G34: =IFERROR(VLOOKUP(G$2,'R.WEALTH-Cummulative (BM)'!$A:$FH,$B34,FALSE)-1,"") -> 0.023448526 | H34: =IFERROR(VLOOKUP(H$2,'R.WEALTH-Cummulative (BM)'!$A:$FH,$B34,FALSE)-1,"") -> 0.067329051 | I34: =IFERROR(VLOOKUP(I$2,'R.WEALTH-Cummulative (BM)'!$A:$FH,$B34,FALSE)-1,"") -> 0.012654162 | J34: =IFERROR(VLOOKUP(J$2,'R.WEALTH-Cummulative (BM)'!$A:$FH,$B34,FALSE)-1,"") -> 0.26334915 | K34: =IFERROR((VLOOKUP(K$2,'R.WEALTH-Cummulative (BM)'!$A:$FH,$B34,FALSE)^(1/(K$2/12)))-1,"") -> 0.21965793 | L34: =IFERROR((VLOOKUP(L$2,'R.WEALTH-Cummulative (BM)'!$A:$FH,$B34,FALSE)^(1/(L$2/12)))-1,"") -> 0.10407552 | M34: =IFERROR((VLOOKUP(M$2,'R.WEALTH-Cummulative (BM)'!$A:$FH,$B34,FALSE)^(1/(M$2/12)))-1,"") -> 0.063878508 | N34: =IFERROR((VLOOKUP(N$2,'R.WEALTH-Cummulative (BM)'!$A:$FH,$B34,FALSE)^(1/(N$2/12)))-1,"") -> 0.11686847 | O34: =IFERROR((VLOOKUP(O$2,'R.WEALTH-Cummulative (BM)'!$A:$FH,$B34,FALSE)^(1/(O$2/12)))-1,"") -> 0.079766596 | P34: =IFERROR((VLOOKUP(P$2,'R.WEALTH-Cummulative (BM)'!$A:$FH,$B34,FALSE)^(1/(P$2/12)))-1,"") -> 0.092275655 | Q34: =IFERROR((VLOOKUP(Q$2,'R.WEALTH-Cummulative (BM)'!$A:$FH,$B34,FALSE)^(1/(Q$2/12)))-1,"") -> 0.087682421 | R34: =IFERROR((VLOOKUP(R$2,'R.WEALTH-Cummulative (BM)'!$A:$FH,$B34,FALSE)^(1/(R$2/12)))-1,"") -> 0.090022952 | ... X34: =IFERROR((VLOOKUP(X$2,'R.WEALTH-Cummulative (BM)'!$A:$FH,$B34,FALSE)^(1/(X$2/12)))-1,"") | Y34: =VLOOKUP(Y$2,'Since Inception (BM)'!$B:$AAC,Summary!B34-1,FALSE) -> 2.8792209 | Z34: =VLOOKUP(Z$2,'Since Inception (BM)'!$B:$AAC,Summary!B34-1,FALSE) -> 0.099548351
A35: 21 | C35: HRT1_D | D35: HBB.D | E35: Harvest Banks & Buildings Income Fund | F35: =IFERROR(VLOOKUP(F$2,'R.WEALTH-Cummulative'!$A:$FG,$A35,FALSE)-1,"") | G35: =IFERROR(VLOOKUP(G$2,'R.WEALTH-Cummulative'!$A:$FG,$A35,FALSE)-1,"") | H35: =IFERROR(VLOOKUP(H$2,'R.WEALTH-Cummulative'!$A:$FG,$A35,FALSE)-1,"") | I35: =IFERROR(VLOOKUP(I$2,'R.WEALTH-Cummulative'!$A:$FG,$A35,FALSE)-1,"") | J35: =IFERROR(VLOOKUP(J$2,'R.WEALTH-Cummulative'!$A:$FG,$A35,FALSE)-1,"") | K35: =IFERROR((VLOOKUP(K$2,'R.WEALTH-Cummulative'!$A:$FG,$A35,FALSE)^(1/(K$2/12)))-1,"") | L35: =IFERROR((VLOOKUP(L$2,'R.WEALTH-Cummulative'!$A:$FG,$A35,FALSE)^(1/(L$2/12)))-1,"") | M35: =IFERROR((VLOOKUP(M$2,'R.WEALTH-Cummulative'!$A:$FG,$A35,FALSE)^(1/(M$2/12)))-1,"") | N35: =IFERROR((VLOOKUP(N$2,'R.WEALTH-Cummulative'!$A:$FG,$A35,FALSE)^(1/(N$2/12)))-1,"") | O35: =IFERROR((VLOOKUP(O$2,'R.WEALTH-Cummulative'!$A:$FG,$A35,FALSE)^(1/(O$2/12)))-1,"") | P35: =IFERROR((VLOOKUP(P$2,'R.WEALTH-Cummulative'!$A:$FG,$A35,FALSE)^(1/(P$2/12)))-1,"") | Q35: =IFERROR((VLOOKUP(Q$2,'R.WEALTH-Cummulative'!$A:$FG,$A35,FALSE)^(1/(Q$2/12)))-1,"") | R35: =IFERROR((VLOOKUP(R$2,'R.WEALTH-Cummulative'!$A:$FG,$A35,FALSE)^(1/(R$2/12)))-1,"") | ... X35: =IFERROR((VLOOKUP(X$2,'R.WEALTH-Cummulative'!$A:$FG,$A35,FALSE)^(1/(X$2/12)))-1,"") | Y35: =VLOOKUP(Y$2,'Since Inception Returns'!$B:$AAB,Summary!A35-1,FALSE) -> 0.82248974 | Z35: =VLOOKUP(Z$2,'Since Inception Returns'!$B:$AAB,Summary!A35-1,FALSE) -> 0.055925544
B36: 21 | C36: HRT1_D | D36: HBB.D | E36: Blended Benchmark | F36: =IFERROR(VLOOKUP(F$2,'R.WEALTH-Cummulative (BM)'!$A:$FH,$B36,FALSE)-1,"") -> 0.012654162 | G36: =IFERROR(VLOOKUP(G$2,'R.WEALTH-Cummulative (BM)'!$A:$FH,$B36,FALSE)-1,"") -> 0.023448526 | H36: =IFERROR(VLOOKUP(H$2,'R.WEALTH-Cummulative (BM)'!$A:$FH,$B36,FALSE)-1,"") -> 0.067329051 | I36: =IFERROR(VLOOKUP(I$2,'R.WEALTH-Cummulative (BM)'!$A:$FH,$B36,FALSE)-1,"") -> 0.012654162 | J36: =IFERROR(VLOOKUP(J$2,'R.WEALTH-Cummulative (BM)'!$A:$FH,$B36,FALSE)-1,"") -> 0.26334915 | K36: =IFERROR((VLOOKUP(K$2,'R.WEALTH-Cummulative (BM)'!$A:$FH,$B36,FALSE)^(1/(K$2/12)))-1,"") -> 0.21965793 | L36: =IFERROR((VLOOKUP(L$2,'R.WEALTH-Cummulative (BM)'!$A:$FH,$B36,FALSE)^(1/(L$2/12)))-1,"") -> 0.10407552 | M36: =IFERROR((VLOOKUP(M$2,'R.WEALTH-Cummulative (BM)'!$A:$FH,$B36,FALSE)^(1/(M$2/12)))-1,"") -> 0.063878508 | N36: =IFERROR((VLOOKUP(N$2,'R.WEALTH-Cummulative (BM)'!$A:$FH,$B36,FALSE)^(1/(N$2/12)))-1,"") -> 0.11686847 | O36: =IFERROR((VLOOKUP(O$2,'R.WEALTH-Cummulative (BM)'!$A:$FH,$B36,FALSE)^(1/(O$2/12)))-1,"") -> 0.079766596 | P36: =IFERROR((VLOOKUP(P$2,'R.WEALTH-Cummulative (BM)'!$A:$FH,$B36,FALSE)^(1/(P$2/12)))-1,"") -> 0.092275655 | Q36: =IFERROR((VLOOKUP(Q$2,'R.WEALTH-Cummulative (BM)'!$A:$FH,$B36,FALSE)^(1/(Q$2/12)))-1,"") -> 0.087682421 | R36: =IFERROR((VLOOKUP(R$2,'R.WEALTH-Cummulative (BM)'!$A:$FH,$B36,FALSE)^(1/(R$2/12)))-1,"") -> 0.090022952 | ... X36: =IFERROR((VLOOKUP(X$2,'R.WEALTH-Cummulative (BM)'!$A:$FH,$B36,FALSE)^(1/(X$2/12)))-1,"") | Y36: =VLOOKUP(Y$2,'Since Inception (BM)'!$B:$AAC,Summary!B36-1,FALSE) -> 1.6671958 | Z36: =VLOOKUP(Z$2,'Since Inception (BM)'!$B:$AAC,Summary!B36-1,FALSE) -> 0.088148233
A37: 22 | C37: HRT3_I | D37: HCF.I | E37: Harvest Canadian Income & Growth Fund | F37: =IFERROR(VLOOKUP(F$2,'R.WEALTH-Cummulative'!$A:$FG,$A37,FALSE)-1,"") | G37: =IFERROR(VLOOKUP(G$2,'R.WEALTH-Cummulative'!$A:$FG,$A37,FALSE)-1,"") | H37: =IFERROR(VLOOKUP(H$2,'R.WEALTH-Cummulative'!$A:$FG,$A37,FALSE)-1,"") | I37: =IFERROR(VLOOKUP(I$2,'R.WEALTH-Cummulative'!$A:$FG,$A37,FALSE)-1,"") | J37: =IFERROR(VLOOKUP(J$2,'R.WEALTH-Cummulative'!$A:$FG,$A37,FALSE)-1,"") | K37: =IFERROR((VLOOKUP(K$2,'R.WEALTH-Cummulative'!$A:$FG,$A37,FALSE)^(1/(K$2/12)))-1,"") | L37: =IFERROR((VLOOKUP(L$2,'R.WEALTH-Cummulative'!$A:$FG,$A37,FALSE)^(1/(L$2/12)))-1,"") | M37: =IFERROR((VLOOKUP(M$2,'R.WEALTH-Cummulative'!$A:$FG,$A37,FALSE)^(1/(M$2/12)))-1,"") | N37: =IFERROR((VLOOKUP(N$2,'R.WEALTH-Cummulative'!$A:$FG,$A37,FALSE)^(1/(N$2/12)))-1,"") | O37: =IFERROR((VLOOKUP(O$2,'R.WEALTH-Cummulative'!$A:$FG,$A37,FALSE)^(1/(O$2/12)))-1,"") | P37: =IFERROR((VLOOKUP(P$2,'R.WEALTH-Cummulative'!$A:$FG,$A37,FALSE)^(1/(P$2/12)))-1,"") | Q37: =IFERROR((VLOOKUP(Q$2,'R.WEALTH-Cummulative'!$A:$FG,$A37,FALSE)^(1/(Q$2/12)))-1,"") | R37: =IFERROR((VLOOKUP(R$2,'R.WEALTH-Cummulative'!$A:$FG,$A37,FALSE)^(1/(R$2/12)))-1,"") | ... X37: =IFERROR((VLOOKUP(X$2,'R.WEALTH-Cummulative'!$A:$FG,$A37,FALSE)^(1/(X$2/12)))-1,"") | Y37: =VLOOKUP(Y$2,'Since Inception Returns'!$B:$AAB,Summary!A37-1,FALSE) -> 1.1309889 | Z37: =VLOOKUP(Z$2,'Since Inception Returns'!$B:$AAB,Summary!A37-1,FALSE) -> 0.051722966
B38: 22 | C38: HRT3_I | D38: HCF.I | E38: S&P/TSX Composite Total Return Index | F38: =IFERROR(VLOOKUP(F$2,'R.WEALTH-Cummulative (BM)'!$A:$FH,$B38,FALSE)-1,"") -> 0.0083545968 | G38: =IFERROR(VLOOKUP(G$2,'R.WEALTH-Cummulative (BM)'!$A:$FH,$B38,FALSE)-1,"") -> 0.061151869 | H38: =IFERROR(VLOOKUP(H$2,'R.WEALTH-Cummulative (BM)'!$A:$FH,$B38,FALSE)-1,"") -> 0.18527224 | I38: =IFERROR(VLOOKUP(I$2,'R.WEALTH-Cummulative (BM)'!$A:$FH,$B38,FALSE)-1,"") -> 0.0083545968 | J38: =IFERROR(VLOOKUP(J$2,'R.WEALTH-Cummulative (BM)'!$A:$FH,$B38,FALSE)-1,"") -> 0.28321663 | K38: =IFERROR((VLOOKUP(K$2,'R.WEALTH-Cummulative (BM)'!$A:$FH,$B38,FALSE)^(1/(K$2/12)))-1,"") -> 0.26745875 | L38: =IFERROR((VLOOKUP(L$2,'R.WEALTH-Cummulative (BM)'!$A:$FH,$B38,FALSE)^(1/(L$2/12)))-1,"") -> 0.18892426 | M38: =IFERROR((VLOOKUP(M$2,'R.WEALTH-Cummulative (BM)'!$A:$FH,$B38,FALSE)^(1/(M$2/12)))-1,"") -> 0.14298057 | N38: =IFERROR((VLOOKUP(N$2,'R.WEALTH-Cummulative (BM)'!$A:$FH,$B38,FALSE)^(1/(N$2/12)))-1,"") -> 0.16358583 | O38: =IFERROR((VLOOKUP(O$2,'R.WEALTH-Cummulative (BM)'!$A:$FH,$B38,FALSE)^(1/(O$2/12)))-1,"") -> 0.14101323 | P38: =IFERROR((VLOOKUP(P$2,'R.WEALTH-Cummulative (BM)'!$A:$FH,$B38,FALSE)^(1/(P$2/12)))-1,"") -> 0.14225994 | Q38: =IFERROR((VLOOKUP(Q$2,'R.WEALTH-Cummulative (BM)'!$A:$FH,$B38,FALSE)^(1/(Q$2/12)))-1,"") -> 0.12409046 | R38: =IFERROR((VLOOKUP(R$2,'R.WEALTH-Cummulative (BM)'!$A:$FH,$B38,FALSE)^(1/(R$2/12)))-1,"") -> 0.11756204 | ... X38: =IFERROR((VLOOKUP(X$2,'R.WEALTH-Cummulative (BM)'!$A:$FH,$B38,FALSE)^(1/(X$2/12)))-1,"") -> 0.090837375 | Y38: =VLOOKUP(Y$2,'Since Inception (BM)'!$B:$AAC,Summary!B38-1,FALSE) -> 3.5026255 | Z38: =VLOOKUP(Z$2,'Since Inception (BM)'!$B:$AAC,Summary!B38-1,FALSE) -> 0.10135205
A39: 23 | C39: HRT3_R | D39: HCF.R | E39: Harvest Canadian Income & Growth Fund | F39: =IFERROR(VLOOKUP(F$2,'R.WEALTH-Cummulative'!$A:$FG,$A39,FALSE)-1,"") | G39: =IFERROR(VLOOKUP(G$2,'R.WEALTH-Cummulative'!$A:$FG,$A39,FALSE)-1,"") | H39: =IFERROR(VLOOKUP(H$2,'R.WEALTH-Cummulative'!$A:$FG,$A39,FALSE)-1,"") | I39: =IFERROR(VLOOKUP(I$2,'R.WEALTH-Cummulative'!$A:$FG,$A39,FALSE)-1,"") | J39: =IFERROR(VLOOKUP(J$2,'R.WEALTH-Cummulative'!$A:$FG,$A39,FALSE)-1,"") | K39: =IFERROR((VLOOKUP(K$2,'R.WEALTH-Cummulative'!$A:$FG,$A39,FALSE)^(1/(K$2/12)))-1,"") | L39: =IFERROR((VLOOKUP(L$2,'R.WEALTH-Cummulative'!$A:$FG,$A39,FALSE)^(1/(L$2/12)))-1,"") | M39: =IFERROR((VLOOKUP(M$2,'R.WEALTH-Cummulative'!$A:$FG,$A39,FALSE)^(1/(M$2/12)))-1,"") | N39: =IFERROR((VLOOKUP(N$2,'R.WEALTH-Cummulative'!$A:$FG,$A39,FALSE)^(1/(N$2/12)))-1,"") | O39: =IFERROR((VLOOKUP(O$2,'R.WEALTH-Cummulative'!$A:$FG,$A39,FALSE)^(1/(O$2/12)))-1,"") | P39: =IFERROR((VLOOKUP(P$2,'R.WEALTH-Cummulative'!$A:$FG,$A39,FALSE)^(1/(P$2/12)))-1,"") | Q39: =IFERROR((VLOOKUP(Q$2,'R.WEALTH-Cummulative'!$A:$FG,$A39,FALSE)^(1/(Q$2/12)))-1,"") | R39: =IFERROR((VLOOKUP(R$2,'R.WEALTH-Cummulative'!$A:$FG,$A39,FALSE)^(1/(R$2/12)))-1,"") | ... X39: =IFERROR((VLOOKUP(X$2,'R.WEALTH-Cummulative'!$A:$FG,$A39,FALSE)^(1/(X$2/12)))-1,"") | Y39: =VLOOKUP(Y$2,'Since Inception Returns'!$B:$AAB,Summary!A39-1,FALSE) -> 0.58188417 | Z39: =VLOOKUP(Z$2,'Since Inception Returns'!$B:$AAB,Summary!A39-1,FALSE) -> 0.035829944
A40: 24 | C40: HRT3_A | D40: HCF.A | E40: Harvest Canadian Income & Growth Fund | F40: =IFERROR(VLOOKUP(F$2,'R.WEALTH-Cummulative'!$A:$FG,$A40,FALSE)-1,"") | G40: =IFERROR(VLOOKUP(G$2,'R.WEALTH-Cummulative'!$A:$FG,$A40,FALSE)-1,"") | H40: =IFERROR(VLOOKUP(H$2,'R.WEALTH-Cummulative'!$A:$FG,$A40,FALSE)-1,"") | I40: =IFERROR(VLOOKUP(I$2,'R.WEALTH-Cummulative'!$A:$FG,$A40,FALSE)-1,"") | J40: =IFERROR(VLOOKUP(J$2,'R.WEALTH-Cummulative'!$A:$FG,$A40,FALSE)-1,"") | K40: =IFERROR((VLOOKUP(K$2,'R.WEALTH-Cummulative'!$A:$FG,$A40,FALSE)^(1/(K$2/12)))-1,"") | L40: =IFERROR((VLOOKUP(L$2,'R.WEALTH-Cummulative'!$A:$FG,$A40,FALSE)^(1/(L$2/12)))-1,"") | M40: =IFERROR((VLOOKUP(M$2,'R.WEALTH-Cummulative'!$A:$FG,$A40,FALSE)^(1/(M$2/12)))-1,"") | N40: =IFERROR((VLOOKUP(N$2,'R.WEALTH-Cummulative'!$A:$FG,$A40,FALSE)^(1/(N$2/12)))-1,"") | O40: =IFERROR((VLOOKUP(O$2,'R.WEALTH-Cummulative'!$A:$FG,$A40,FALSE)^(1/(O$2/12)))-1,"") | P40: =IFERROR((VLOOKUP(P$2,'R.WEALTH-Cummulative'!$A:$FG,$A40,FALSE)^(1/(P$2/12)))-1,"") | Q40: =IFERROR((VLOOKUP(Q$2,'R.WEALTH-Cummulative'!$A:$FG,$A40,FALSE)^(1/(Q$2/12)))-1,"") | R40: =IFERROR((VLOOKUP(R$2,'R.WEALTH-Cummulative'!$A:$FG,$A40,FALSE)^(1/(R$2/12)))-1,"") | ... X40: =IFERROR((VLOOKUP(X$2,'R.WEALTH-Cummulative'!$A:$FG,$A40,FALSE)^(1/(X$2/12)))-1,"") | Y40: =VLOOKUP(Y$2,'Since Inception Returns'!$B:$AAB,Summary!A40-1,FALSE) -> 0.54907012 | Z40: =VLOOKUP(Z$2,'Since Inception Returns'!$B:$AAB,Summary!A40-1,FALSE) -> 0.034164624
A41: 25 | C41: HRT3_F | D41: HCF.F | E41: Harvest Canadian Income & Growth Fund | F41: =IFERROR(VLOOKUP(F$2,'R.WEALTH-Cummulative'!$A:$FG,$A41,FALSE)-1,"") | G41: =IFERROR(VLOOKUP(G$2,'R.WEALTH-Cummulative'!$A:$FG,$A41,FALSE)-1,"") | H41: =IFERROR(VLOOKUP(H$2,'R.WEALTH-Cummulative'!$A:$FG,$A41,FALSE)-1,"") | I41: =IFERROR(VLOOKUP(I$2,'R.WEALTH-Cummulative'!$A:$FG,$A41,FALSE)-1,"") | J41: =IFERROR(VLOOKUP(J$2,'R.WEALTH-Cummulative'!$A:$FG,$A41,FALSE)-1,"") | K41: =IFERROR((VLOOKUP(K$2,'R.WEALTH-Cummulative'!$A:$FG,$A41,FALSE)^(1/(K$2/12)))-1,"") | L41: =IFERROR((VLOOKUP(L$2,'R.WEALTH-Cummulative'!$A:$FG,$A41,FALSE)^(1/(L$2/12)))-1,"") | M41: =IFERROR((VLOOKUP(M$2,'R.WEALTH-Cummulative'!$A:$FG,$A41,FALSE)^(1/(M$2/12)))-1,"") | N41: =IFERROR((VLOOKUP(N$2,'R.WEALTH-Cummulative'!$A:$FG,$A41,FALSE)^(1/(N$2/12)))-1,"") | O41: =IFERROR((VLOOKUP(O$2,'R.WEALTH-Cummulative'!$A:$FG,$A41,FALSE)^(1/(O$2/12)))-1,"") | P41: =IFERROR((VLOOKUP(P$2,'R.WEALTH-Cummulative'!$A:$FG,$A41,FALSE)^(1/(P$2/12)))-1,"") | Q41: =IFERROR((VLOOKUP(Q$2,'R.WEALTH-Cummulative'!$A:$FG,$A41,FALSE)^(1/(Q$2/12)))-1,"") | R41: =IFERROR((VLOOKUP(R$2,'R.WEALTH-Cummulative'!$A:$FG,$A41,FALSE)^(1/(R$2/12)))-1,"") | ... X41: =IFERROR((VLOOKUP(X$2,'R.WEALTH-Cummulative'!$A:$FG,$A41,FALSE)^(1/(X$2/12)))-1,"") | Y41: =VLOOKUP(Y$2,'Since Inception Returns'!$B:$AAB,Summary!A41-1,FALSE) -> 0.85656962 | Z41: =VLOOKUP(Z$2,'Since Inception Returns'!$B:$AAB,Summary!A41-1,FALSE) -> 0.048639041
B42: 25 | C42: HRT3_F | D42: HCF R.A.F. | E42: S&P/TSX Composite Total Return Index | F42: =IFERROR(VLOOKUP(F$2,'R.WEALTH-Cummulative (BM)'!$A:$FH,$B42,FALSE)-1,"") -> 0.0083545968 | G42: =IFERROR(VLOOKUP(G$2,'R.WEALTH-Cummulative (BM)'!$A:$FH,$B42,FALSE)-1,"") -> 0.061151869 | H42: =IFERROR(VLOOKUP(H$2,'R.WEALTH-Cummulative (BM)'!$A:$FH,$B42,FALSE)-1,"") -> 0.18527224 | I42: =IFERROR(VLOOKUP(I$2,'R.WEALTH-Cummulative (BM)'!$A:$FH,$B42,FALSE)-1,"") -> 0.0083545968 | J42: =IFERROR(VLOOKUP(J$2,'R.WEALTH-Cummulative (BM)'!$A:$FH,$B42,FALSE)-1,"") -> 0.28321663 | K42: =IFERROR((VLOOKUP(K$2,'R.WEALTH-Cummulative (BM)'!$A:$FH,$B42,FALSE)^(1/(K$2/12)))-1,"") -> 0.26745875 | L42: =IFERROR((VLOOKUP(L$2,'R.WEALTH-Cummulative (BM)'!$A:$FH,$B42,FALSE)^(1/(L$2/12)))-1,"") -> 0.18892426 | M42: =IFERROR((VLOOKUP(M$2,'R.WEALTH-Cummulative (BM)'!$A:$FH,$B42,FALSE)^(1/(M$2/12)))-1,"") -> 0.14298057 | N42: =IFERROR((VLOOKUP(N$2,'R.WEALTH-Cummulative (BM)'!$A:$FH,$B42,FALSE)^(1/(N$2/12)))-1,"") -> 0.16358583 | O42: =IFERROR((VLOOKUP(O$2,'R.WEALTH-Cummulative (BM)'!$A:$FH,$B42,FALSE)^(1/(O$2/12)))-1,"") -> 0.14101323 | P42: =IFERROR((VLOOKUP(P$2,'R.WEALTH-Cummulative (BM)'!$A:$FH,$B42,FALSE)^(1/(P$2/12)))-1,"") -> 0.14225994 | Q42: =IFERROR((VLOOKUP(Q$2,'R.WEALTH-Cummulative (BM)'!$A:$FH,$B42,FALSE)^(1/(Q$2/12)))-1,"") -> 0.12409046 | R42: =IFERROR((VLOOKUP(R$2,'R.WEALTH-Cummulative (BM)'!$A:$FH,$B42,FALSE)^(1/(R$2/12)))-1,"") -> 0.11756204 | ... X42: =IFERROR((VLOOKUP(X$2,'R.WEALTH-Cummulative (BM)'!$A:$FH,$B42,FALSE)^(1/(X$2/12)))-1,"") | Y42: =VLOOKUP(Y$2,'Since Inception (BM)'!$B:$AAC,Summary!B42-1,FALSE) -> 3.0904111 | Z42: =VLOOKUP(Z$2,'Since Inception (BM)'!$B:$AAC,Summary!B42-1,FALSE) -> 0.10903728
A43: 26 | C43: HRT3_D | D43: HCF.D | E43: Harvest Canadian Income & Growth Fund | F43: =IFERROR(VLOOKUP(F$2,'R.WEALTH-Cummulative'!$A:$FG,$A43,FALSE)-1,"") | G43: =IFERROR(VLOOKUP(G$2,'R.WEALTH-Cummulative'!$A:$FG,$A43,FALSE)-1,"") | H43: =IFERROR(VLOOKUP(H$2,'R.WEALTH-Cummulative'!$A:$FG,$A43,FALSE)-1,"") | I43: =IFERROR(VLOOKUP(I$2,'R.WEALTH-Cummulative'!$A:$FG,$A43,FALSE)-1,"") | J43: =IFERROR(VLOOKUP(J$2,'R.WEALTH-Cummulative'!$A:$FG,$A43,FALSE)-1,"") | K43: =IFERROR((VLOOKUP(K$2,'R.WEALTH-Cummulative'!$A:$FG,$A43,FALSE)^(1/(K$2/12)))-1,"") | L43: =IFERROR((VLOOKUP(L$2,'R.WEALTH-Cummulative'!$A:$FG,$A43,FALSE)^(1/(L$2/12)))-1,"") | M43: =IFERROR((VLOOKUP(M$2,'R.WEALTH-Cummulative'!$A:$FG,$A43,FALSE)^(1/(M$2/12)))-1,"") | N43: =IFERROR((VLOOKUP(N$2,'R.WEALTH-Cummulative'!$A:$FG,$A43,FALSE)^(1/(N$2/12)))-1,"") | O43: =IFERROR((VLOOKUP(O$2,'R.WEALTH-Cummulative'!$A:$FG,$A43,FALSE)^(1/(O$2/12)))-1,"") | P43: =IFERROR((VLOOKUP(P$2,'R.WEALTH-Cummulative'!$A:$FG,$A43,FALSE)^(1/(P$2/12)))-1,"") | Q43: =IFERROR((VLOOKUP(Q$2,'R.WEALTH-Cummulative'!$A:$FG,$A43,FALSE)^(1/(Q$2/12)))-1,"") | R43: =IFERROR((VLOOKUP(R$2,'R.WEALTH-Cummulative'!$A:$FG,$A43,FALSE)^(1/(R$2/12)))-1,"") | ... X43: =IFERROR((VLOOKUP(X$2,'R.WEALTH-Cummulative'!$A:$FG,$A43,FALSE)^(1/(X$2/12)))-1,"") | Y43: =VLOOKUP(Y$2,'Since Inception Returns'!$B:$AAB,Summary!A43-1,FALSE) -> 0.38431822 | Z43: =VLOOKUP(Z$2,'Since Inception Returns'!$B:$AAB,Summary!A43-1,FALSE) -> 0.029924069
B44: 26 | C44: HRT3_D | D44: HCF.D | E44: S&P/TSX Composite Total Return Index | F44: =IFERROR(VLOOKUP(F$2,'R.WEALTH-Cummulative (BM)'!$A:$FH,$B44,FALSE)-1,"") -> 0.0083545968 | G44: =IFERROR(VLOOKUP(G$2,'R.WEALTH-Cummulative (BM)'!$A:$FH,$B44,FALSE)-1,"") -> 0.061151869 | H44: =IFERROR(VLOOKUP(H$2,'R.WEALTH-Cummulative (BM)'!$A:$FH,$B44,FALSE)-1,"") -> 0.18527224 | I44: =IFERROR(VLOOKUP(I$2,'R.WEALTH-Cummulative (BM)'!$A:$FH,$B44,FALSE)-1,"") -> 0.0083545968 | J44: =IFERROR(VLOOKUP(J$2,'R.WEALTH-Cummulative (BM)'!$A:$FH,$B44,FALSE)-1,"") -> 0.28321663 | K44: =IFERROR((VLOOKUP(K$2,'R.WEALTH-Cummulative (BM)'!$A:$FH,$B44,FALSE)^(1/(K$2/12)))-1,"") -> 0.26745875 | L44: =IFERROR((VLOOKUP(L$2,'R.WEALTH-Cummulative (BM)'!$A:$FH,$B44,FALSE)^(1/(L$2/12)))-1,"") -> 0.18892426 | M44: =IFERROR((VLOOKUP(M$2,'R.WEALTH-Cummulative (BM)'!$A:$FH,$B44,FALSE)^(1/(M$2/12)))-1,"") -> 0.14298057 | N44: =IFERROR((VLOOKUP(N$2,'R.WEALTH-Cummulative (BM)'!$A:$FH,$B44,FALSE)^(1/(N$2/12)))-1,"") -> 0.16358583 | O44: =IFERROR((VLOOKUP(O$2,'R.WEALTH-Cummulative (BM)'!$A:$FH,$B44,FALSE)^(1/(O$2/12)))-1,"") -> 0.14101323 | P44: =IFERROR((VLOOKUP(P$2,'R.WEALTH-Cummulative (BM)'!$A:$FH,$B44,FALSE)^(1/(P$2/12)))-1,"") -> 0.14225994 | Q44: =IFERROR((VLOOKUP(Q$2,'R.WEALTH-Cummulative (BM)'!$A:$FH,$B44,FALSE)^(1/(Q$2/12)))-1,"") -> 0.12409046 | R44: =IFERROR((VLOOKUP(R$2,'R.WEALTH-Cummulative (BM)'!$A:$FH,$B44,FALSE)^(1/(R$2/12)))-1,"") -> 0.11756204 | ... X44: =IFERROR((VLOOKUP(X$2,'R.WEALTH-Cummulative (BM)'!$A:$FH,$B44,FALSE)^(1/(X$2/12)))-1,"") | Y44: =VLOOKUP(Y$2,'Since Inception (BM)'!$B:$AAC,Summary!B44-1,FALSE) -> 1.9819292 | Z44: =VLOOKUP(Z$2,'Since Inception (BM)'!$B:$AAC,Summary!B44-1,FALSE) -> 0.098650334
A45: 27 | C45: HRT9_A | D45: HBF | E45: Harvest Brand Leaders Plus Income ETF | F45: =IFERROR(VLOOKUP(F$2,'R.WEALTH-Cummulative'!$A:$FG,$A45,FALSE)-1,"") -> 9.3395099e-05 | G45: =IFERROR(VLOOKUP(G$2,'R.WEALTH-Cummulative'!$A:$FG,$A45,FALSE)-1,"") -> 0.0056333597 | H45: =IFERROR(VLOOKUP(H$2,'R.WEALTH-Cummulative'!$A:$FG,$A45,FALSE)-1,"") -> 0.097949563 | I45: =IFERROR(VLOOKUP(I$2,'R.WEALTH-Cummulative'!$A:$FG,$A45,FALSE)-1,"") -> 9.3395099e-05 | J45: =IFERROR(VLOOKUP(J$2,'R.WEALTH-Cummulative'!$A:$FG,$A45,FALSE)-1,"") -> 0.11805251 | K45: =IFERROR((VLOOKUP(K$2,'R.WEALTH-Cummulative'!$A:$FG,$A45,FALSE)^(1/(K$2/12)))-1,"") -> 0.14072633 | L45: =IFERROR((VLOOKUP(L$2,'R.WEALTH-Cummulative'!$A:$FG,$A45,FALSE)^(1/(L$2/12)))-1,"") -> 0.11458161 | M45: =IFERROR((VLOOKUP(M$2,'R.WEALTH-Cummulative'!$A:$FG,$A45,FALSE)^(1/(M$2/12)))-1,"") -> 0.059291356 | N45: =IFERROR((VLOOKUP(N$2,'R.WEALTH-Cummulative'!$A:$FG,$A45,FALSE)^(1/(N$2/12)))-1,"") -> 0.089489455 | O45: =IFERROR((VLOOKUP(O$2,'R.WEALTH-Cummulative'!$A:$FG,$A45,FALSE)^(1/(O$2/12)))-1,"") -> 0.089645801 | P45: =IFERROR((VLOOKUP(P$2,'R.WEALTH-Cummulative'!$A:$FG,$A45,FALSE)^(1/(P$2/12)))-1,"") -> 0.10516392 | Q45: =IFERROR((VLOOKUP(Q$2,'R.WEALTH-Cummulative'!$A:$FG,$A45,FALSE)^(1/(Q$2/12)))-1,"") -> 0.08685948 | R45: =IFERROR((VLOOKUP(R$2,'R.WEALTH-Cummulative'!$A:$FG,$A45,FALSE)^(1/(R$2/12)))-1,"") -> 0.10071869 | ... X45: =IFERROR((VLOOKUP(X$2,'R.WEALTH-Cummulative'!$A:$FG,$A45,FALSE)^(1/(X$2/12)))-1,"") | Y45: =VLOOKUP(Y$2,'Since Inception Returns'!$B:$AAB,Summary!A45-1,FALSE) -> 1.6331058 | Z45: =VLOOKUP(Z$2,'Since Inception Returns'!$B:$AAB,Summary!A45-1,FALSE) -> 0.087683982
B46: 27 | C46: HRT9_A | D46: HBF | E46: Solactive GBS United States 100 Equal Weight Index NTR | F46: =IFERROR(VLOOKUP(F$2,'R.WEALTH-Cummulative (BM)'!$A:$FH,$B46,FALSE)-1,"") -> 0.028536104 | G46: =IFERROR(VLOOKUP(G$2,'R.WEALTH-Cummulative (BM)'!$A:$FH,$B46,FALSE)-1,"") -> 0.048929859 | H46: =IFERROR(VLOOKUP(H$2,'R.WEALTH-Cummulative (BM)'!$A:$FH,$B46,FALSE)-1,"") -> 0.12180124 | I46: =IFERROR(VLOOKUP(I$2,'R.WEALTH-Cummulative (BM)'!$A:$FH,$B46,FALSE)-1,"") -> 0.028536104 | J46: =IFERROR(VLOOKUP(J$2,'R.WEALTH-Cummulative (BM)'!$A:$FH,$B46,FALSE)-1,"") -> 0.16753368 | K46: =IFERROR((VLOOKUP(K$2,'R.WEALTH-Cummulative (BM)'!$A:$FH,$B46,FALSE)^(1/(K$2/12)))-1,"") -> 0.18551682 | L46: =IFERROR((VLOOKUP(L$2,'R.WEALTH-Cummulative (BM)'!$A:$FH,$B46,FALSE)^(1/(L$2/12)))-1,"") -> 0.18222919 | M46: =IFERROR((VLOOKUP(M$2,'R.WEALTH-Cummulative (BM)'!$A:$FH,$B46,FALSE)^(1/(M$2/12)))-1,"") -> 0.11980941 | N46: =IFERROR((VLOOKUP(N$2,'R.WEALTH-Cummulative (BM)'!$A:$FH,$B46,FALSE)^(1/(N$2/12)))-1,"") -> 0.13479897 | O46: =IFERROR((VLOOKUP(O$2,'R.WEALTH-Cummulative (BM)'!$A:$FH,$B46,FALSE)^(1/(O$2/12)))-1,"") -> 0.14118152 | P46: =IFERROR((VLOOKUP(P$2,'R.WEALTH-Cummulative (BM)'!$A:$FH,$B46,FALSE)^(1/(P$2/12)))-1,"") -> 0.14703621 | Q46: =IFERROR((VLOOKUP(Q$2,'R.WEALTH-Cummulative (BM)'!$A:$FH,$B46,FALSE)^(1/(Q$2/12)))-1,"") -> 0.12308229 | R46: =IFERROR((VLOOKUP(R$2,'R.WEALTH-Cummulative (BM)'!$A:$FH,$B46,FALSE)^(1/(R$2/12)))-1,"") -> 0.13850159 | ... X46: =IFERROR((VLOOKUP(X$2,'R.WEALTH-Cummulative (BM)'!$A:$FH,$B46,FALSE)^(1/(X$2/12)))-1,"") | Y46: =VLOOKUP(Y$2,'Since Inception (BM)'!$B:$AAC,Summary!B46-1,FALSE) -> 2.8211882 | Z46: =VLOOKUP(Z$2,'Since Inception (BM)'!$B:$AAC,Summary!B46-1,FALSE) -> 0.12342284
A47: 28 | C47: HRT9_B | D47: HBF.B | E47: Harvest Brand Leaders Plus Income ETF | F47: =IFERROR(VLOOKUP(F$2,'R.WEALTH-Cummulative'!$A:$FG,$A47,FALSE)-1,"") -> -0.0063588058 | G47: =IFERROR(VLOOKUP(G$2,'R.WEALTH-Cummulative'!$A:$FG,$A47,FALSE)-1,"") -> -0.018144478 | H47: =IFERROR(VLOOKUP(H$2,'R.WEALTH-Cummulative'!$A:$FG,$A47,FALSE)-1,"") -> 0.089896494 | I47: =IFERROR(VLOOKUP(I$2,'R.WEALTH-Cummulative'!$A:$FG,$A47,FALSE)-1,"") -> -0.0063588058 | J47: =IFERROR(VLOOKUP(J$2,'R.WEALTH-Cummulative'!$A:$FG,$A47,FALSE)-1,"") -> 0.068016147 | K47: =IFERROR((VLOOKUP(K$2,'R.WEALTH-Cummulative'!$A:$FG,$A47,FALSE)^(1/(K$2/12)))-1,"") -> 0.1644338 | L47: =IFERROR((VLOOKUP(L$2,'R.WEALTH-Cummulative'!$A:$FG,$A47,FALSE)^(1/(L$2/12)))-1,"") -> 0.1368241 | M47: =IFERROR((VLOOKUP(M$2,'R.WEALTH-Cummulative'!$A:$FG,$A47,FALSE)^(1/(M$2/12)))-1,"") -> 0.09036527 | N47: =IFERROR((VLOOKUP(N$2,'R.WEALTH-Cummulative'!$A:$FG,$A47,FALSE)^(1/(N$2/12)))-1,"") -> 0.11393712 | O47: =IFERROR((VLOOKUP(O$2,'R.WEALTH-Cummulative'!$A:$FG,$A47,FALSE)^(1/(O$2/12)))-1,"") | P47: =IFERROR((VLOOKUP(P$2,'R.WEALTH-Cummulative'!$A:$FG,$A47,FALSE)^(1/(P$2/12)))-1,"") | Q47: =IFERROR((VLOOKUP(Q$2,'R.WEALTH-Cummulative'!$A:$FG,$A47,FALSE)^(1/(Q$2/12)))-1,"") | R47: =IFERROR((VLOOKUP(R$2,'R.WEALTH-Cummulative'!$A:$FG,$A47,FALSE)^(1/(R$2/12)))-1,"") | ... X47: =IFERROR((VLOOKUP(X$2,'R.WEALTH-Cummulative'!$A:$FG,$A47,FALSE)^(1/(X$2/12)))-1,"") | Y47: =VLOOKUP(Y$2,'Since Inception Returns'!$B:$AAB,Summary!A47-1,FALSE) -> 1.0437448 | Z47: =VLOOKUP(Z$2,'Since Inception Returns'!$B:$AAB,Summary!A47-1,FALSE) -> 0.1290312
B48: 28 | C48: HRT9_B | D48: HBF.B | E48: Solactive GBS United States 100 Equal Weight Index NTR | F48: =IFERROR(VLOOKUP(F$2,'R.WEALTH-Cummulative (BM)'!$A:$FH,$B48,FALSE)-1,"") -> 0.028536104 | G48: =IFERROR(VLOOKUP(G$2,'R.WEALTH-Cummulative (BM)'!$A:$FH,$B48,FALSE)-1,"") -> 0.048929859 | H48: =IFERROR(VLOOKUP(H$2,'R.WEALTH-Cummulative (BM)'!$A:$FH,$B48,FALSE)-1,"") -> 0.12180124 | I48: =IFERROR(VLOOKUP(I$2,'R.WEALTH-Cummulative (BM)'!$A:$FH,$B48,FALSE)-1,"") -> 0.028536104 | J48: =IFERROR(VLOOKUP(J$2,'R.WEALTH-Cummulative (BM)'!$A:$FH,$B48,FALSE)-1,"") -> 0.16753368 | K48: =IFERROR((VLOOKUP(K$2,'R.WEALTH-Cummulative (BM)'!$A:$FH,$B48,FALSE)^(1/(K$2/12)))-1,"") -> 0.18551682 | L48: =IFERROR((VLOOKUP(L$2,'R.WEALTH-Cummulative (BM)'!$A:$FH,$B48,FALSE)^(1/(L$2/12)))-1,"") -> 0.18222919 | M48: =IFERROR((VLOOKUP(M$2,'R.WEALTH-Cummulative (BM)'!$A:$FH,$B48,FALSE)^(1/(M$2/12)))-1,"") -> 0.11980941 | N48: =IFERROR((VLOOKUP(N$2,'R.WEALTH-Cummulative (BM)'!$A:$FH,$B48,FALSE)^(1/(N$2/12)))-1,"") -> 0.13479897 | O48: =IFERROR((VLOOKUP(O$2,'R.WEALTH-Cummulative (BM)'!$A:$FH,$B48,FALSE)^(1/(O$2/12)))-1,"") | P48: =IFERROR((VLOOKUP(P$2,'R.WEALTH-Cummulative (BM)'!$A:$FH,$B48,FALSE)^(1/(P$2/12)))-1,"") | Q48: =IFERROR((VLOOKUP(Q$2,'R.WEALTH-Cummulative (BM)'!$A:$FH,$B48,FALSE)^(1/(Q$2/12)))-1,"") | R48: =IFERROR((VLOOKUP(R$2,'R.WEALTH-Cummulative (BM)'!$A:$FH,$B48,FALSE)^(1/(R$2/12)))-1,"") | ... X48: =IFERROR((VLOOKUP(X$2,'R.WEALTH-Cummulative (BM)'!$A:$FH,$B48,FALSE)^(1/(X$2/12)))-1,"") | Y48: =VLOOKUP(Y$2,'Since Inception (BM)'!$B:$AAC,Summary!B48-1,FALSE) -> 1.433879 | Z48: =VLOOKUP(Z$2,'Since Inception (BM)'!$B:$AAC,Summary!B48-1,FALSE) -> 0.16302208
A49: 29 | C49: HRT9_U | D49: HBF.U | E49: Harvest Brand Leaders Plus Income ETF | F49: =IFERROR(VLOOKUP(F$2,'R.WEALTH-Cummulative'!$A:$FG,$A49,FALSE)-1,"") -> 0.001602704 | G49: =IFERROR(VLOOKUP(G$2,'R.WEALTH-Cummulative'!$A:$FG,$A49,FALSE)-1,"") -> 0.011367886 | H49: =IFERROR(VLOOKUP(H$2,'R.WEALTH-Cummulative'!$A:$FG,$A49,FALSE)-1,"") -> 0.10907983 | I49: =IFERROR(VLOOKUP(I$2,'R.WEALTH-Cummulative'!$A:$FG,$A49,FALSE)-1,"") -> 0.001602704 | J49: =IFERROR(VLOOKUP(J$2,'R.WEALTH-Cummulative'!$A:$FG,$A49,FALSE)-1,"") -> 0.13998044 | K49: =IFERROR((VLOOKUP(K$2,'R.WEALTH-Cummulative'!$A:$FG,$A49,FALSE)^(1/(K$2/12)))-1,"") -> 0.15707 | L49: =IFERROR((VLOOKUP(L$2,'R.WEALTH-Cummulative'!$A:$FG,$A49,FALSE)^(1/(L$2/12)))-1,"") -> 0.12812934 | M49: =IFERROR((VLOOKUP(M$2,'R.WEALTH-Cummulative'!$A:$FG,$A49,FALSE)^(1/(M$2/12)))-1,"") -> 0.071774613 | N49: =IFERROR((VLOOKUP(N$2,'R.WEALTH-Cummulative'!$A:$FG,$A49,FALSE)^(1/(N$2/12)))-1,"") -> 0.10001643 | O49: =IFERROR((VLOOKUP(O$2,'R.WEALTH-Cummulative'!$A:$FG,$A49,FALSE)^(1/(O$2/12)))-1,"") -> 0.10292777 | P49: =IFERROR((VLOOKUP(P$2,'R.WEALTH-Cummulative'!$A:$FG,$A49,FALSE)^(1/(P$2/12)))-1,"") -> 0.11770465 | Q49: =IFERROR((VLOOKUP(Q$2,'R.WEALTH-Cummulative'!$A:$FG,$A49,FALSE)^(1/(Q$2/12)))-1,"") -> 0.09863892 | R49: =IFERROR((VLOOKUP(R$2,'R.WEALTH-Cummulative'!$A:$FG,$A49,FALSE)^(1/(R$2/12)))-1,"") -> 0.11244978 | ... X49: =IFERROR((VLOOKUP(X$2,'R.WEALTH-Cummulative'!$A:$FG,$A49,FALSE)^(1/(X$2/12)))-1,"") | Y49: =VLOOKUP(Y$2,'Since Inception Returns'!$B:$AAB,Summary!A49-1,FALSE) -> 1.9492347 | Z49: =VLOOKUP(Z$2,'Since Inception Returns'!$B:$AAB,Summary!A49-1,FALSE) -> 0.098443103
B50: 29 | C50: HRT9_U | D50: HBF.U | E50: Solactive GBS United States 100 Equal Weight Index NTR | F50: =IFERROR(VLOOKUP(F$2,'R.WEALTH-Cummulative (BM)'!$A:$FH,$B50,FALSE)-1,"") -> 0.028536104 | G50: =IFERROR(VLOOKUP(G$2,'R.WEALTH-Cummulative (BM)'!$A:$FH,$B50,FALSE)-1,"") -> 0.048929859 | H50: =IFERROR(VLOOKUP(H$2,'R.WEALTH-Cummulative (BM)'!$A:$FH,$B50,FALSE)-1,"") -> 0.12180124 | I50: =IFERROR(VLOOKUP(I$2,'R.WEALTH-Cummulative (BM)'!$A:$FH,$B50,FALSE)-1,"") -> 0.028536104 | J50: =IFERROR(VLOOKUP(J$2,'R.WEALTH-Cummulative (BM)'!$A:$FH,$B50,FALSE)-1,"") -> 0.16753368 | K50: =IFERROR((VLOOKUP(K$2,'R.WEALTH-Cummulative (BM)'!$A:$FH,$B50,FALSE)^(1/(K$2/12)))-1,"") -> 0.18551682 | L50: =IFERROR((VLOOKUP(L$2,'R.WEALTH-Cummulative (BM)'!$A:$FH,$B50,FALSE)^(1/(L$2/12)))-1,"") -> 0.18222919 | M50: =IFERROR((VLOOKUP(M$2,'R.WEALTH-Cummulative (BM)'!$A:$FH,$B50,FALSE)^(1/(M$2/12)))-1,"") -> 0.11980941 | N50: =IFERROR((VLOOKUP(N$2,'R.WEALTH-Cummulative (BM)'!$A:$FH,$B50,FALSE)^(1/(N$2/12)))-1,"") -> 0.13479897 | O50: =IFERROR((VLOOKUP(O$2,'R.WEALTH-Cummulative (BM)'!$A:$FH,$B50,FALSE)^(1/(O$2/12)))-1,"") -> 0.14118152 | P50: =IFERROR((VLOOKUP(P$2,'R.WEALTH-Cummulative (BM)'!$A:$FH,$B50,FALSE)^(1/(P$2/12)))-1,"") -> 0.14703621 | Q50: =IFERROR((VLOOKUP(Q$2,'R.WEALTH-Cummulative (BM)'!$A:$FH,$B50,FALSE)^(1/(Q$2/12)))-1,"") -> 0.12308229 | R50: =IFERROR((VLOOKUP(R$2,'R.WEALTH-Cummulative (BM)'!$A:$FH,$B50,FALSE)^(1/(R$2/12)))-1,"") -> 0.13850159 | ... X50: =IFERROR((VLOOKUP(X$2,'R.WEALTH-Cummulative (BM)'!$A:$FH,$B50,FALSE)^(1/(X$2/12)))-1,"") | Y50: =VLOOKUP(Y$2,'Since Inception (BM)'!$B:$AAC,Summary!B50-1,FALSE) -> 2.8211882 | Z50: =VLOOKUP(Z$2,'Since Inception (BM)'!$B:$AAC,Summary!B50-1,FALSE) -> 0.12342284
A51: 30 | C51: HRTF | D51: HGGG | E51: Harvest Global Gold Giants Index ETF | F51: =IFERROR(VLOOKUP(F$2,'R.WEALTH-Cummulative'!$A:$FG,$A51,FALSE)-1,"") -> 0.079774346 | G51: =IFERROR(VLOOKUP(G$2,'R.WEALTH-Cummulative'!$A:$FG,$A51,FALSE)-1,"") -> 0.31394586 | H51: =IFERROR(VLOOKUP(H$2,'R.WEALTH-Cummulative'!$A:$FG,$A51,FALSE)-1,"") -> 0.97695586 | I51: =IFERROR(VLOOKUP(I$2,'R.WEALTH-Cummulative'!$A:$FG,$A51,FALSE)-1,"") -> 0.079774346 | J51: =IFERROR(VLOOKUP(J$2,'R.WEALTH-Cummulative'!$A:$FG,$A51,FALSE)-1,"") -> 1.4919783 | K51: =IFERROR((VLOOKUP(K$2,'R.WEALTH-Cummulative'!$A:$FG,$A51,FALSE)^(1/(K$2/12)))-1,"") -> 1.012678 | L51: =IFERROR((VLOOKUP(L$2,'R.WEALTH-Cummulative'!$A:$FG,$A51,FALSE)^(1/(L$2/12)))-1,"") -> 0.51632314 | M51: =IFERROR((VLOOKUP(M$2,'R.WEALTH-Cummulative'!$A:$FG,$A51,FALSE)^(1/(M$2/12)))-1,"") -> 0.40985735 | N51: =IFERROR((VLOOKUP(N$2,'R.WEALTH-Cummulative'!$A:$FG,$A51,FALSE)^(1/(N$2/12)))-1,"") -> 0.27134146 | O51: =IFERROR((VLOOKUP(O$2,'R.WEALTH-Cummulative'!$A:$FG,$A51,FALSE)^(1/(O$2/12)))-1,"") -> 0.2542819 | P51: =IFERROR((VLOOKUP(P$2,'R.WEALTH-Cummulative'!$A:$FG,$A51,FALSE)^(1/(P$2/12)))-1,"") -> 0.24927823 | Q51: =IFERROR((VLOOKUP(Q$2,'R.WEALTH-Cummulative'!$A:$FG,$A51,FALSE)^(1/(Q$2/12)))-1,"") | R51: =IFERROR((VLOOKUP(R$2,'R.WEALTH-Cummulative'!$A:$FG,$A51,FALSE)^(1/(R$2/12)))-1,"") | ... X51: =IFERROR((VLOOKUP(X$2,'R.WEALTH-Cummulative'!$A:$FG,$A51,FALSE)^(1/(X$2/12)))-1,"") | Y51: =VLOOKUP(Y$2,'Since Inception Returns'!$B:$AAB,Summary!A51-1,FALSE) -> 4.0249849 | Z51: =VLOOKUP(Z$2,'Since Inception Returns'!$B:$AAB,Summary!A51-1,FALSE) -> 0.25702979
B52: 30 | C52: HRTF | D52: HGGG | E52: Solactive Global Gold Giants Index TR | F52: =IFERROR(VLOOKUP(F$2,'R.WEALTH-Cummulative (BM)'!$A:$FH,$B52,FALSE)-1,"") -> 0.080620155 | G52: =IFERROR(VLOOKUP(G$2,'R.WEALTH-Cummulative (BM)'!$A:$FH,$B52,FALSE)-1,"") -> 0.31951417 | H52: =IFERROR(VLOOKUP(H$2,'R.WEALTH-Cummulative (BM)'!$A:$FH,$B52,FALSE)-1,"") -> 0.99842144 | I52: =IFERROR(VLOOKUP(I$2,'R.WEALTH-Cummulative (BM)'!$A:$FH,$B52,FALSE)-1,"") -> 0.080620155 | J52: =IFERROR(VLOOKUP(J$2,'R.WEALTH-Cummulative (BM)'!$A:$FH,$B52,FALSE)-1,"") -> 1.5419194 | K52: =IFERROR((VLOOKUP(K$2,'R.WEALTH-Cummulative (BM)'!$A:$FH,$B52,FALSE)^(1/(K$2/12)))-1,"") -> 1.0493736 | L52: =IFERROR((VLOOKUP(L$2,'R.WEALTH-Cummulative (BM)'!$A:$FH,$B52,FALSE)^(1/(L$2/12)))-1,"") -> 0.53942037 | M52: =IFERROR((VLOOKUP(M$2,'R.WEALTH-Cummulative (BM)'!$A:$FH,$B52,FALSE)^(1/(M$2/12)))-1,"") -> 0.42881428 | N52: =IFERROR((VLOOKUP(N$2,'R.WEALTH-Cummulative (BM)'!$A:$FH,$B52,FALSE)^(1/(N$2/12)))-1,"") -> 0.2868874 | O52: =IFERROR((VLOOKUP(O$2,'R.WEALTH-Cummulative (BM)'!$A:$FH,$B52,FALSE)^(1/(O$2/12)))-1,"") -> 0.26883391 | P52: =IFERROR((VLOOKUP(P$2,'R.WEALTH-Cummulative (BM)'!$A:$FH,$B52,FALSE)^(1/(P$2/12)))-1,"") -> 0.26373816 | Q52: =IFERROR((VLOOKUP(Q$2,'R.WEALTH-Cummulative (BM)'!$A:$FH,$B52,FALSE)^(1/(Q$2/12)))-1,"") | R52: =IFERROR((VLOOKUP(R$2,'R.WEALTH-Cummulative (BM)'!$A:$FH,$B52,FALSE)^(1/(R$2/12)))-1,"") | ... X52: =IFERROR((VLOOKUP(X$2,'R.WEALTH-Cummulative (BM)'!$A:$FH,$B52,FALSE)^(1/(X$2/12)))-1,"") | Y52: =VLOOKUP(Y$2,'Since Inception (BM)'!$B:$AAC,Summary!B52-1,FALSE) -> 4.4683533 | Z52: =VLOOKUP(Z$2,'Since Inception (BM)'!$B:$AAC,Summary!B52-1,FALSE) -> 0.27218062
A53: 31 | C53: HRTG | D53: HGR | E53: Harvest Global REIT Leaders Income ETF | F53: =IFERROR(VLOOKUP(F$2,'R.WEALTH-Cummulative'!$A:$FG,$A53,FALSE)-1,"") -> 0.024899083 | G53: =IFERROR(VLOOKUP(G$2,'R.WEALTH-Cummulative'!$A:$FG,$A53,FALSE)-1,"") -> 0.014768331 | H53: =IFERROR(VLOOKUP(H$2,'R.WEALTH-Cummulative'!$A:$FG,$A53,FALSE)-1,"") -> 0.00074045823 | I53: =IFERROR(VLOOKUP(I$2,'R.WEALTH-Cummulative'!$A:$FG,$A53,FALSE)-1,"") -> 0.024899083 | J53: =IFERROR(VLOOKUP(J$2,'R.WEALTH-Cummulative'!$A:$FG,$A53,FALSE)-1,"") -> 0.007734841 | K53: =IFERROR((VLOOKUP(K$2,'R.WEALTH-Cummulative'!$A:$FG,$A53,FALSE)^(1/(K$2/12)))-1,"") -> 0.04351792 | L53: =IFERROR((VLOOKUP(L$2,'R.WEALTH-Cummulative'!$A:$FG,$A53,FALSE)^(1/(L$2/12)))-1,"") -> 0.0018639034 | M53: =IFERROR((VLOOKUP(M$2,'R.WEALTH-Cummulative'!$A:$FG,$A53,FALSE)^(1/(M$2/12)))-1,"") -> -0.044005213 | N53: =IFERROR((VLOOKUP(N$2,'R.WEALTH-Cummulative'!$A:$FG,$A53,FALSE)^(1/(N$2/12)))-1,"") -> -0.013283406 | O53: =IFERROR((VLOOKUP(O$2,'R.WEALTH-Cummulative'!$A:$FG,$A53,FALSE)^(1/(O$2/12)))-1,"") -> -0.030385079 | P53: =IFERROR((VLOOKUP(P$2,'R.WEALTH-Cummulative'!$A:$FG,$A53,FALSE)^(1/(P$2/12)))-1,"") -> -0.0060694023 | Q53: =IFERROR((VLOOKUP(Q$2,'R.WEALTH-Cummulative'!$A:$FG,$A53,FALSE)^(1/(Q$2/12)))-1,"") -> -0.0016479654 | R53: =IFERROR((VLOOKUP(R$2,'R.WEALTH-Cummulative'!$A:$FG,$A53,FALSE)^(1/(R$2/12)))-1,"") | ... X53: =IFERROR((VLOOKUP(X$2,'R.WEALTH-Cummulative'!$A:$FG,$A53,FALSE)^(1/(X$2/12)))-1,"") | Y53: =VLOOKUP(Y$2,'Since Inception Returns'!$B:$AAB,Summary!A53-1,FALSE) -> -0.0018937803 | Z53: =VLOOKUP(Z$2,'Since Inception Returns'!$B:$AAB,Summary!A53-1,FALSE) -> -0.00022033641
B54: 31 | C54: HRTG | D54: HGR | E54: MSCI World Real Estate Investment Trusts Gross TR Local | F54: =IFERROR(VLOOKUP(F$2,'R.WEALTH-Cummulative (BM)'!$A:$FH,$B54,FALSE)-1,"") -> 0.025833804 | G54: =IFERROR(VLOOKUP(G$2,'R.WEALTH-Cummulative (BM)'!$A:$FH,$B54,FALSE)-1,"") -> 0.017733202 | H54: =IFERROR(VLOOKUP(H$2,'R.WEALTH-Cummulative (BM)'!$A:$FH,$B54,FALSE)-1,"") -> 0.028965008 | I54: =IFERROR(VLOOKUP(I$2,'R.WEALTH-Cummulative (BM)'!$A:$FH,$B54,FALSE)-1,"") -> 0.025833804 | J54: =IFERROR(VLOOKUP(J$2,'R.WEALTH-Cummulative (BM)'!$A:$FH,$B54,FALSE)-1,"") -> 0.046290284 | K54: =IFERROR((VLOOKUP(K$2,'R.WEALTH-Cummulative (BM)'!$A:$FH,$B54,FALSE)^(1/(K$2/12)))-1,"") -> 0.076240888 | L54: =IFERROR((VLOOKUP(L$2,'R.WEALTH-Cummulative (BM)'!$A:$FH,$B54,FALSE)^(1/(L$2/12)))-1,"") -> 0.041073446 | M54: =IFERROR((VLOOKUP(M$2,'R.WEALTH-Cummulative (BM)'!$A:$FH,$B54,FALSE)^(1/(M$2/12)))-1,"") -> 0.0041348222 | N54: =IFERROR((VLOOKUP(N$2,'R.WEALTH-Cummulative (BM)'!$A:$FH,$B54,FALSE)^(1/(N$2/12)))-1,"") -> 0.053377067 | O54: =IFERROR((VLOOKUP(O$2,'R.WEALTH-Cummulative (BM)'!$A:$FH,$B54,FALSE)^(1/(O$2/12)))-1,"") -> 0.031626823 | P54: =IFERROR((VLOOKUP(P$2,'R.WEALTH-Cummulative (BM)'!$A:$FH,$B54,FALSE)^(1/(P$2/12)))-1,"") -> 0.051298778 | Q54: =IFERROR((VLOOKUP(Q$2,'R.WEALTH-Cummulative (BM)'!$A:$FH,$B54,FALSE)^(1/(Q$2/12)))-1,"") -> 0.056421179 | R54: =IFERROR((VLOOKUP(R$2,'R.WEALTH-Cummulative (BM)'!$A:$FH,$B54,FALSE)^(1/(R$2/12)))-1,"") | ... X54: =IFERROR((VLOOKUP(X$2,'R.WEALTH-Cummulative (BM)'!$A:$FH,$B54,FALSE)^(1/(X$2/12)))-1,"") | Y54: =VLOOKUP(Y$2,'Since Inception (BM)'!$B:$AAC,Summary!B54-1,FALSE) -> 0.57648574 | Z54: =VLOOKUP(Z$2,'Since Inception (BM)'!$B:$AAC,Summary!B54-1,FALSE) -> 0.054341905
A55: 32 | C55: HRTH_A | D55: HHL | E55: Harvest Healthcare Leaders Income ETF | F55: =IFERROR(VLOOKUP(F$2,'R.WEALTH-Cummulative'!$A:$FG,$A55,FALSE)-1,"") -> -0.0058851041 | G55: =IFERROR(VLOOKUP(G$2,'R.WEALTH-Cummulative'!$A:$FG,$A55,FALSE)-1,"") -> 0.051257079 | H55: =IFERROR(VLOOKUP(H$2,'R.WEALTH-Cummulative'!$A:$FG,$A55,FALSE)-1,"") -> 0.15224509 | I55: =IFERROR(VLOOKUP(I$2,'R.WEALTH-Cummulative'!$A:$FG,$A55,FALSE)-1,"") -> -0.0058851041 | J55: =IFERROR(VLOOKUP(J$2,'R.WEALTH-Cummulative'!$A:$FG,$A55,FALSE)-1,"") -> 0.031648917 | K55: =IFERROR((VLOOKUP(K$2,'R.WEALTH-Cummulative'!$A:$FG,$A55,FALSE)^(1/(K$2/12)))-1,"") -> 0.050047008 | L55: =IFERROR((VLOOKUP(L$2,'R.WEALTH-Cummulative'!$A:$FG,$A55,FALSE)^(1/(L$2/12)))-1,"") -> 0.071538588 | M55: =IFERROR((VLOOKUP(M$2,'R.WEALTH-Cummulative'!$A:$FG,$A55,FALSE)^(1/(M$2/12)))-1,"") -> 0.065137195 | N55: =IFERROR((VLOOKUP(N$2,'R.WEALTH-Cummulative'!$A:$FG,$A55,FALSE)^(1/(N$2/12)))-1,"") -> 0.08817941 | O55: =IFERROR((VLOOKUP(O$2,'R.WEALTH-Cummulative'!$A:$FG,$A55,FALSE)^(1/(O$2/12)))-1,"") -> 0.088986028 | P55: =IFERROR((VLOOKUP(P$2,'R.WEALTH-Cummulative'!$A:$FG,$A55,FALSE)^(1/(P$2/12)))-1,"") -> 0.085542044 | Q55: =IFERROR((VLOOKUP(Q$2,'R.WEALTH-Cummulative'!$A:$FG,$A55,FALSE)^(1/(Q$2/12)))-1,"") -> 0.075881957 | R55: =IFERROR((VLOOKUP(R$2,'R.WEALTH-Cummulative'!$A:$FG,$A55,FALSE)^(1/(R$2/12)))-1,"") -> 0.085966326 | ... X55: =IFERROR((VLOOKUP(X$2,'R.WEALTH-Cummulative'!$A:$FG,$A55,FALSE)^(1/(X$2/12)))-1,"") | Y55: =VLOOKUP(Y$2,'Since Inception Returns'!$B:$AAB,Summary!A55-1,FALSE) -> 1.1057619 | Z55: =VLOOKUP(Z$2,'Since Inception Returns'!$B:$AAB,Summary!A55-1,FALSE) -> 0.069271685
B56: 32 | C56: HRTH_A | D56: HHL | E56: MSCI World Health Care Net Total Return USD Index | F56: =IFERROR(VLOOKUP(F$2,'R.WEALTH-Cummulative (BM)'!$A:$FH,$B56,FALSE)-1,"") -> 0.010953014 | G56: =IFERROR(VLOOKUP(G$2,'R.WEALTH-Cummulative (BM)'!$A:$FH,$B56,FALSE)-1,"") -> 0.084428037 | H56: =IFERROR(VLOOKUP(H$2,'R.WEALTH-Cummulative (BM)'!$A:$FH,$B56,FALSE)-1,"") -> 0.18692932 | I56: =IFERROR(VLOOKUP(I$2,'R.WEALTH-Cummulative (BM)'!$A:$FH,$B56,FALSE)-1,"") -> 0.010953014 | J56: =IFERROR(VLOOKUP(J$2,'R.WEALTH-Cummulative (BM)'!$A:$FH,$B56,FALSE)-1,"") -> 0.091091301 | K56: =IFERROR((VLOOKUP(K$2,'R.WEALTH-Cummulative (BM)'!$A:$FH,$B56,FALSE)^(1/(K$2/12)))-1,"") -> 0.069243604 | L56: =IFERROR((VLOOKUP(L$2,'R.WEALTH-Cummulative (BM)'!$A:$FH,$B56,FALSE)^(1/(L$2/12)))-1,"") -> 0.0702882 | M56: =IFERROR((VLOOKUP(M$2,'R.WEALTH-Cummulative (BM)'!$A:$FH,$B56,FALSE)^(1/(M$2/12)))-1,"") -> 0.056114545 | N56: =IFERROR((VLOOKUP(N$2,'R.WEALTH-Cummulative (BM)'!$A:$FH,$B56,FALSE)^(1/(N$2/12)))-1,"") -> 0.064327671 | O56: =IFERROR((VLOOKUP(O$2,'R.WEALTH-Cummulative (BM)'!$A:$FH,$B56,FALSE)^(1/(O$2/12)))-1,"") -> 0.080298061 | P56: =IFERROR((VLOOKUP(P$2,'R.WEALTH-Cummulative (BM)'!$A:$FH,$B56,FALSE)^(1/(P$2/12)))-1,"") -> 0.090725588 | Q56: =IFERROR((VLOOKUP(Q$2,'R.WEALTH-Cummulative (BM)'!$A:$FH,$B56,FALSE)^(1/(Q$2/12)))-1,"") -> 0.081717353 | R56: =IFERROR((VLOOKUP(R$2,'R.WEALTH-Cummulative (BM)'!$A:$FH,$B56,FALSE)^(1/(R$2/12)))-1,"") -> 0.098067164 | ... X56: =IFERROR((VLOOKUP(X$2,'R.WEALTH-Cummulative (BM)'!$A:$FH,$B56,FALSE)^(1/(X$2/12)))-1,"") | Y56: =VLOOKUP(Y$2,'Since Inception (BM)'!$B:$AAC,Summary!B56-1,FALSE) -> 1.3015007 | Z56: =VLOOKUP(Z$2,'Since Inception (BM)'!$B:$AAC,Summary!B56-1,FALSE) -> 0.07785414
A57: 33 | C57: HRTH_B | D57: HHL.B | E57: Harvest Healthcare Leaders Income ETF | F57: =IFERROR(VLOOKUP(F$2,'R.WEALTH-Cummulative'!$A:$FG,$A57,FALSE)-1,"") -> -0.012635319 | G57: =IFERROR(VLOOKUP(G$2,'R.WEALTH-Cummulative'!$A:$FG,$A57,FALSE)-1,"") -> 0.025626558 | H57: =IFERROR(VLOOKUP(H$2,'R.WEALTH-Cummulative'!$A:$FG,$A57,FALSE)-1,"") -> 0.14239215 | I57: =IFERROR(VLOOKUP(I$2,'R.WEALTH-Cummulative'!$A:$FG,$A57,FALSE)-1,"") -> -0.012635319 | J57: =IFERROR(VLOOKUP(J$2,'R.WEALTH-Cummulative'!$A:$FG,$A57,FALSE)-1,"") -> -0.0151065 | K57: =IFERROR((VLOOKUP(K$2,'R.WEALTH-Cummulative'!$A:$FG,$A57,FALSE)^(1/(K$2/12)))-1,"") -> 0.071658577 | L57: =IFERROR((VLOOKUP(L$2,'R.WEALTH-Cummulative'!$A:$FG,$A57,FALSE)^(1/(L$2/12)))-1,"") -> 0.09218425 | M57: =IFERROR((VLOOKUP(M$2,'R.WEALTH-Cummulative'!$A:$FG,$A57,FALSE)^(1/(M$2/12)))-1,"") -> 0.094801641 | N57: =IFERROR((VLOOKUP(N$2,'R.WEALTH-Cummulative'!$A:$FG,$A57,FALSE)^(1/(N$2/12)))-1,"") -> 0.11105477 | O57: =IFERROR((VLOOKUP(O$2,'R.WEALTH-Cummulative'!$A:$FG,$A57,FALSE)^(1/(O$2/12)))-1,"") | P57: =IFERROR((VLOOKUP(P$2,'R.WEALTH-Cummulative'!$A:$FG,$A57,FALSE)^(1/(P$2/12)))-1,"") | Q57: =IFERROR((VLOOKUP(Q$2,'R.WEALTH-Cummulative'!$A:$FG,$A57,FALSE)^(1/(Q$2/12)))-1,"") | R57: =IFERROR((VLOOKUP(R$2,'R.WEALTH-Cummulative'!$A:$FG,$A57,FALSE)^(1/(R$2/12)))-1,"") | ... X57: =IFERROR((VLOOKUP(X$2,'R.WEALTH-Cummulative'!$A:$FG,$A57,FALSE)^(1/(X$2/12)))-1,"") | Y57: =VLOOKUP(Y$2,'Since Inception Returns'!$B:$AAB,Summary!A57-1,FALSE) -> 0.78925063 | Z57: =VLOOKUP(Z$2,'Since Inception Returns'!$B:$AAB,Summary!A57-1,FALSE) -> 0.10382417
B58: 33 | C58: HRTH_B | D58: HHL.B | E58: MSCI World Health Care Net Total Return USD Index | F58: =IFERROR(VLOOKUP(F$2,'R.WEALTH-Cummulative (BM)'!$A:$FH,$B58,FALSE)-1,"") -> 0.010953014 | G58: =IFERROR(VLOOKUP(G$2,'R.WEALTH-Cummulative (BM)'!$A:$FH,$B58,FALSE)-1,"") -> 0.084428037 | H58: =IFERROR(VLOOKUP(H$2,'R.WEALTH-Cummulative (BM)'!$A:$FH,$B58,FALSE)-1,"") -> 0.18692932 | I58: =IFERROR(VLOOKUP(I$2,'R.WEALTH-Cummulative (BM)'!$A:$FH,$B58,FALSE)-1,"") -> 0.010953014 | J58: =IFERROR(VLOOKUP(J$2,'R.WEALTH-Cummulative (BM)'!$A:$FH,$B58,FALSE)-1,"") -> 0.091091301 | K58: =IFERROR((VLOOKUP(K$2,'R.WEALTH-Cummulative (BM)'!$A:$FH,$B58,FALSE)^(1/(K$2/12)))-1,"") -> 0.069243604 | L58: =IFERROR((VLOOKUP(L$2,'R.WEALTH-Cummulative (BM)'!$A:$FH,$B58,FALSE)^(1/(L$2/12)))-1,"") -> 0.0702882 | M58: =IFERROR((VLOOKUP(M$2,'R.WEALTH-Cummulative (BM)'!$A:$FH,$B58,FALSE)^(1/(M$2/12)))-1,"") -> 0.056114545 | N58: =IFERROR((VLOOKUP(N$2,'R.WEALTH-Cummulative (BM)'!$A:$FH,$B58,FALSE)^(1/(N$2/12)))-1,"") -> 0.064327671 | O58: =IFERROR((VLOOKUP(O$2,'R.WEALTH-Cummulative (BM)'!$A:$FH,$B58,FALSE)^(1/(O$2/12)))-1,"") | P58: =IFERROR((VLOOKUP(P$2,'R.WEALTH-Cummulative (BM)'!$A:$FH,$B58,FALSE)^(1/(P$2/12)))-1,"") | Q58: =IFERROR((VLOOKUP(Q$2,'R.WEALTH-Cummulative (BM)'!$A:$FH,$B58,FALSE)^(1/(Q$2/12)))-1,"") | R58: =IFERROR((VLOOKUP(R$2,'R.WEALTH-Cummulative (BM)'!$A:$FH,$B58,FALSE)^(1/(R$2/12)))-1,"") | ... X58: =IFERROR((VLOOKUP(X$2,'R.WEALTH-Cummulative (BM)'!$A:$FH,$B58,FALSE)^(1/(X$2/12)))-1,"") | Y58: =VLOOKUP(Y$2,'Since Inception (BM)'!$B:$AAC,Summary!B58-1,FALSE) -> 0.68172832 | Z58: =VLOOKUP(Z$2,'Since Inception (BM)'!$B:$AAC,Summary!B58-1,FALSE) -> 0.092270149
A59: 34 | C59: HRTH_U | D59: HHL.U | E59: Harvest Healthcare Leaders Income ETF | F59: =IFERROR(VLOOKUP(F$2,'R.WEALTH-Cummulative'!$A:$FG,$A59,FALSE)-1,"") -> -0.0047183756 | G59: =IFERROR(VLOOKUP(G$2,'R.WEALTH-Cummulative'!$A:$FG,$A59,FALSE)-1,"") -> 0.056457457 | H59: =IFERROR(VLOOKUP(H$2,'R.WEALTH-Cummulative'!$A:$FG,$A59,FALSE)-1,"") -> 0.16250828 | I59: =IFERROR(VLOOKUP(I$2,'R.WEALTH-Cummulative'!$A:$FG,$A59,FALSE)-1,"") -> -0.0047183756 | J59: =IFERROR(VLOOKUP(J$2,'R.WEALTH-Cummulative'!$A:$FG,$A59,FALSE)-1,"") -> 0.051243733 | K59: =IFERROR((VLOOKUP(K$2,'R.WEALTH-Cummulative'!$A:$FG,$A59,FALSE)^(1/(K$2/12)))-1,"") -> 0.064894941 | L59: =IFERROR((VLOOKUP(L$2,'R.WEALTH-Cummulative'!$A:$FG,$A59,FALSE)^(1/(L$2/12)))-1,"") -> 0.083843658 | M59: =IFERROR((VLOOKUP(M$2,'R.WEALTH-Cummulative'!$A:$FG,$A59,FALSE)^(1/(M$2/12)))-1,"") -> 0.076161463 | N59: =IFERROR((VLOOKUP(N$2,'R.WEALTH-Cummulative'!$A:$FG,$A59,FALSE)^(1/(N$2/12)))-1,"") -> 0.097194064 | O59: =IFERROR((VLOOKUP(O$2,'R.WEALTH-Cummulative'!$A:$FG,$A59,FALSE)^(1/(O$2/12)))-1,"") -> 0.099566959 | P59: =IFERROR((VLOOKUP(P$2,'R.WEALTH-Cummulative'!$A:$FG,$A59,FALSE)^(1/(P$2/12)))-1,"") -> 0.095823633 | Q59: =IFERROR((VLOOKUP(Q$2,'R.WEALTH-Cummulative'!$A:$FG,$A59,FALSE)^(1/(Q$2/12)))-1,"") -> 0.085928224 | R59: =IFERROR((VLOOKUP(R$2,'R.WEALTH-Cummulative'!$A:$FG,$A59,FALSE)^(1/(R$2/12)))-1,"") | ... X59: =IFERROR((VLOOKUP(X$2,'R.WEALTH-Cummulative'!$A:$FG,$A59,FALSE)^(1/(X$2/12)))-1,"") | Y59: =VLOOKUP(Y$2,'Since Inception Returns'!$B:$AAB,Summary!A59-1,FALSE) -> 1.2469859 | Z59: =VLOOKUP(Z$2,'Since Inception Returns'!$B:$AAB,Summary!A59-1,FALSE) -> 0.094320089
B60: 34 | C60: HRTH_U | D60: HHL.U | E60: MSCI World Health Care Net Total Return USD Index | F60: =IFERROR(VLOOKUP(F$2,'R.WEALTH-Cummulative (BM)'!$A:$FH,$B60,FALSE)-1,"") -> 0.010953014 | G60: =IFERROR(VLOOKUP(G$2,'R.WEALTH-Cummulative (BM)'!$A:$FH,$B60,FALSE)-1,"") -> 0.084428037 | H60: =IFERROR(VLOOKUP(H$2,'R.WEALTH-Cummulative (BM)'!$A:$FH,$B60,FALSE)-1,"") -> 0.18692932 | I60: =IFERROR(VLOOKUP(I$2,'R.WEALTH-Cummulative (BM)'!$A:$FH,$B60,FALSE)-1,"") -> 0.010953014 | J60: =IFERROR(VLOOKUP(J$2,'R.WEALTH-Cummulative (BM)'!$A:$FH,$B60,FALSE)-1,"") -> 0.091091301 | K60: =IFERROR((VLOOKUP(K$2,'R.WEALTH-Cummulative (BM)'!$A:$FH,$B60,FALSE)^(1/(K$2/12)))-1,"") -> 0.069243604 | L60: =IFERROR((VLOOKUP(L$2,'R.WEALTH-Cummulative (BM)'!$A:$FH,$B60,FALSE)^(1/(L$2/12)))-1,"") -> 0.0702882 | M60: =IFERROR((VLOOKUP(M$2,'R.WEALTH-Cummulative (BM)'!$A:$FH,$B60,FALSE)^(1/(M$2/12)))-1,"") -> 0.056114545 | N60: =IFERROR((VLOOKUP(N$2,'R.WEALTH-Cummulative (BM)'!$A:$FH,$B60,FALSE)^(1/(N$2/12)))-1,"") -> 0.064327671 | O60: =IFERROR((VLOOKUP(O$2,'R.WEALTH-Cummulative (BM)'!$A:$FH,$B60,FALSE)^(1/(O$2/12)))-1,"") -> 0.080298061 | P60: =IFERROR((VLOOKUP(P$2,'R.WEALTH-Cummulative (BM)'!$A:$FH,$B60,FALSE)^(1/(P$2/12)))-1,"") -> 0.090725588 | Q60: =IFERROR((VLOOKUP(Q$2,'R.WEALTH-Cummulative (BM)'!$A:$FH,$B60,FALSE)^(1/(Q$2/12)))-1,"") -> 0.081717353 | R60: =IFERROR((VLOOKUP(R$2,'R.WEALTH-Cummulative (BM)'!$A:$FH,$B60,FALSE)^(1/(R$2/12)))-1,"") | ... X60: =IFERROR((VLOOKUP(X$2,'R.WEALTH-Cummulative (BM)'!$A:$FH,$B60,FALSE)^(1/(X$2/12)))-1,"") | Y60: =VLOOKUP(Y$2,'Since Inception (BM)'!$B:$AAC,Summary!B60-1,FALSE) -> 1.2954055 | Z60: =VLOOKUP(Z$2,'Since Inception (BM)'!$B:$AAC,Summary!B60-1,FALSE) -> 0.09692063
A61: 35 | C61: HRTJ | D61: HBLK | E61: Blockchain Technologies ETF | F61: =IFERROR(VLOOKUP(F$2,'R.WEALTH-Cummulative'!$A:$FG,$A61,FALSE)-1,"") -> 0.026827919 | G61: =IFERROR(VLOOKUP(G$2,'R.WEALTH-Cummulative'!$A:$FG,$A61,FALSE)-1,"") -> -0.26466677 | H61: =IFERROR(VLOOKUP(H$2,'R.WEALTH-Cummulative'!$A:$FG,$A61,FALSE)-1,"") -> 0.064522088 | I61: =IFERROR(VLOOKUP(I$2,'R.WEALTH-Cummulative'!$A:$FG,$A61,FALSE)-1,"") -> 0.026827919 | J61: =IFERROR(VLOOKUP(J$2,'R.WEALTH-Cummulative'!$A:$FG,$A61,FALSE)-1,"") -> 0.089636537 | K61: =IFERROR((VLOOKUP(K$2,'R.WEALTH-Cummulative'!$A:$FG,$A61,FALSE)^(1/(K$2/12)))-1,"") -> 0.28919705 | L61: =IFERROR((VLOOKUP(L$2,'R.WEALTH-Cummulative'!$A:$FG,$A61,FALSE)^(1/(L$2/12)))-1,"") -> 0.29566078 | M61: =IFERROR((VLOOKUP(M$2,'R.WEALTH-Cummulative'!$A:$FG,$A61,FALSE)^(1/(M$2/12)))-1,"") -> 0.040884798 | N61: =IFERROR((VLOOKUP(N$2,'R.WEALTH-Cummulative'!$A:$FG,$A61,FALSE)^(1/(N$2/12)))-1,"") -> 0.050057466 | O61: =IFERROR((VLOOKUP(O$2,'R.WEALTH-Cummulative'!$A:$FG,$A61,FALSE)^(1/(O$2/12)))-1,"") -> 0.22007502 | P61: =IFERROR((VLOOKUP(P$2,'R.WEALTH-Cummulative'!$A:$FG,$A61,FALSE)^(1/(P$2/12)))-1,"") -> 0.20678008 | Q61: =IFERROR((VLOOKUP(Q$2,'R.WEALTH-Cummulative'!$A:$FG,$A61,FALSE)^(1/(Q$2/12)))-1,"") | R61: =IFERROR((VLOOKUP(R$2,'R.WEALTH-Cummulative'!$A:$FG,$A61,FALSE)^(1/(R$2/12)))-1,"") | ... X61: =IFERROR((VLOOKUP(X$2,'R.WEALTH-Cummulative'!$A:$FG,$A61,FALSE)^(1/(X$2/12)))-1,"") | Y61: =VLOOKUP(Y$2,'Since Inception Returns'!$B:$AAB,Summary!A61-1,FALSE) -> 1.18969 | Z61: =VLOOKUP(Z$2,'Since Inception Returns'!$B:$AAB,Summary!A61-1,FALSE) -> 0.10309339
B62: 35 | C62: HRTJ | D62: HBLK | E62: MSCI ACWI Small Information Technology Net Return USD Index | F62: =IFERROR(VLOOKUP(F$2,'R.WEALTH-Cummulative (BM)'!$A:$FH,$B62,FALSE)-1,"") -> 0.094875857 | G62: =IFERROR(VLOOKUP(G$2,'R.WEALTH-Cummulative (BM)'!$A:$FH,$B62,FALSE)-1,"") -> 0.072141768 | H62: =IFERROR(VLOOKUP(H$2,'R.WEALTH-Cummulative (BM)'!$A:$FH,$B62,FALSE)-1,"") -> 0.28044999 | I62: =IFERROR(VLOOKUP(I$2,'R.WEALTH-Cummulative (BM)'!$A:$FH,$B62,FALSE)-1,"") -> 0.094875857 | J62: =IFERROR(VLOOKUP(J$2,'R.WEALTH-Cummulative (BM)'!$A:$FH,$B62,FALSE)-1,"") -> 0.31801814 | K62: =IFERROR((VLOOKUP(K$2,'R.WEALTH-Cummulative (BM)'!$A:$FH,$B62,FALSE)^(1/(K$2/12)))-1,"") -> 0.22524849 | L62: =IFERROR((VLOOKUP(L$2,'R.WEALTH-Cummulative (BM)'!$A:$FH,$B62,FALSE)^(1/(L$2/12)))-1,"") -> 0.20479661 | M62: =IFERROR((VLOOKUP(M$2,'R.WEALTH-Cummulative (BM)'!$A:$FH,$B62,FALSE)^(1/(M$2/12)))-1,"") -> 0.11814066 | N62: =IFERROR((VLOOKUP(N$2,'R.WEALTH-Cummulative (BM)'!$A:$FH,$B62,FALSE)^(1/(N$2/12)))-1,"") -> 0.093700011 | O62: =IFERROR((VLOOKUP(O$2,'R.WEALTH-Cummulative (BM)'!$A:$FH,$B62,FALSE)^(1/(O$2/12)))-1,"") -> 0.14860647 | P62: =IFERROR((VLOOKUP(P$2,'R.WEALTH-Cummulative (BM)'!$A:$FH,$B62,FALSE)^(1/(P$2/12)))-1,"") -> 0.16512895 | Q62: =IFERROR((VLOOKUP(Q$2,'R.WEALTH-Cummulative (BM)'!$A:$FH,$B62,FALSE)^(1/(Q$2/12)))-1,"") | R62: =IFERROR((VLOOKUP(R$2,'R.WEALTH-Cummulative (BM)'!$A:$FH,$B62,FALSE)^(1/(R$2/12)))-1,"") | ... X62: =IFERROR((VLOOKUP(X$2,'R.WEALTH-Cummulative (BM)'!$A:$FH,$B62,FALSE)^(1/(X$2/12)))-1,"") | Y62: =VLOOKUP(Y$2,'Since Inception (BM)'!$B:$AAC,Summary!B62-1,FALSE) -> 1.8246728 | Z62: =VLOOKUP(Z$2,'Since Inception (BM)'!$B:$AAC,Summary!B62-1,FALSE) -> 0.13882348
B63: 36 | C63: HRTJ | D63: HBLK | E63: Harvest Blockchain Technologies Index | F63: =IFERROR(VLOOKUP(F$2,'R.WEALTH-Cummulative (BM)'!$A:$FH,$B63,FALSE)-1,"") -> 0.024144585 | G63: =IFERROR(VLOOKUP(G$2,'R.WEALTH-Cummulative (BM)'!$A:$FH,$B63,FALSE)-1,"") -> -0.26847307 | H63: =IFERROR(VLOOKUP(H$2,'R.WEALTH-Cummulative (BM)'!$A:$FH,$B63,FALSE)-1,"") -> 0.064683433 | I63: =IFERROR(VLOOKUP(I$2,'R.WEALTH-Cummulative (BM)'!$A:$FH,$B63,FALSE)-1,"") -> 0.024144585 | J63: =IFERROR(VLOOKUP(J$2,'R.WEALTH-Cummulative (BM)'!$A:$FH,$B63,FALSE)-1,"") -> 0.09721662 | K63: =IFERROR((VLOOKUP(K$2,'R.WEALTH-Cummulative (BM)'!$A:$FH,$B63,FALSE)^(1/(K$2/12)))-1,"") -> 0.29817334 | L63: =IFERROR((VLOOKUP(L$2,'R.WEALTH-Cummulative (BM)'!$A:$FH,$B63,FALSE)^(1/(L$2/12)))-1,"") -> 0.3006313 | M63: =IFERROR((VLOOKUP(M$2,'R.WEALTH-Cummulative (BM)'!$A:$FH,$B63,FALSE)^(1/(M$2/12)))-1,"") -> 0.046452443 | N63: =IFERROR((VLOOKUP(N$2,'R.WEALTH-Cummulative (BM)'!$A:$FH,$B63,FALSE)^(1/(N$2/12)))-1,"") -> 0.055944447 | O63: =IFERROR((VLOOKUP(O$2,'R.WEALTH-Cummulative (BM)'!$A:$FH,$B63,FALSE)^(1/(O$2/12)))-1,"") -> 0.22387347 | P63: =IFERROR((VLOOKUP(P$2,'R.WEALTH-Cummulative (BM)'!$A:$FH,$B63,FALSE)^(1/(P$2/12)))-1,"") -> 0.21161002 | Q63: =IFERROR((VLOOKUP(Q$2,'R.WEALTH-Cummulative (BM)'!$A:$FH,$B63,FALSE)^(1/(Q$2/12)))-1,"") | R63: =IFERROR((VLOOKUP(R$2,'R.WEALTH-Cummulative (BM)'!$A:$FH,$B63,FALSE)^(1/(R$2/12)))-1,"") | ... X63: =IFERROR((VLOOKUP(X$2,'R.WEALTH-Cummulative (BM)'!$A:$FH,$B63,FALSE)^(1/(X$2/12)))-1,"") | Y63: =VLOOKUP(Y$2,'Since Inception (BM)'!$B:$AAC,Summary!B63-1,FALSE) -> 1.176 | Z63: =VLOOKUP(Z$2,'Since Inception (BM)'!$B:$AAC,Summary!B63-1,FALSE) -> 0.10222764
A64: 36 | C64: HRTM | D64: HUTL | E64: Harvest Equal Weight Global Utilities Income ETF | F64: =IFERROR(VLOOKUP(F$2,'R.WEALTH-Cummulative'!$A:$FG,$A64,FALSE)-1,"") -> 0.043670862 | G64: =IFERROR(VLOOKUP(G$2,'R.WEALTH-Cummulative'!$A:$FG,$A64,FALSE)-1,"") -> 0.045887466 | H64: =IFERROR(VLOOKUP(H$2,'R.WEALTH-Cummulative'!$A:$FG,$A64,FALSE)-1,"") -> 0.075886718 | I64: =IFERROR(VLOOKUP(I$2,'R.WEALTH-Cummulative'!$A:$FG,$A64,FALSE)-1,"") -> 0.043670862 | J64: =IFERROR(VLOOKUP(J$2,'R.WEALTH-Cummulative'!$A:$FG,$A64,FALSE)-1,"") -> 0.19178702 | K64: =IFERROR((VLOOKUP(K$2,'R.WEALTH-Cummulative'!$A:$FG,$A64,FALSE)^(1/(K$2/12)))-1,"") -> 0.18020808 | L64: =IFERROR((VLOOKUP(L$2,'R.WEALTH-Cummulative'!$A:$FG,$A64,FALSE)^(1/(L$2/12)))-1,"") -> 0.1122266 | M64: =IFERROR((VLOOKUP(M$2,'R.WEALTH-Cummulative'!$A:$FG,$A64,FALSE)^(1/(M$2/12)))-1,"") -> 0.074736262 | N64: =IFERROR((VLOOKUP(N$2,'R.WEALTH-Cummulative'!$A:$FG,$A64,FALSE)^(1/(N$2/12)))-1,"") -> 0.094652575 | O64: =IFERROR((VLOOKUP(O$2,'R.WEALTH-Cummulative'!$A:$FG,$A64,FALSE)^(1/(O$2/12)))-1,"") -> 0.052386124 | P64: =IFERROR((VLOOKUP(P$2,'R.WEALTH-Cummulative'!$A:$FG,$A64,FALSE)^(1/(P$2/12)))-1,"") -> 0.068796295 | Q64: =IFERROR((VLOOKUP(Q$2,'R.WEALTH-Cummulative'!$A:$FG,$A64,FALSE)^(1/(Q$2/12)))-1,"") | R64: =IFERROR((VLOOKUP(R$2,'R.WEALTH-Cummulative'!$A:$FG,$A64,FALSE)^(1/(R$2/12)))-1,"") | ... X64: =IFERROR((VLOOKUP(X$2,'R.WEALTH-Cummulative'!$A:$FG,$A64,FALSE)^(1/(X$2/12)))-1,"") | Y64: =VLOOKUP(Y$2,'Since Inception Returns'!$B:$AAB,Summary!A64-1,FALSE) -> 0.62137828 | Z64: =VLOOKUP(Z$2,'Since Inception Returns'!$B:$AAB,Summary!A64-1,FALSE) -> 0.070875662
B65: 37 | C65: HRTM | D65: HUTL | E65: MSCI World Utilities GRTR Local Index | F65: =IFERROR(VLOOKUP(F$2,'R.WEALTH-Cummulative (BM)'!$A:$FH,$B65,FALSE)-1,"") -> 0.03314887 | G65: =IFERROR(VLOOKUP(G$2,'R.WEALTH-Cummulative (BM)'!$A:$FH,$B65,FALSE)-1,"") -> 0.021324403 | H65: =IFERROR(VLOOKUP(H$2,'R.WEALTH-Cummulative (BM)'!$A:$FH,$B65,FALSE)-1,"") -> 0.082156746 | I65: =IFERROR(VLOOKUP(I$2,'R.WEALTH-Cummulative (BM)'!$A:$FH,$B65,FALSE)-1,"") -> 0.03314887 | J65: =IFERROR(VLOOKUP(J$2,'R.WEALTH-Cummulative (BM)'!$A:$FH,$B65,FALSE)-1,"") -> 0.22844476 | K65: =IFERROR((VLOOKUP(K$2,'R.WEALTH-Cummulative (BM)'!$A:$FH,$B65,FALSE)^(1/(K$2/12)))-1,"") -> 0.22649441 | L65: =IFERROR((VLOOKUP(L$2,'R.WEALTH-Cummulative (BM)'!$A:$FH,$B65,FALSE)^(1/(L$2/12)))-1,"") -> 0.13749448 | M65: =IFERROR((VLOOKUP(M$2,'R.WEALTH-Cummulative (BM)'!$A:$FH,$B65,FALSE)^(1/(M$2/12)))-1,"") -> 0.10395198 | N65: =IFERROR((VLOOKUP(N$2,'R.WEALTH-Cummulative (BM)'!$A:$FH,$B65,FALSE)^(1/(N$2/12)))-1,"") -> 0.10532983 | O65: =IFERROR((VLOOKUP(O$2,'R.WEALTH-Cummulative (BM)'!$A:$FH,$B65,FALSE)^(1/(O$2/12)))-1,"") -> 0.079638413 | P65: =IFERROR((VLOOKUP(P$2,'R.WEALTH-Cummulative (BM)'!$A:$FH,$B65,FALSE)^(1/(P$2/12)))-1,"") -> 0.10296772 | Q65: =IFERROR((VLOOKUP(Q$2,'R.WEALTH-Cummulative (BM)'!$A:$FH,$B65,FALSE)^(1/(Q$2/12)))-1,"") | R65: =IFERROR((VLOOKUP(R$2,'R.WEALTH-Cummulative (BM)'!$A:$FH,$B65,FALSE)^(1/(R$2/12)))-1,"") | ... X65: =IFERROR((VLOOKUP(X$2,'R.WEALTH-Cummulative (BM)'!$A:$FH,$B65,FALSE)^(1/(X$2/12)))-1,"") | Y65: =VLOOKUP(Y$2,'Since Inception (BM)'!$B:$AAC,Summary!B65-1,FALSE) -> 1.0356516 | Z65: =VLOOKUP(Z$2,'Since Inception (BM)'!$B:$AAC,Summary!B65-1,FALSE) -> 0.10596397
A66: 37 | C66: HRTP_A | D66: HUBL | E66: Harvest US Bank Leaders Income ETF | F66: =IFERROR(VLOOKUP(F$2,'R.WEALTH-Cummulative'!$A:$FG,$A66,FALSE)-1,"") -> 0.025186885 | G66: =IFERROR(VLOOKUP(G$2,'R.WEALTH-Cummulative'!$A:$FG,$A66,FALSE)-1,"") -> 0.12065171 | H66: =IFERROR(VLOOKUP(H$2,'R.WEALTH-Cummulative'!$A:$FG,$A66,FALSE)-1,"") -> 0.14924304 | I66: =IFERROR(VLOOKUP(I$2,'R.WEALTH-Cummulative'!$A:$FG,$A66,FALSE)-1,"") -> 0.025186885 | J66: =IFERROR(VLOOKUP(J$2,'R.WEALTH-Cummulative'!$A:$FG,$A66,FALSE)-1,"") -> 0.12160776 | K66: =IFERROR((VLOOKUP(K$2,'R.WEALTH-Cummulative'!$A:$FG,$A66,FALSE)^(1/(K$2/12)))-1,"") -> 0.2471166 | L66: =IFERROR((VLOOKUP(L$2,'R.WEALTH-Cummulative'!$A:$FG,$A66,FALSE)^(1/(L$2/12)))-1,"") -> 0.092528058 | M66: =IFERROR((VLOOKUP(M$2,'R.WEALTH-Cummulative'!$A:$FG,$A66,FALSE)^(1/(M$2/12)))-1,"") -> 0.040410734 | N66: =IFERROR((VLOOKUP(N$2,'R.WEALTH-Cummulative'!$A:$FG,$A66,FALSE)^(1/(N$2/12)))-1,"") -> 0.092500113 | O66: =IFERROR((VLOOKUP(O$2,'R.WEALTH-Cummulative'!$A:$FG,$A66,FALSE)^(1/(O$2/12)))-1,"") -> 0.066042687 | P66: =IFERROR((VLOOKUP(P$2,'R.WEALTH-Cummulative'!$A:$FG,$A66,FALSE)^(1/(P$2/12)))-1,"") -> 0.069911144 | Q66: =IFERROR((VLOOKUP(Q$2,'R.WEALTH-Cummulative'!$A:$FG,$A66,FALSE)^(1/(Q$2/12)))-1,"") -> 0.03644675 | R66: =IFERROR((VLOOKUP(R$2,'R.WEALTH-Cummulative'!$A:$FG,$A66,FALSE)^(1/(R$2/12)))-1,"") | ... X66: =IFERROR((VLOOKUP(X$2,'R.WEALTH-Cummulative'!$A:$FG,$A66,FALSE)^(1/(X$2/12)))-1,"") | Y66: =VLOOKUP(Y$2,'Since Inception Returns'!$B:$AAB,Summary!A66-1,FALSE) -> 0.33160664 | Z66: =VLOOKUP(Z$2,'Since Inception Returns'!$B:$AAB,Summary!A66-1,FALSE) -> 0.03644675
A67: 38 | C67: HRTP_U | D67: HUBL.U | E67: Harvest US Bank Leaders Income ETF | F67: =IFERROR(VLOOKUP(F$2,'R.WEALTH-Cummulative'!$A:$FG,$A67,FALSE)-1,"") -> 0.025618787 | G67: =IFERROR(VLOOKUP(G$2,'R.WEALTH-Cummulative'!$A:$FG,$A67,FALSE)-1,"") -> 0.12575425 | H67: =IFERROR(VLOOKUP(H$2,'R.WEALTH-Cummulative'!$A:$FG,$A67,FALSE)-1,"") -> 0.15961469 | I67: =IFERROR(VLOOKUP(I$2,'R.WEALTH-Cummulative'!$A:$FG,$A67,FALSE)-1,"") -> 0.025618787 | J67: =IFERROR(VLOOKUP(J$2,'R.WEALTH-Cummulative'!$A:$FG,$A67,FALSE)-1,"") -> 0.14431258 | K67: =IFERROR((VLOOKUP(K$2,'R.WEALTH-Cummulative'!$A:$FG,$A67,FALSE)^(1/(K$2/12)))-1,"") -> 0.26661566 | L67: =IFERROR((VLOOKUP(L$2,'R.WEALTH-Cummulative'!$A:$FG,$A67,FALSE)^(1/(L$2/12)))-1,"") -> 0.10791511 | M67: =IFERROR((VLOOKUP(M$2,'R.WEALTH-Cummulative'!$A:$FG,$A67,FALSE)^(1/(M$2/12)))-1,"") -> 0.055095587 | N67: =IFERROR((VLOOKUP(N$2,'R.WEALTH-Cummulative'!$A:$FG,$A67,FALSE)^(1/(N$2/12)))-1,"") -> 0.10727072 | O67: =IFERROR((VLOOKUP(O$2,'R.WEALTH-Cummulative'!$A:$FG,$A67,FALSE)^(1/(O$2/12)))-1,"") -> 0.085179203 | P67: =IFERROR((VLOOKUP(P$2,'R.WEALTH-Cummulative'!$A:$FG,$A67,FALSE)^(1/(P$2/12)))-1,"") -> 0.087492443 | Q67: =IFERROR((VLOOKUP(Q$2,'R.WEALTH-Cummulative'!$A:$FG,$A67,FALSE)^(1/(Q$2/12)))-1,"") -> 0.051149682 | R67: =IFERROR((VLOOKUP(R$2,'R.WEALTH-Cummulative'!$A:$FG,$A67,FALSE)^(1/(R$2/12)))-1,"") | ... X67: =IFERROR((VLOOKUP(X$2,'R.WEALTH-Cummulative'!$A:$FG,$A67,FALSE)^(1/(X$2/12)))-1,"") | Y67: =VLOOKUP(Y$2,'Since Inception Returns'!$B:$AAB,Summary!A67-1,FALSE) -> 0.49044689 | Z67: =VLOOKUP(Z$2,'Since Inception Returns'!$B:$AAB,Summary!A67-1,FALSE) -> 0.051149682
B68: 39 | C68: HRTP_A | D68: HUBL | E68: MSCI US Banks Net Total Return Index | F68: =IFERROR(VLOOKUP(F$2,'R.WEALTH-Cummulative (BM)'!$A:$FH,$B68,FALSE)-1,"") -> -0.019518012 | G68: =IFERROR(VLOOKUP(G$2,'R.WEALTH-Cummulative (BM)'!$A:$FH,$B68,FALSE)-1,"") -> 0.048382767 | H68: =IFERROR(VLOOKUP(H$2,'R.WEALTH-Cummulative (BM)'!$A:$FH,$B68,FALSE)-1,"") -> 0.11576918 | I68: =IFERROR(VLOOKUP(I$2,'R.WEALTH-Cummulative (BM)'!$A:$FH,$B68,FALSE)-1,"") -> -0.019518012 | J68: =IFERROR(VLOOKUP(J$2,'R.WEALTH-Cummulative (BM)'!$A:$FH,$B68,FALSE)-1,"") -> 0.18436813 | K68: =IFERROR((VLOOKUP(K$2,'R.WEALTH-Cummulative (BM)'!$A:$FH,$B68,FALSE)^(1/(K$2/12)))-1,"") -> 0.32235204 | L68: =IFERROR((VLOOKUP(L$2,'R.WEALTH-Cummulative (BM)'!$A:$FH,$B68,FALSE)^(1/(L$2/12)))-1,"") -> 0.21625099 | M68: =IFERROR((VLOOKUP(M$2,'R.WEALTH-Cummulative (BM)'!$A:$FH,$B68,FALSE)^(1/(M$2/12)))-1,"") -> 0.11566266 | N68: =IFERROR((VLOOKUP(N$2,'R.WEALTH-Cummulative (BM)'!$A:$FH,$B68,FALSE)^(1/(N$2/12)))-1,"") -> 0.16242656 | O68: =IFERROR((VLOOKUP(O$2,'R.WEALTH-Cummulative (BM)'!$A:$FH,$B68,FALSE)^(1/(O$2/12)))-1,"") -> 0.1166187 | P68: =IFERROR((VLOOKUP(P$2,'R.WEALTH-Cummulative (BM)'!$A:$FH,$B68,FALSE)^(1/(P$2/12)))-1,"") -> 0.12183569 | Q68: =IFERROR((VLOOKUP(Q$2,'R.WEALTH-Cummulative (BM)'!$A:$FH,$B68,FALSE)^(1/(Q$2/12)))-1,"") -> 0.084832033 | R68: =IFERROR((VLOOKUP(R$2,'R.WEALTH-Cummulative (BM)'!$A:$FH,$B68,FALSE)^(1/(R$2/12)))-1,"") | ... X68: =IFERROR((VLOOKUP(X$2,'R.WEALTH-Cummulative (BM)'!$A:$FH,$B68,FALSE)^(1/(X$2/12)))-1,"") | Y68: =VLOOKUP(Y$2,'Since Inception (BM)'!$B:$AAC,Summary!B68-1,FALSE) -> 0.91822702 | Z68: =VLOOKUP(Z$2,'Since Inception (BM)'!$B:$AAC,Summary!B68-1,FALSE) -> 0.084832033
A69: 39 | C69: HRTX | D69: HCLN | E69: Harvest Clean Energy ETF | F69: =IFERROR(VLOOKUP(F$2,'R.WEALTH-Cummulative'!$A:$FG,$A69,FALSE)-1,"") -> 0.095312438 | G69: =IFERROR(VLOOKUP(G$2,'R.WEALTH-Cummulative'!$A:$FG,$A69,FALSE)-1,"") -> 0.037057611 | H69: =IFERROR(VLOOKUP(H$2,'R.WEALTH-Cummulative'!$A:$FG,$A69,FALSE)-1,"") -> 0.27397324 | I69: =IFERROR(VLOOKUP(I$2,'R.WEALTH-Cummulative'!$A:$FG,$A69,FALSE)-1,"") -> 0.095312438 | J69: =IFERROR(VLOOKUP(J$2,'R.WEALTH-Cummulative'!$A:$FG,$A69,FALSE)-1,"") -> 0.45095172 | K69: =IFERROR((VLOOKUP(K$2,'R.WEALTH-Cummulative'!$A:$FG,$A69,FALSE)^(1/(K$2/12)))-1,"") -> 0.13229166 | L69: =IFERROR((VLOOKUP(L$2,'R.WEALTH-Cummulative'!$A:$FG,$A69,FALSE)^(1/(L$2/12)))-1,"") -> -0.054581089 | M69: =IFERROR((VLOOKUP(M$2,'R.WEALTH-Cummulative'!$A:$FG,$A69,FALSE)^(1/(M$2/12)))-1,"") -> -0.035404575 | N69: =IFERROR((VLOOKUP(N$2,'R.WEALTH-Cummulative'!$A:$FG,$A69,FALSE)^(1/(N$2/12)))-1,"") -> -0.10923812 | O69: =IFERROR((VLOOKUP(O$2,'R.WEALTH-Cummulative'!$A:$FG,$A69,FALSE)^(1/(O$2/12)))-1,"") | P69: =IFERROR((VLOOKUP(P$2,'R.WEALTH-Cummulative'!$A:$FG,$A69,FALSE)^(1/(P$2/12)))-1,"") | Q69: =IFERROR((VLOOKUP(Q$2,'R.WEALTH-Cummulative'!$A:$FG,$A69,FALSE)^(1/(Q$2/12)))-1,"") | R69: =IFERROR((VLOOKUP(R$2,'R.WEALTH-Cummulative'!$A:$FG,$A69,FALSE)^(1/(R$2/12)))-1,"") | ... X69: =IFERROR((VLOOKUP(X$2,'R.WEALTH-Cummulative'!$A:$FG,$A69,FALSE)^(1/(X$2/12)))-1,"") | Y69: =VLOOKUP(Y$2,'Since Inception Returns'!$B:$AAB,Summary!A69-1,FALSE) -> -0.449255 | Z69: =VLOOKUP(Z$2,'Since Inception Returns'!$B:$AAB,Summary!A69-1,FALSE) -> -0.11130704
B70: 40 | C70: HRTX | D70: HCLN | E70: MSCI Global Alternative Energy Gross Return Index | F70: =IFERROR(VLOOKUP(F$2,'R.WEALTH-Cummulative (BM)'!$A:$FH,$B70,FALSE)-1,"") -> 0.064980593 | G70: =IFERROR(VLOOKUP(G$2,'R.WEALTH-Cummulative (BM)'!$A:$FH,$B70,FALSE)-1,"") -> 0.077527236 | H70: =IFERROR(VLOOKUP(H$2,'R.WEALTH-Cummulative (BM)'!$A:$FH,$B70,FALSE)-1,"") -> 0.31549644 | I70: =IFERROR(VLOOKUP(I$2,'R.WEALTH-Cummulative (BM)'!$A:$FH,$B70,FALSE)-1,"") -> 0.064980593 | J70: =IFERROR(VLOOKUP(J$2,'R.WEALTH-Cummulative (BM)'!$A:$FH,$B70,FALSE)-1,"") -> 0.5757688 | K70: =IFERROR((VLOOKUP(K$2,'R.WEALTH-Cummulative (BM)'!$A:$FH,$B70,FALSE)^(1/(K$2/12)))-1,"") -> 0.081448632 | L70: =IFERROR((VLOOKUP(L$2,'R.WEALTH-Cummulative (BM)'!$A:$FH,$B70,FALSE)^(1/(L$2/12)))-1,"") -> -0.083634692 | M70: =IFERROR((VLOOKUP(M$2,'R.WEALTH-Cummulative (BM)'!$A:$FH,$B70,FALSE)^(1/(M$2/12)))-1,"") -> -0.049655449 | N70: =IFERROR((VLOOKUP(N$2,'R.WEALTH-Cummulative (BM)'!$A:$FH,$B70,FALSE)^(1/(N$2/12)))-1,"") -> -0.099599784 | O70: =IFERROR((VLOOKUP(O$2,'R.WEALTH-Cummulative (BM)'!$A:$FH,$B70,FALSE)^(1/(O$2/12)))-1,"") | P70: =IFERROR((VLOOKUP(P$2,'R.WEALTH-Cummulative (BM)'!$A:$FH,$B70,FALSE)^(1/(P$2/12)))-1,"") | Q70: =IFERROR((VLOOKUP(Q$2,'R.WEALTH-Cummulative (BM)'!$A:$FH,$B70,FALSE)^(1/(Q$2/12)))-1,"") | R70: =IFERROR((VLOOKUP(R$2,'R.WEALTH-Cummulative (BM)'!$A:$FH,$B70,FALSE)^(1/(R$2/12)))-1,"") | ... X70: =IFERROR((VLOOKUP(X$2,'R.WEALTH-Cummulative (BM)'!$A:$FH,$B70,FALSE)^(1/(X$2/12)))-1,"") | Y70: =VLOOKUP(Y$2,'Since Inception (BM)'!$B:$AAC,Summary!B70-1,FALSE) -> -0.45460374 | Z70: =VLOOKUP(Z$2,'Since Inception (BM)'!$B:$AAC,Summary!B70-1,FALSE) -> -0.11302119
A71: 40 | C71: HRTY_A | D71: TRVL | E71: Harvest Travel Leisure Index ETF | F71: =IFERROR(VLOOKUP(F$2,'R.WEALTH-Cummulative'!$A:$FG,$A71,FALSE)-1,"") -> -0.017052328 | G71: =IFERROR(VLOOKUP(G$2,'R.WEALTH-Cummulative'!$A:$FG,$A71,FALSE)-1,"") -> 0.060401468 | H71: =IFERROR(VLOOKUP(H$2,'R.WEALTH-Cummulative'!$A:$FG,$A71,FALSE)-1,"") -> 0.050944171 | I71: =IFERROR(VLOOKUP(I$2,'R.WEALTH-Cummulative'!$A:$FG,$A71,FALSE)-1,"") -> -0.017052328 | J71: =IFERROR(VLOOKUP(J$2,'R.WEALTH-Cummulative'!$A:$FG,$A71,FALSE)-1,"") -> 0.01562815 | K71: =IFERROR((VLOOKUP(K$2,'R.WEALTH-Cummulative'!$A:$FG,$A71,FALSE)^(1/(K$2/12)))-1,"") -> 0.18006236 | L71: =IFERROR((VLOOKUP(L$2,'R.WEALTH-Cummulative'!$A:$FG,$A71,FALSE)^(1/(L$2/12)))-1,"") -> 0.17031418 | M71: =IFERROR((VLOOKUP(M$2,'R.WEALTH-Cummulative'!$A:$FG,$A71,FALSE)^(1/(M$2/12)))-1,"") -> 0.11941833 | N71: =IFERROR((VLOOKUP(N$2,'R.WEALTH-Cummulative'!$A:$FG,$A71,FALSE)^(1/(N$2/12)))-1,"") -> 0.12099631 | O71: =IFERROR((VLOOKUP(O$2,'R.WEALTH-Cummulative'!$A:$FG,$A71,FALSE)^(1/(O$2/12)))-1,"") | P71: =IFERROR((VLOOKUP(P$2,'R.WEALTH-Cummulative'!$A:$FG,$A71,FALSE)^(1/(P$2/12)))-1,"") | Q71: =IFERROR((VLOOKUP(Q$2,'R.WEALTH-Cummulative'!$A:$FG,$A71,FALSE)^(1/(Q$2/12)))-1,"") | R71: =IFERROR((VLOOKUP(R$2,'R.WEALTH-Cummulative'!$A:$FG,$A71,FALSE)^(1/(R$2/12)))-1,"") | ... X71: =IFERROR((VLOOKUP(X$2,'R.WEALTH-Cummulative'!$A:$FG,$A71,FALSE)^(1/(X$2/12)))-1,"") | Y71: =VLOOKUP(Y$2,'Since Inception Returns'!$B:$AAB,Summary!A71-1,FALSE) -> 0.63735 | Z71: =VLOOKUP(Z$2,'Since Inception Returns'!$B:$AAB,Summary!A71-1,FALSE) -> 0.10246305
A72: 41 | C72: HRTY_U | D72: TRVL.U | E72: Harvest Travel Leisure Index ETF | F72: =IFERROR(VLOOKUP(F$2,'R.WEALTH-Cummulative'!$A:$FG,$A72,FALSE)-1,"") -> -0.0091745782 | G72: =IFERROR(VLOOKUP(G$2,'R.WEALTH-Cummulative'!$A:$FG,$A72,FALSE)-1,"") -> 0.09226547 | H72: =IFERROR(VLOOKUP(H$2,'R.WEALTH-Cummulative'!$A:$FG,$A72,FALSE)-1,"") -> 0.069443091 | I72: =IFERROR(VLOOKUP(I$2,'R.WEALTH-Cummulative'!$A:$FG,$A72,FALSE)-1,"") -> -0.0091745782 | J72: =IFERROR(VLOOKUP(J$2,'R.WEALTH-Cummulative'!$A:$FG,$A72,FALSE)-1,"") -> 0.084022495 | K72: =IFERROR((VLOOKUP(K$2,'R.WEALTH-Cummulative'!$A:$FG,$A72,FALSE)^(1/(K$2/12)))-1,"") -> 0.17258104 | L72: =IFERROR((VLOOKUP(L$2,'R.WEALTH-Cummulative'!$A:$FG,$A72,FALSE)^(1/(L$2/12)))-1,"") -> 0.16133235 | M72: =IFERROR((VLOOKUP(M$2,'R.WEALTH-Cummulative'!$A:$FG,$A72,FALSE)^(1/(M$2/12)))-1,"") -> 0.10032991 | N72: =IFERROR((VLOOKUP(N$2,'R.WEALTH-Cummulative'!$A:$FG,$A72,FALSE)^(1/(N$2/12)))-1,"") -> 0.10701156 | O72: =IFERROR((VLOOKUP(O$2,'R.WEALTH-Cummulative'!$A:$FG,$A72,FALSE)^(1/(O$2/12)))-1,"") | P72: =IFERROR((VLOOKUP(P$2,'R.WEALTH-Cummulative'!$A:$FG,$A72,FALSE)^(1/(P$2/12)))-1,"") | Q72: =IFERROR((VLOOKUP(Q$2,'R.WEALTH-Cummulative'!$A:$FG,$A72,FALSE)^(1/(Q$2/12)))-1,"") | R72: =IFERROR((VLOOKUP(R$2,'R.WEALTH-Cummulative'!$A:$FG,$A72,FALSE)^(1/(R$2/12)))-1,"") | ... X72: =IFERROR((VLOOKUP(X$2,'R.WEALTH-Cummulative'!$A:$FG,$A72,FALSE)^(1/(X$2/12)))-1,"") | Y72: =VLOOKUP(Y$2,'Since Inception Returns'!$B:$AAB,Summary!A72-1,FALSE) -> 0.536255 | Z72: =VLOOKUP(Z$2,'Since Inception Returns'!$B:$AAB,Summary!A72-1,FALSE) -> 0.088650322
B73: 42 | C73: HRTY_A | D73: TRVL | E73: Solactive Travel & Leisure Index GTR | F73: =IFERROR(VLOOKUP(F$2,'R.WEALTH-Cummulative (BM)'!$A:$FH,$B73,FALSE)-1,"") -> -0.020848614 | G73: =IFERROR(VLOOKUP(G$2,'R.WEALTH-Cummulative (BM)'!$A:$FH,$B73,FALSE)-1,"") -> 0.058246557 | H73: =IFERROR(VLOOKUP(H$2,'R.WEALTH-Cummulative (BM)'!$A:$FH,$B73,FALSE)-1,"") -> 0.052251867 | I73: =IFERROR(VLOOKUP(I$2,'R.WEALTH-Cummulative (BM)'!$A:$FH,$B73,FALSE)-1,"") -> -0.020848614 | J73: =IFERROR(VLOOKUP(J$2,'R.WEALTH-Cummulative (BM)'!$A:$FH,$B73,FALSE)-1,"") -> 0.022379147 | K73: =IFERROR((VLOOKUP(K$2,'R.WEALTH-Cummulative (BM)'!$A:$FH,$B73,FALSE)^(1/(K$2/12)))-1,"") -> 0.19194691 | L73: =IFERROR((VLOOKUP(L$2,'R.WEALTH-Cummulative (BM)'!$A:$FH,$B73,FALSE)^(1/(L$2/12)))-1,"") -> 0.1778235 | M73: =IFERROR((VLOOKUP(M$2,'R.WEALTH-Cummulative (BM)'!$A:$FH,$B73,FALSE)^(1/(M$2/12)))-1,"") -> 0.12795643 | N73: =IFERROR((VLOOKUP(N$2,'R.WEALTH-Cummulative (BM)'!$A:$FH,$B73,FALSE)^(1/(N$2/12)))-1,"") -> 0.12952359 | O73: =IFERROR((VLOOKUP(O$2,'R.WEALTH-Cummulative (BM)'!$A:$FH,$B73,FALSE)^(1/(O$2/12)))-1,"") | P73: =IFERROR((VLOOKUP(P$2,'R.WEALTH-Cummulative (BM)'!$A:$FH,$B73,FALSE)^(1/(P$2/12)))-1,"") | Q73: =IFERROR((VLOOKUP(Q$2,'R.WEALTH-Cummulative (BM)'!$A:$FH,$B73,FALSE)^(1/(Q$2/12)))-1,"") | R73: =IFERROR((VLOOKUP(R$2,'R.WEALTH-Cummulative (BM)'!$A:$FH,$B73,FALSE)^(1/(R$2/12)))-1,"") | ... X73: =IFERROR((VLOOKUP(X$2,'R.WEALTH-Cummulative (BM)'!$A:$FH,$B73,FALSE)^(1/(X$2/12)))-1,"") | Y73: =VLOOKUP(Y$2,'Since Inception (BM)'!$B:$AAC,Summary!B73-1,FALSE) -> 0.69372702 | Z73: =VLOOKUP(Z$2,'Since Inception (BM)'!$B:$AAC,Summary!B73-1,FALSE) -> 0.10987111
A74: 42 | C74: HRVF | D74: HRIF | E74: Harvest Diversified Equity Income ETF | F74: =IFERROR(VLOOKUP(F$2,'R.WEALTH-Cummulative'!$A:$FG,$A74,FALSE)-1,"") -> 0.0042606268 | G74: =IFERROR(VLOOKUP(G$2,'R.WEALTH-Cummulative'!$A:$FG,$A74,FALSE)-1,"") -> 0.031075201 | H74: =IFERROR(VLOOKUP(H$2,'R.WEALTH-Cummulative'!$A:$FG,$A74,FALSE)-1,"") -> 0.087560961 | I74: =IFERROR(VLOOKUP(I$2,'R.WEALTH-Cummulative'!$A:$FG,$A74,FALSE)-1,"") -> 0.0042606268 | J74: =IFERROR(VLOOKUP(J$2,'R.WEALTH-Cummulative'!$A:$FG,$A74,FALSE)-1,"") -> 0.10255983 | K74: =IFERROR((VLOOKUP(K$2,'R.WEALTH-Cummulative'!$A:$FG,$A74,FALSE)^(1/(K$2/12)))-1,"") -> 0.1403945 | L74: =IFERROR((VLOOKUP(L$2,'R.WEALTH-Cummulative'!$A:$FG,$A74,FALSE)^(1/(L$2/12)))-1,"") | M74: =IFERROR((VLOOKUP(M$2,'R.WEALTH-Cummulative'!$A:$FG,$A74,FALSE)^(1/(M$2/12)))-1,"") | N74: =IFERROR((VLOOKUP(N$2,'R.WEALTH-Cummulative'!$A:$FG,$A74,FALSE)^(1/(N$2/12)))-1,"") | O74: =IFERROR((VLOOKUP(O$2,'R.WEALTH-Cummulative'!$A:$FG,$A74,FALSE)^(1/(O$2/12)))-1,"") | P74: =IFERROR((VLOOKUP(P$2,'R.WEALTH-Cummulative'!$A:$FG,$A74,FALSE)^(1/(P$2/12)))-1,"") | Q74: =IFERROR((VLOOKUP(Q$2,'R.WEALTH-Cummulative'!$A:$FG,$A74,FALSE)^(1/(Q$2/12)))-1,"") | R74: =IFERROR((VLOOKUP(R$2,'R.WEALTH-Cummulative'!$A:$FG,$A74,FALSE)^(1/(R$2/12)))-1,"") | ... X74: =IFERROR((VLOOKUP(X$2,'R.WEALTH-Cummulative'!$A:$FG,$A74,FALSE)^(1/(X$2/12)))-1,"") | Y74: =VLOOKUP(Y$2,'Since Inception Returns'!$B:$AAB,Summary!A74-1,FALSE) -> 0.4196532 | Z74: =VLOOKUP(Z$2,'Since Inception Returns'!$B:$AAB,Summary!A74-1,FALSE) -> 0.13252222
B75: 43 | C75: HRVF | D75: HRIF | E75: Solactive GBS United States 500 Index TR | F75: =IFERROR(VLOOKUP(F$2,'R.WEALTH-Cummulative (BM)'!$A:$FH,$B75,FALSE)-1,"") -> 0.012539964 | G75: =IFERROR(VLOOKUP(G$2,'R.WEALTH-Cummulative (BM)'!$A:$FH,$B75,FALSE)-1,"") -> 0.01270775 | H75: =IFERROR(VLOOKUP(H$2,'R.WEALTH-Cummulative (BM)'!$A:$FH,$B75,FALSE)-1,"") -> 0.096905279 | I75: =IFERROR(VLOOKUP(I$2,'R.WEALTH-Cummulative (BM)'!$A:$FH,$B75,FALSE)-1,"") -> 0.012539964 | J75: =IFERROR(VLOOKUP(J$2,'R.WEALTH-Cummulative (BM)'!$A:$FH,$B75,FALSE)-1,"") -> 0.15937136 | K75: =IFERROR((VLOOKUP(K$2,'R.WEALTH-Cummulative (BM)'!$A:$FH,$B75,FALSE)^(1/(K$2/12)))-1,"") -> 0.21519072 | L75: =IFERROR((VLOOKUP(L$2,'R.WEALTH-Cummulative (BM)'!$A:$FH,$B75,FALSE)^(1/(L$2/12)))-1,"") | M75: =IFERROR((VLOOKUP(M$2,'R.WEALTH-Cummulative (BM)'!$A:$FH,$B75,FALSE)^(1/(M$2/12)))-1,"") | N75: =IFERROR((VLOOKUP(N$2,'R.WEALTH-Cummulative (BM)'!$A:$FH,$B75,FALSE)^(1/(N$2/12)))-1,"") | O75: =IFERROR((VLOOKUP(O$2,'R.WEALTH-Cummulative (BM)'!$A:$FH,$B75,FALSE)^(1/(O$2/12)))-1,"") | P75: =IFERROR((VLOOKUP(P$2,'R.WEALTH-Cummulative (BM)'!$A:$FH,$B75,FALSE)^(1/(P$2/12)))-1,"") | Q75: =IFERROR((VLOOKUP(Q$2,'R.WEALTH-Cummulative (BM)'!$A:$FH,$B75,FALSE)^(1/(Q$2/12)))-1,"") | R75: =IFERROR((VLOOKUP(R$2,'R.WEALTH-Cummulative (BM)'!$A:$FH,$B75,FALSE)^(1/(R$2/12)))-1,"") | ... X75: =IFERROR((VLOOKUP(X$2,'R.WEALTH-Cummulative (BM)'!$A:$FH,$B75,FALSE)^(1/(X$2/12)))-1,"") | Y75: =VLOOKUP(Y$2,'Since Inception (BM)'!$B:$AAC,Summary!B75-1,FALSE) -> 0.77591366 | Z75: =VLOOKUP(Z$2,'Since Inception (BM)'!$B:$AAC,Summary!B75-1,FALSE) -> 0.22625518
A76: 43 | C76: HRVG | D76: TRVI | E76: Harvest Travel & Leisure Income ETF | F76: =IFERROR(VLOOKUP(F$2,'R.WEALTH-Cummulative'!$A:$FG,$A76,FALSE)-1,"") -> -0.012912482 | G76: =IFERROR(VLOOKUP(G$2,'R.WEALTH-Cummulative'!$A:$FG,$A76,FALSE)-1,"") -> 0.068988412 | H76: =IFERROR(VLOOKUP(H$2,'R.WEALTH-Cummulative'!$A:$FG,$A76,FALSE)-1,"") -> 0.055809793 | I76: =IFERROR(VLOOKUP(I$2,'R.WEALTH-Cummulative'!$A:$FG,$A76,FALSE)-1,"") -> -0.012912482 | J76: =IFERROR(VLOOKUP(J$2,'R.WEALTH-Cummulative'!$A:$FG,$A76,FALSE)-1,"") -> 0.020381643 | K76: =IFERROR((VLOOKUP(K$2,'R.WEALTH-Cummulative'!$A:$FG,$A76,FALSE)^(1/(K$2/12)))-1,"") -> 0.11938376 | L76: =IFERROR((VLOOKUP(L$2,'R.WEALTH-Cummulative'!$A:$FG,$A76,FALSE)^(1/(L$2/12)))-1,"") | M76: =IFERROR((VLOOKUP(M$2,'R.WEALTH-Cummulative'!$A:$FG,$A76,FALSE)^(1/(M$2/12)))-1,"") | N76: =IFERROR((VLOOKUP(N$2,'R.WEALTH-Cummulative'!$A:$FG,$A76,FALSE)^(1/(N$2/12)))-1,"") | O76: =IFERROR((VLOOKUP(O$2,'R.WEALTH-Cummulative'!$A:$FG,$A76,FALSE)^(1/(O$2/12)))-1,"") | P76: =IFERROR((VLOOKUP(P$2,'R.WEALTH-Cummulative'!$A:$FG,$A76,FALSE)^(1/(P$2/12)))-1,"") | Q76: =IFERROR((VLOOKUP(Q$2,'R.WEALTH-Cummulative'!$A:$FG,$A76,FALSE)^(1/(Q$2/12)))-1,"") | R76: =IFERROR((VLOOKUP(R$2,'R.WEALTH-Cummulative'!$A:$FG,$A76,FALSE)^(1/(R$2/12)))-1,"") | ... X76: =IFERROR((VLOOKUP(X$2,'R.WEALTH-Cummulative'!$A:$FG,$A76,FALSE)^(1/(X$2/12)))-1,"") | Y76: =VLOOKUP(Y$2,'Since Inception Returns'!$B:$AAB,Summary!A76-1,FALSE) -> 0.44085218 | Z76: =VLOOKUP(Z$2,'Since Inception Returns'!$B:$AAB,Summary!A76-1,FALSE) -> 0.13849953
B77: 44 | C77: HRVG | D77: TRVI | E77: Solactive Travel & Leisure Index GTR | F77: =IFERROR(VLOOKUP(F$2,'R.WEALTH-Cummulative (BM)'!$A:$FH,$B77,FALSE)-1,"") -> -0.020848614 | G77: =IFERROR(VLOOKUP(G$2,'R.WEALTH-Cummulative (BM)'!$A:$FH,$B77,FALSE)-1,"") -> 0.058246557 | H77: =IFERROR(VLOOKUP(H$2,'R.WEALTH-Cummulative (BM)'!$A:$FH,$B77,FALSE)-1,"") -> 0.052251867 | I77: =IFERROR(VLOOKUP(I$2,'R.WEALTH-Cummulative (BM)'!$A:$FH,$B77,FALSE)-1,"") -> -0.020848614 | J77: =IFERROR(VLOOKUP(J$2,'R.WEALTH-Cummulative (BM)'!$A:$FH,$B77,FALSE)-1,"") -> 0.022379147 | K77: =IFERROR((VLOOKUP(K$2,'R.WEALTH-Cummulative (BM)'!$A:$FH,$B77,FALSE)^(1/(K$2/12)))-1,"") -> 0.19194691 | L77: =IFERROR((VLOOKUP(L$2,'R.WEALTH-Cummulative (BM)'!$A:$FH,$B77,FALSE)^(1/(L$2/12)))-1,"") | M77: =IFERROR((VLOOKUP(M$2,'R.WEALTH-Cummulative (BM)'!$A:$FH,$B77,FALSE)^(1/(M$2/12)))-1,"") | N77: =IFERROR((VLOOKUP(N$2,'R.WEALTH-Cummulative (BM)'!$A:$FH,$B77,FALSE)^(1/(N$2/12)))-1,"") | O77: =IFERROR((VLOOKUP(O$2,'R.WEALTH-Cummulative (BM)'!$A:$FH,$B77,FALSE)^(1/(O$2/12)))-1,"") | P77: =IFERROR((VLOOKUP(P$2,'R.WEALTH-Cummulative (BM)'!$A:$FH,$B77,FALSE)^(1/(P$2/12)))-1,"") | Q77: =IFERROR((VLOOKUP(Q$2,'R.WEALTH-Cummulative (BM)'!$A:$FH,$B77,FALSE)^(1/(Q$2/12)))-1,"") | R77: =IFERROR((VLOOKUP(R$2,'R.WEALTH-Cummulative (BM)'!$A:$FH,$B77,FALSE)^(1/(R$2/12)))-1,"") | ... X77: =IFERROR((VLOOKUP(X$2,'R.WEALTH-Cummulative (BM)'!$A:$FH,$B77,FALSE)^(1/(X$2/12)))-1,"") | Y77: =VLOOKUP(Y$2,'Since Inception (BM)'!$B:$AAC,Summary!B77-1,FALSE) -> 0.7194254 | Z77: =VLOOKUP(Z$2,'Since Inception (BM)'!$B:$AAC,Summary!B77-1,FALSE) -> 0.21225826
A78: 44 | C78: HRVJ | D78: TBIL | E78: Harvest Canadian T-Bill ETF | F78: =IFERROR(VLOOKUP(F$2,'R.WEALTH-Cummulative'!$A:$FG,$A78,FALSE)-1,"") -> 0.0017040034 | G78: =IFERROR(VLOOKUP(G$2,'R.WEALTH-Cummulative'!$A:$FG,$A78,FALSE)-1,"") -> 0.0053896465 | H78: =IFERROR(VLOOKUP(H$2,'R.WEALTH-Cummulative'!$A:$FG,$A78,FALSE)-1,"") -> 0.011726823 | I78: =IFERROR(VLOOKUP(I$2,'R.WEALTH-Cummulative'!$A:$FG,$A78,FALSE)-1,"") -> 0.0017040034 | J78: =IFERROR(VLOOKUP(J$2,'R.WEALTH-Cummulative'!$A:$FG,$A78,FALSE)-1,"") -> 0.02499132 | K78: =IFERROR((VLOOKUP(K$2,'R.WEALTH-Cummulative'!$A:$FG,$A78,FALSE)^(1/(K$2/12)))-1,"") -> 0.034299526 | L78: =IFERROR((VLOOKUP(L$2,'R.WEALTH-Cummulative'!$A:$FG,$A78,FALSE)^(1/(L$2/12)))-1,"") | M78: =IFERROR((VLOOKUP(M$2,'R.WEALTH-Cummulative'!$A:$FG,$A78,FALSE)^(1/(M$2/12)))-1,"") | N78: =IFERROR((VLOOKUP(N$2,'R.WEALTH-Cummulative'!$A:$FG,$A78,FALSE)^(1/(N$2/12)))-1,"") | O78: =IFERROR((VLOOKUP(O$2,'R.WEALTH-Cummulative'!$A:$FG,$A78,FALSE)^(1/(O$2/12)))-1,"") | P78: =IFERROR((VLOOKUP(P$2,'R.WEALTH-Cummulative'!$A:$FG,$A78,FALSE)^(1/(P$2/12)))-1,"") | Q78: =IFERROR((VLOOKUP(Q$2,'R.WEALTH-Cummulative'!$A:$FG,$A78,FALSE)^(1/(Q$2/12)))-1,"") | R78: =IFERROR((VLOOKUP(R$2,'R.WEALTH-Cummulative'!$A:$FG,$A78,FALSE)^(1/(R$2/12)))-1,"") | ... X78: =IFERROR((VLOOKUP(X$2,'R.WEALTH-Cummulative'!$A:$FG,$A78,FALSE)^(1/(X$2/12)))-1,"") | Y78: =VLOOKUP(Y$2,'Since Inception Returns'!$B:$AAB,Summary!A78-1,FALSE) -> 0.072111899 | Z78: =VLOOKUP(Z$2,'Since Inception Returns'!$B:$AAB,Summary!A78-1,FALSE) -> 0.034467513
B79: 45 | C79: HRVJ | D79: TBIL | E79: Bank of Canada Treasury Bills One Month Index | F79: =IFERROR(VLOOKUP(F$2,'R.WEALTH-Cummulative (BM)'!$A:$FH,$B79,FALSE)-1,"") -> -4.1166607e-05 | G79: =IFERROR(VLOOKUP(G$2,'R.WEALTH-Cummulative (BM)'!$A:$FH,$B79,FALSE)-1,"") -> 8.2343383e-05 | H79: =IFERROR(VLOOKUP(H$2,'R.WEALTH-Cummulative (BM)'!$A:$FH,$B79,FALSE)-1,"") -> 0.00045305758 | I79: =IFERROR(VLOOKUP(I$2,'R.WEALTH-Cummulative (BM)'!$A:$FH,$B79,FALSE)-1,"") -> -4.1166607e-05 | J79: =IFERROR(VLOOKUP(J$2,'R.WEALTH-Cummulative (BM)'!$A:$FH,$B79,FALSE)-1,"") -> 0.00064263822 | K79: =IFERROR((VLOOKUP(K$2,'R.WEALTH-Cummulative (BM)'!$A:$FH,$B79,FALSE)^(1/(K$2/12)))-1,"") -> 0.0012042843 | L79: =IFERROR((VLOOKUP(L$2,'R.WEALTH-Cummulative (BM)'!$A:$FH,$B79,FALSE)^(1/(L$2/12)))-1,"") | M79: =IFERROR((VLOOKUP(M$2,'R.WEALTH-Cummulative (BM)'!$A:$FH,$B79,FALSE)^(1/(M$2/12)))-1,"") | N79: =IFERROR((VLOOKUP(N$2,'R.WEALTH-Cummulative (BM)'!$A:$FH,$B79,FALSE)^(1/(N$2/12)))-1,"") | O79: =IFERROR((VLOOKUP(O$2,'R.WEALTH-Cummulative (BM)'!$A:$FH,$B79,FALSE)^(1/(O$2/12)))-1,"") | P79: =IFERROR((VLOOKUP(P$2,'R.WEALTH-Cummulative (BM)'!$A:$FH,$B79,FALSE)^(1/(P$2/12)))-1,"") | Q79: =IFERROR((VLOOKUP(Q$2,'R.WEALTH-Cummulative (BM)'!$A:$FH,$B79,FALSE)^(1/(Q$2/12)))-1,"") | R79: =IFERROR((VLOOKUP(R$2,'R.WEALTH-Cummulative (BM)'!$A:$FH,$B79,FALSE)^(1/(R$2/12)))-1,"") | ... X79: =IFERROR((VLOOKUP(X$2,'R.WEALTH-Cummulative (BM)'!$A:$FH,$B79,FALSE)^(1/(X$2/12)))-1,"") | Y79: =VLOOKUP(Y$2,'Since Inception (BM)'!$B:$AAC,Summary!B79-1,FALSE) -> 0.0023686596 | Z79: =VLOOKUP(Z$2,'Since Inception (BM)'!$B:$AAC,Summary!B79-1,FALSE) -> 0.0011520477
A80: 45 | C80: HRAX | D80: HDIF | E80: Harvest Diversified Monthly Income ETF | F80: =IFERROR(VLOOKUP(F$2,'R.WEALTH-Cummulative'!$A:$FG,$A80,FALSE)-1,"") -> 0.0045624315 | G80: =IFERROR(VLOOKUP(G$2,'R.WEALTH-Cummulative'!$A:$FG,$A80,FALSE)-1,"") -> 0.037776627 | H80: =IFERROR(VLOOKUP(H$2,'R.WEALTH-Cummulative'!$A:$FG,$A80,FALSE)-1,"") -> 0.10627477 | I80: =IFERROR(VLOOKUP(I$2,'R.WEALTH-Cummulative'!$A:$FG,$A80,FALSE)-1,"") -> 0.0045624315 | J80: =IFERROR(VLOOKUP(J$2,'R.WEALTH-Cummulative'!$A:$FG,$A80,FALSE)-1,"") -> 0.11712546 | K80: =IFERROR((VLOOKUP(K$2,'R.WEALTH-Cummulative'!$A:$FG,$A80,FALSE)^(1/(K$2/12)))-1,"") -> 0.16619934 | L80: =IFERROR((VLOOKUP(L$2,'R.WEALTH-Cummulative'!$A:$FG,$A80,FALSE)^(1/(L$2/12)))-1,"") -> 0.13332449 | M80: =IFERROR((VLOOKUP(M$2,'R.WEALTH-Cummulative'!$A:$FG,$A80,FALSE)^(1/(M$2/12)))-1,"") | N80: =IFERROR((VLOOKUP(N$2,'R.WEALTH-Cummulative'!$A:$FG,$A80,FALSE)^(1/(N$2/12)))-1,"") | O80: =IFERROR((VLOOKUP(O$2,'R.WEALTH-Cummulative'!$A:$FG,$A80,FALSE)^(1/(O$2/12)))-1,"") | P80: =IFERROR((VLOOKUP(P$2,'R.WEALTH-Cummulative'!$A:$FG,$A80,FALSE)^(1/(P$2/12)))-1,"") | Q80: =IFERROR((VLOOKUP(Q$2,'R.WEALTH-Cummulative'!$A:$FG,$A80,FALSE)^(1/(Q$2/12)))-1,"") | R80: =IFERROR((VLOOKUP(R$2,'R.WEALTH-Cummulative'!$A:$FG,$A80,FALSE)^(1/(R$2/12)))-1,"") | ... X80: =IFERROR((VLOOKUP(X$2,'R.WEALTH-Cummulative'!$A:$FG,$A80,FALSE)^(1/(X$2/12)))-1,"") | Y80: =VLOOKUP(Y$2,'Since Inception Returns'!$B:$AAB,Summary!A80-1,FALSE) -> 0.33666838 | Z80: =VLOOKUP(Z$2,'Since Inception Returns'!$B:$AAB,Summary!A80-1,FALSE) -> 0.075964958
B81: 46 | C81: HRAX | D81: HDIF | E81: Solactive GBS United States 500 Index TR | F81: =IFERROR(VLOOKUP(F$2,'R.WEALTH-Cummulative (BM)'!$A:$FH,$B81,FALSE)-1,"") -> 0.012539964 | G81: =IFERROR(VLOOKUP(G$2,'R.WEALTH-Cummulative (BM)'!$A:$FH,$B81,FALSE)-1,"") -> 0.01270775 | H81: =IFERROR(VLOOKUP(H$2,'R.WEALTH-Cummulative (BM)'!$A:$FH,$B81,FALSE)-1,"") -> 0.096905279 | I81: =IFERROR(VLOOKUP(I$2,'R.WEALTH-Cummulative (BM)'!$A:$FH,$B81,FALSE)-1,"") -> 0.012539964 | J81: =IFERROR(VLOOKUP(J$2,'R.WEALTH-Cummulative (BM)'!$A:$FH,$B81,FALSE)-1,"") -> 0.15937136 | K81: =IFERROR((VLOOKUP(K$2,'R.WEALTH-Cummulative (BM)'!$A:$FH,$B81,FALSE)^(1/(K$2/12)))-1,"") -> 0.21519072 | L81: =IFERROR((VLOOKUP(L$2,'R.WEALTH-Cummulative (BM)'!$A:$FH,$B81,FALSE)^(1/(L$2/12)))-1,"") -> 0.2161744 | M81: =IFERROR((VLOOKUP(M$2,'R.WEALTH-Cummulative (BM)'!$A:$FH,$B81,FALSE)^(1/(M$2/12)))-1,"") | N81: =IFERROR((VLOOKUP(N$2,'R.WEALTH-Cummulative (BM)'!$A:$FH,$B81,FALSE)^(1/(N$2/12)))-1,"") | O81: =IFERROR((VLOOKUP(O$2,'R.WEALTH-Cummulative (BM)'!$A:$FH,$B81,FALSE)^(1/(O$2/12)))-1,"") | P81: =IFERROR((VLOOKUP(P$2,'R.WEALTH-Cummulative (BM)'!$A:$FH,$B81,FALSE)^(1/(P$2/12)))-1,"") | Q81: =IFERROR((VLOOKUP(Q$2,'R.WEALTH-Cummulative (BM)'!$A:$FH,$B81,FALSE)^(1/(Q$2/12)))-1,"") | R81: =IFERROR((VLOOKUP(R$2,'R.WEALTH-Cummulative (BM)'!$A:$FH,$B81,FALSE)^(1/(R$2/12)))-1,"") | ... X81: =IFERROR((VLOOKUP(X$2,'R.WEALTH-Cummulative (BM)'!$A:$FH,$B81,FALSE)^(1/(X$2/12)))-1,"") | Y81: =VLOOKUP(Y$2,'Since Inception (BM)'!$B:$AAC,Summary!B81-1,FALSE) -> 0.66302707 | Z81: =VLOOKUP(Z$2,'Since Inception (BM)'!$B:$AAC,Summary!B81-1,FALSE) -> 0.13693864
A82: 46 | C82: HRTS | D82: PRM | E82: Big Pharm Fund | F82: =IFERROR(VLOOKUP(F$2,'R.WEALTH-Cummulative'!$A:$FG,$A82,FALSE)-1,"") -> 0.019210503 | G82: =IFERROR(VLOOKUP(G$2,'R.WEALTH-Cummulative'!$A:$FG,$A82,FALSE)-1,"") -> 0.11263726 | H82: =IFERROR(VLOOKUP(H$2,'R.WEALTH-Cummulative'!$A:$FG,$A82,FALSE)-1,"") -> 0.23458446 | I82: =IFERROR(VLOOKUP(I$2,'R.WEALTH-Cummulative'!$A:$FG,$A82,FALSE)-1,"") -> 0.019210503 | J82: =IFERROR(VLOOKUP(J$2,'R.WEALTH-Cummulative'!$A:$FG,$A82,FALSE)-1,"") -> 0.15934471 | K82: =IFERROR((VLOOKUP(K$2,'R.WEALTH-Cummulative'!$A:$FG,$A82,FALSE)^(1/(K$2/12)))-1,"") -> 0.088925156 | L82: =IFERROR((VLOOKUP(L$2,'R.WEALTH-Cummulative'!$A:$FG,$A82,FALSE)^(1/(L$2/12)))-1,"") -> 0.074282224 | M82: =IFERROR((VLOOKUP(M$2,'R.WEALTH-Cummulative'!$A:$FG,$A82,FALSE)^(1/(M$2/12)))-1,"") -> 0.072599512 | N82: =IFERROR((VLOOKUP(N$2,'R.WEALTH-Cummulative'!$A:$FG,$A82,FALSE)^(1/(N$2/12)))-1,"") -> 0.082995791 | O82: =IFERROR((VLOOKUP(O$2,'R.WEALTH-Cummulative'!$A:$FG,$A82,FALSE)^(1/(O$2/12)))-1,"") -> 0.080385502 | P82: =IFERROR((VLOOKUP(P$2,'R.WEALTH-Cummulative'!$A:$FG,$A82,FALSE)^(1/(P$2/12)))-1,"") -> 0.087115035 | Q82: =IFERROR((VLOOKUP(Q$2,'R.WEALTH-Cummulative'!$A:$FG,$A82,FALSE)^(1/(Q$2/12)))-1,"") -> 0.080800954 | R82: =IFERROR((VLOOKUP(R$2,'R.WEALTH-Cummulative'!$A:$FG,$A82,FALSE)^(1/(R$2/12)))-1,"") | ... X82: =IFERROR((VLOOKUP(X$2,'R.WEALTH-Cummulative'!$A:$FG,$A82,FALSE)^(1/(X$2/12)))-1,"") | Y82: =VLOOKUP(Y$2,'Since Inception Returns'!$B:$AAB,Summary!A82-1,FALSE) -> 0.92996114 | Z82: =VLOOKUP(Z$2,'Since Inception Returns'!$B:$AAB,Summary!A82-1,FALSE) -> 0.083639309
A83: 47 | C83: HRTSP | D83: PRM.PR.A | E83: Big Pharma Split Corp Preferred class | F83: =IFERROR(VLOOKUP(F$2,'R.WEALTH-Cummulative'!$A:$FG,$A83,FALSE)-1,"") -> 0 | G83: =IFERROR(VLOOKUP(G$2,'R.WEALTH-Cummulative'!$A:$FG,$A83,FALSE)-1,"") -> 0.0125 | H83: =IFERROR(VLOOKUP(H$2,'R.WEALTH-Cummulative'!$A:$FG,$A83,FALSE)-1,"") -> 0.02515625 | I83: =IFERROR(VLOOKUP(I$2,'R.WEALTH-Cummulative'!$A:$FG,$A83,FALSE)-1,"") -> 0 | J83: =IFERROR(VLOOKUP(J$2,'R.WEALTH-Cummulative'!$A:$FG,$A83,FALSE)-1,"") -> 0.050945337 | K83: =IFERROR((VLOOKUP(K$2,'R.WEALTH-Cummulative'!$A:$FG,$A83,FALSE)^(1/(K$2/12)))-1,"") -> 0.050945337 | L83: =IFERROR((VLOOKUP(L$2,'R.WEALTH-Cummulative'!$A:$FG,$A83,FALSE)^(1/(L$2/12)))-1,"") -> 0.050945337 | M83: =IFERROR((VLOOKUP(M$2,'R.WEALTH-Cummulative'!$A:$FG,$A83,FALSE)^(1/(M$2/12)))-1,"") -> 0.050945337 | N83: =IFERROR((VLOOKUP(N$2,'R.WEALTH-Cummulative'!$A:$FG,$A83,FALSE)^(1/(N$2/12)))-1,"") -> 0.050945337 | O83: =IFERROR((VLOOKUP(O$2,'R.WEALTH-Cummulative'!$A:$FG,$A83,FALSE)^(1/(O$2/12)))-1,"") -> 0.050945337 | P83: =IFERROR((VLOOKUP(P$2,'R.WEALTH-Cummulative'!$A:$FG,$A83,FALSE)^(1/(P$2/12)))-1,"") -> 0.050945337 | Q83: =IFERROR((VLOOKUP(Q$2,'R.WEALTH-Cummulative'!$A:$FG,$A83,FALSE)^(1/(Q$2/12)))-1,"") -> 0.050945337 | R83: =IFERROR((VLOOKUP(R$2,'R.WEALTH-Cummulative'!$A:$FG,$A83,FALSE)^(1/(R$2/12)))-1,"") | ... X83: =IFERROR((VLOOKUP(X$2,'R.WEALTH-Cummulative'!$A:$FG,$A83,FALSE)^(1/(X$2/12)))-1,"") | Y83: =VLOOKUP(Y$2,'Since Inception Returns'!$B:$AAB,Summary!A83-1,FALSE) -> 0.49581373 | Z83: =VLOOKUP(Z$2,'Since Inception Returns'!$B:$AAB,Summary!A83-1,FALSE) -> 0.0504233
A84: 48 | C84: HRTS | D84: PRM | E84: Big Pharma Split Corp | F84: =IFERROR(VLOOKUP(F$2,'R.WEALTH-Cummulative'!$A:$FG,$A84,FALSE)-1,"") -> 0.032924749 | G84: =IFERROR(VLOOKUP(G$2,'R.WEALTH-Cummulative'!$A:$FG,$A84,FALSE)-1,"") -> 0.1940638 | H84: =IFERROR(VLOOKUP(H$2,'R.WEALTH-Cummulative'!$A:$FG,$A84,FALSE)-1,"") -> 0.43562679 | I84: =IFERROR(VLOOKUP(I$2,'R.WEALTH-Cummulative'!$A:$FG,$A84,FALSE)-1,"") -> 0.032924749 | J84: =IFERROR(VLOOKUP(J$2,'R.WEALTH-Cummulative'!$A:$FG,$A84,FALSE)-1,"") -> 0.24952377 | K84: =IFERROR((VLOOKUP(K$2,'R.WEALTH-Cummulative'!$A:$FG,$A84,FALSE)^(1/(K$2/12)))-1,"") -> 0.11862177 | L84: =IFERROR((VLOOKUP(L$2,'R.WEALTH-Cummulative'!$A:$FG,$A84,FALSE)^(1/(L$2/12)))-1,"") -> 0.092630211 | M84: =IFERROR((VLOOKUP(M$2,'R.WEALTH-Cummulative'!$A:$FG,$A84,FALSE)^(1/(M$2/12)))-1,"") -> 0.089113229 | N84: =IFERROR((VLOOKUP(N$2,'R.WEALTH-Cummulative'!$A:$FG,$A84,FALSE)^(1/(N$2/12)))-1,"") -> 0.10727607 | O84: =IFERROR((VLOOKUP(O$2,'R.WEALTH-Cummulative'!$A:$FG,$A84,FALSE)^(1/(O$2/12)))-1,"") -> 0.10267206 | P84: =IFERROR((VLOOKUP(P$2,'R.WEALTH-Cummulative'!$A:$FG,$A84,FALSE)^(1/(P$2/12)))-1,"") -> 0.11453969 | Q84: =IFERROR((VLOOKUP(Q$2,'R.WEALTH-Cummulative'!$A:$FG,$A84,FALSE)^(1/(Q$2/12)))-1,"") -> 0.10332079 | R84: =IFERROR((VLOOKUP(R$2,'R.WEALTH-Cummulative'!$A:$FG,$A84,FALSE)^(1/(R$2/12)))-1,"") | ... X84: =IFERROR((VLOOKUP(X$2,'R.WEALTH-Cummulative'!$A:$FG,$A84,FALSE)^(1/(X$2/12)))-1,"") | Y84: =VLOOKUP(Y$2,'Since Inception Returns'!$B:$AAB,Summary!A84-1,FALSE) -> 1.3266941 | Z84: =VLOOKUP(Z$2,'Since Inception Returns'!$B:$AAB,Summary!A84-1,FALSE) -> 0.10867338
B85: 49 | C85: HRTS | D85: PRM | E85: MSCI World Pharmaceuticals Gross Total Return Local Index | F85: =IFERROR(VLOOKUP(F$2,'R.WEALTH-Cummulative (BM)'!$A:$FH,$B85,FALSE)-1,"") -> 0.031404596 | G85: =IFERROR(VLOOKUP(G$2,'R.WEALTH-Cummulative (BM)'!$A:$FH,$B85,FALSE)-1,"") -> 0.17749212 | H85: =IFERROR(VLOOKUP(H$2,'R.WEALTH-Cummulative (BM)'!$A:$FH,$B85,FALSE)-1,"") -> 0.29564764 | I85: =IFERROR(VLOOKUP(I$2,'R.WEALTH-Cummulative (BM)'!$A:$FH,$B85,FALSE)-1,"") -> 0.031404596 | J85: =IFERROR(VLOOKUP(J$2,'R.WEALTH-Cummulative (BM)'!$A:$FH,$B85,FALSE)-1,"") -> 0.17817466 | K85: =IFERROR((VLOOKUP(K$2,'R.WEALTH-Cummulative (BM)'!$A:$FH,$B85,FALSE)^(1/(K$2/12)))-1,"") -> 0.11380074 | L85: =IFERROR((VLOOKUP(L$2,'R.WEALTH-Cummulative (BM)'!$A:$FH,$B85,FALSE)^(1/(L$2/12)))-1,"") -> 0.11617629 | M85: =IFERROR((VLOOKUP(M$2,'R.WEALTH-Cummulative (BM)'!$A:$FH,$B85,FALSE)^(1/(M$2/12)))-1,"") -> 0.1061368 | N85: =IFERROR((VLOOKUP(N$2,'R.WEALTH-Cummulative (BM)'!$A:$FH,$B85,FALSE)^(1/(N$2/12)))-1,"") -> 0.11691929 | O85: =IFERROR((VLOOKUP(O$2,'R.WEALTH-Cummulative (BM)'!$A:$FH,$B85,FALSE)^(1/(O$2/12)))-1,"") -> 0.10185507 | P85: =IFERROR((VLOOKUP(P$2,'R.WEALTH-Cummulative (BM)'!$A:$FH,$B85,FALSE)^(1/(P$2/12)))-1,"") -> 0.11261058 | Q85: =IFERROR((VLOOKUP(Q$2,'R.WEALTH-Cummulative (BM)'!$A:$FH,$B85,FALSE)^(1/(Q$2/12)))-1,"") -> 0.10592731 | R85: =IFERROR((VLOOKUP(R$2,'R.WEALTH-Cummulative (BM)'!$A:$FH,$B85,FALSE)^(1/(R$2/12)))-1,"") | ... X85: =IFERROR((VLOOKUP(X$2,'R.WEALTH-Cummulative (BM)'!$A:$FH,$B85,FALSE)^(1/(X$2/12)))-1,"") | Y85: =VLOOKUP(Y$2,'Since Inception (BM)'!$B:$AAC,Summary!B85-1,FALSE) -> 1.2727477 | Z85: =VLOOKUP(Z$2,'Since Inception (BM)'!$B:$AAC,Summary!B85-1,FALSE) -> 0.10550056
A86: 49 | C86: HRVL_A | D86: HPYM | E86: Harvest Premium Yield Treasury 7-10 Year Treasury ETF | F86: =IFERROR(VLOOKUP(F$2,'R.WEALTH-Cummulative'!$A:$FG,$A86,FALSE)-1,"") -> -0.0021237408 | G86: =IFERROR(VLOOKUP(G$2,'R.WEALTH-Cummulative'!$A:$FG,$A86,FALSE)-1,"") -> -0.00050712575 | H86: =IFERROR(VLOOKUP(H$2,'R.WEALTH-Cummulative'!$A:$FG,$A86,FALSE)-1,"") -> 0.025946831 | I86: =IFERROR(VLOOKUP(I$2,'R.WEALTH-Cummulative'!$A:$FG,$A86,FALSE)-1,"") -> -0.0021237408 | J86: =IFERROR(VLOOKUP(J$2,'R.WEALTH-Cummulative'!$A:$FG,$A86,FALSE)-1,"") -> 0.057875352 | K86: =IFERROR((VLOOKUP(K$2,'R.WEALTH-Cummulative'!$A:$FG,$A86,FALSE)^(1/(K$2/12)))-1,"") -> 0.02137388 | L86: =IFERROR((VLOOKUP(L$2,'R.WEALTH-Cummulative'!$A:$FG,$A86,FALSE)^(1/(L$2/12)))-1,"") | M86: =IFERROR((VLOOKUP(M$2,'R.WEALTH-Cummulative'!$A:$FG,$A86,FALSE)^(1/(M$2/12)))-1,"") | N86: =IFERROR((VLOOKUP(N$2,'R.WEALTH-Cummulative'!$A:$FG,$A86,FALSE)^(1/(N$2/12)))-1,"") | O86: =IFERROR((VLOOKUP(O$2,'R.WEALTH-Cummulative'!$A:$FG,$A86,FALSE)^(1/(O$2/12)))-1,"") | P86: =IFERROR((VLOOKUP(P$2,'R.WEALTH-Cummulative'!$A:$FG,$A86,FALSE)^(1/(P$2/12)))-1,"") | Q86: =IFERROR((VLOOKUP(Q$2,'R.WEALTH-Cummulative'!$A:$FG,$A86,FALSE)^(1/(Q$2/12)))-1,"") | R86: =IFERROR((VLOOKUP(R$2,'R.WEALTH-Cummulative'!$A:$FG,$A86,FALSE)^(1/(R$2/12)))-1,"") | ... X86: =IFERROR((VLOOKUP(X$2,'R.WEALTH-Cummulative'!$A:$FG,$A86,FALSE)^(1/(X$2/12)))-1,"") | Y86: =VLOOKUP(Y$2,'Since Inception Returns'!$B:$AAB,Summary!A86-1,FALSE) -> 0.043674045 | Z86: =VLOOKUP(Z$2,'Since Inception Returns'!$B:$AAB,Summary!A86-1,FALSE) -> 0.021021553
A87: 50 | C87: HRVL_U | D87: HPYM.U | E87: Harvest Premium Yield Treasury 7-10 Year Treasury ETF | F87: =IFERROR(VLOOKUP(F$2,'R.WEALTH-Cummulative'!$A:$FG,$A87,FALSE)-1,"") -> -0.00082247364 | G87: =IFERROR(VLOOKUP(G$2,'R.WEALTH-Cummulative'!$A:$FG,$A87,FALSE)-1,"") -> 0.0046473723 | H87: =IFERROR(VLOOKUP(H$2,'R.WEALTH-Cummulative'!$A:$FG,$A87,FALSE)-1,"") -> 0.03472861 | I87: =IFERROR(VLOOKUP(I$2,'R.WEALTH-Cummulative'!$A:$FG,$A87,FALSE)-1,"") -> -0.00082247364 | J87: =IFERROR(VLOOKUP(J$2,'R.WEALTH-Cummulative'!$A:$FG,$A87,FALSE)-1,"") -> 0.07633965 | K87: =IFERROR((VLOOKUP(K$2,'R.WEALTH-Cummulative'!$A:$FG,$A87,FALSE)^(1/(K$2/12)))-1,"") -> 0.035751709 | L87: =IFERROR((VLOOKUP(L$2,'R.WEALTH-Cummulative'!$A:$FG,$A87,FALSE)^(1/(L$2/12)))-1,"") | M87: =IFERROR((VLOOKUP(M$2,'R.WEALTH-Cummulative'!$A:$FG,$A87,FALSE)^(1/(M$2/12)))-1,"") | N87: =IFERROR((VLOOKUP(N$2,'R.WEALTH-Cummulative'!$A:$FG,$A87,FALSE)^(1/(N$2/12)))-1,"") | O87: =IFERROR((VLOOKUP(O$2,'R.WEALTH-Cummulative'!$A:$FG,$A87,FALSE)^(1/(O$2/12)))-1,"") | P87: =IFERROR((VLOOKUP(P$2,'R.WEALTH-Cummulative'!$A:$FG,$A87,FALSE)^(1/(P$2/12)))-1,"") | Q87: =IFERROR((VLOOKUP(Q$2,'R.WEALTH-Cummulative'!$A:$FG,$A87,FALSE)^(1/(Q$2/12)))-1,"") | R87: =IFERROR((VLOOKUP(R$2,'R.WEALTH-Cummulative'!$A:$FG,$A87,FALSE)^(1/(R$2/12)))-1,"") | ... X87: =IFERROR((VLOOKUP(X$2,'R.WEALTH-Cummulative'!$A:$FG,$A87,FALSE)^(1/(X$2/12)))-1,"") | Y87: =VLOOKUP(Y$2,'Since Inception Returns'!$B:$AAB,Summary!A87-1,FALSE) -> 0.072495528 | Z87: =VLOOKUP(Z$2,'Since Inception Returns'!$B:$AAB,Summary!A87-1,FALSE) -> 0.034647641
B88: 51 | C88: HRVL_A | D88: HPYM | E88: Solactive US 7-10 Year Treasury Bond Index (Total Return) | F88: =IFERROR(VLOOKUP(F$2,'R.WEALTH-Cummulative (BM)'!$A:$FH,$B88,FALSE)-1,"") -> -0.0021793054 | G88: =IFERROR(VLOOKUP(G$2,'R.WEALTH-Cummulative (BM)'!$A:$FH,$B88,FALSE)-1,"") -> 0.0001197129 | H88: =IFERROR(VLOOKUP(H$2,'R.WEALTH-Cummulative (BM)'!$A:$FH,$B88,FALSE)-1,"") -> 0.030801666 | I88: =IFERROR(VLOOKUP(I$2,'R.WEALTH-Cummulative (BM)'!$A:$FH,$B88,FALSE)-1,"") -> -0.0021793054 | J88: =IFERROR(VLOOKUP(J$2,'R.WEALTH-Cummulative (BM)'!$A:$FH,$B88,FALSE)-1,"") -> 0.072239965 | K88: =IFERROR((VLOOKUP(K$2,'R.WEALTH-Cummulative (BM)'!$A:$FH,$B88,FALSE)^(1/(K$2/12)))-1,"") -> 0.036338729 | L88: =IFERROR((VLOOKUP(L$2,'R.WEALTH-Cummulative (BM)'!$A:$FH,$B88,FALSE)^(1/(L$2/12)))-1,"") | M88: =IFERROR((VLOOKUP(M$2,'R.WEALTH-Cummulative (BM)'!$A:$FH,$B88,FALSE)^(1/(M$2/12)))-1,"") | N88: =IFERROR((VLOOKUP(N$2,'R.WEALTH-Cummulative (BM)'!$A:$FH,$B88,FALSE)^(1/(N$2/12)))-1,"") | O88: =IFERROR((VLOOKUP(O$2,'R.WEALTH-Cummulative (BM)'!$A:$FH,$B88,FALSE)^(1/(O$2/12)))-1,"") | P88: =IFERROR((VLOOKUP(P$2,'R.WEALTH-Cummulative (BM)'!$A:$FH,$B88,FALSE)^(1/(P$2/12)))-1,"") | Q88: =IFERROR((VLOOKUP(Q$2,'R.WEALTH-Cummulative (BM)'!$A:$FH,$B88,FALSE)^(1/(Q$2/12)))-1,"") | R88: =IFERROR((VLOOKUP(R$2,'R.WEALTH-Cummulative (BM)'!$A:$FH,$B88,FALSE)^(1/(R$2/12)))-1,"") | ... X88: =IFERROR((VLOOKUP(X$2,'R.WEALTH-Cummulative (BM)'!$A:$FH,$B88,FALSE)^(1/(X$2/12)))-1,"") | Y88: =VLOOKUP(Y$2,'Since Inception (BM)'!$B:$AAC,Summary!B88-1,FALSE) -> 0.079136987 | Z88: =VLOOKUP(Z$2,'Since Inception (BM)'!$B:$AAC,Summary!B88-1,FALSE) -> 0.037760815
A89: 51 | C89: HRVN | D89: HBIG | E89: Harvest Balanced Income & Growth ETF | F89: =IFERROR(VLOOKUP(F$2,'R.WEALTH-Cummulative'!$A:$FG,$A89,FALSE)-1,"") -> 0.0026343782 | G89: =IFERROR(VLOOKUP(G$2,'R.WEALTH-Cummulative'!$A:$FG,$A89,FALSE)-1,"") -> 0.017027086 | H89: =IFERROR(VLOOKUP(H$2,'R.WEALTH-Cummulative'!$A:$FG,$A89,FALSE)-1,"") -> 0.061405009 | I89: =IFERROR(VLOOKUP(I$2,'R.WEALTH-Cummulative'!$A:$FG,$A89,FALSE)-1,"") -> 0.0026343782 | J89: =IFERROR(VLOOKUP(J$2,'R.WEALTH-Cummulative'!$A:$FG,$A89,FALSE)-1,"") -> 0.077917593 | K89: =IFERROR((VLOOKUP(K$2,'R.WEALTH-Cummulative'!$A:$FG,$A89,FALSE)^(1/(K$2/12)))-1,"") | L89: =IFERROR((VLOOKUP(L$2,'R.WEALTH-Cummulative'!$A:$FG,$A89,FALSE)^(1/(L$2/12)))-1,"") | M89: =IFERROR((VLOOKUP(M$2,'R.WEALTH-Cummulative'!$A:$FG,$A89,FALSE)^(1/(M$2/12)))-1,"") | N89: =IFERROR((VLOOKUP(N$2,'R.WEALTH-Cummulative'!$A:$FG,$A89,FALSE)^(1/(N$2/12)))-1,"") | O89: =IFERROR((VLOOKUP(O$2,'R.WEALTH-Cummulative'!$A:$FG,$A89,FALSE)^(1/(O$2/12)))-1,"") | P89: =IFERROR((VLOOKUP(P$2,'R.WEALTH-Cummulative'!$A:$FG,$A89,FALSE)^(1/(P$2/12)))-1,"") | Q89: =IFERROR((VLOOKUP(Q$2,'R.WEALTH-Cummulative'!$A:$FG,$A89,FALSE)^(1/(Q$2/12)))-1,"") | R89: =IFERROR((VLOOKUP(R$2,'R.WEALTH-Cummulative'!$A:$FG,$A89,FALSE)^(1/(R$2/12)))-1,"") | ... X89: =IFERROR((VLOOKUP(X$2,'R.WEALTH-Cummulative'!$A:$FG,$A89,FALSE)^(1/(X$2/12)))-1,"") | Y89: =VLOOKUP(Y$2,'Since Inception Returns'!$B:$AAB,Summary!A89-1,FALSE) -> 0.15572386 | Z89: =VLOOKUP(Z$2,'Since Inception Returns'!$B:$AAB,Summary!A89-1,FALSE) -> 0.083493146
B90: 52 | C90: HRVN | D90: HBIG | E90: Blended Benchmark | F90: =IFERROR(VLOOKUP(F$2,'R.WEALTH-Cummulative (BM)'!$A:$FH,$B90,FALSE)-1,"") -> 0.0070084015 | G90: =IFERROR(VLOOKUP(G$2,'R.WEALTH-Cummulative (BM)'!$A:$FH,$B90,FALSE)-1,"") -> 0.0053055571 | H90: =IFERROR(VLOOKUP(H$2,'R.WEALTH-Cummulative (BM)'!$A:$FH,$B90,FALSE)-1,"") -> 0.066456296 | I90: =IFERROR(VLOOKUP(I$2,'R.WEALTH-Cummulative (BM)'!$A:$FH,$B90,FALSE)-1,"") -> 0.0070084015 | J90: =IFERROR(VLOOKUP(J$2,'R.WEALTH-Cummulative (BM)'!$A:$FH,$B90,FALSE)-1,"") -> 0.11458818 | K90: =IFERROR((VLOOKUP(K$2,'R.WEALTH-Cummulative (BM)'!$A:$FH,$B90,FALSE)^(1/(K$2/12)))-1,"") | L90: =IFERROR((VLOOKUP(L$2,'R.WEALTH-Cummulative (BM)'!$A:$FH,$B90,FALSE)^(1/(L$2/12)))-1,"") | M90: =IFERROR((VLOOKUP(M$2,'R.WEALTH-Cummulative (BM)'!$A:$FH,$B90,FALSE)^(1/(M$2/12)))-1,"") | N90: =IFERROR((VLOOKUP(N$2,'R.WEALTH-Cummulative (BM)'!$A:$FH,$B90,FALSE)^(1/(N$2/12)))-1,"") | O90: =IFERROR((VLOOKUP(O$2,'R.WEALTH-Cummulative (BM)'!$A:$FH,$B90,FALSE)^(1/(O$2/12)))-1,"") | P90: =IFERROR((VLOOKUP(P$2,'R.WEALTH-Cummulative (BM)'!$A:$FH,$B90,FALSE)^(1/(P$2/12)))-1,"") | Q90: =IFERROR((VLOOKUP(Q$2,'R.WEALTH-Cummulative (BM)'!$A:$FH,$B90,FALSE)^(1/(Q$2/12)))-1,"") | R90: =IFERROR((VLOOKUP(R$2,'R.WEALTH-Cummulative (BM)'!$A:$FH,$B90,FALSE)^(1/(R$2/12)))-1,"") | ... X90: =IFERROR((VLOOKUP(X$2,'R.WEALTH-Cummulative (BM)'!$A:$FH,$B90,FALSE)^(1/(X$2/12)))-1,"") | Y90: =VLOOKUP(Y$2,'Since Inception (BM)'!$B:$AAC,Summary!B90-1,FALSE) -> 0.25033253 | Z90: =VLOOKUP(Z$2,'Since Inception (BM)'!$B:$AAC,Summary!B90-1,FALSE) -> 0.13177443
A91: 52 | C91: HRVO | D91: HBIE | E91: Harvest Balanced Income & Growth Enhanced ETF | F91: =IFERROR(VLOOKUP(F$2,'R.WEALTH-Cummulative'!$A:$FG,$A91,FALSE)-1,"") -> 0.002614495 | G91: =IFERROR(VLOOKUP(G$2,'R.WEALTH-Cummulative'!$A:$FG,$A91,FALSE)-1,"") -> 0.018054439 | H91: =IFERROR(VLOOKUP(H$2,'R.WEALTH-Cummulative'!$A:$FG,$A91,FALSE)-1,"") -> 0.071722246 | I91: =IFERROR(VLOOKUP(I$2,'R.WEALTH-Cummulative'!$A:$FG,$A91,FALSE)-1,"") -> 0.002614495 | J91: =IFERROR(VLOOKUP(J$2,'R.WEALTH-Cummulative'!$A:$FG,$A91,FALSE)-1,"") -> 0.088394264 | K91: =IFERROR((VLOOKUP(K$2,'R.WEALTH-Cummulative'!$A:$FG,$A91,FALSE)^(1/(K$2/12)))-1,"") | L91: =IFERROR((VLOOKUP(L$2,'R.WEALTH-Cummulative'!$A:$FG,$A91,FALSE)^(1/(L$2/12)))-1,"") | M91: =IFERROR((VLOOKUP(M$2,'R.WEALTH-Cummulative'!$A:$FG,$A91,FALSE)^(1/(M$2/12)))-1,"") | N91: =IFERROR((VLOOKUP(N$2,'R.WEALTH-Cummulative'!$A:$FG,$A91,FALSE)^(1/(N$2/12)))-1,"") | O91: =IFERROR((VLOOKUP(O$2,'R.WEALTH-Cummulative'!$A:$FG,$A91,FALSE)^(1/(O$2/12)))-1,"") | P91: =IFERROR((VLOOKUP(P$2,'R.WEALTH-Cummulative'!$A:$FG,$A91,FALSE)^(1/(P$2/12)))-1,"") | Q91: =IFERROR((VLOOKUP(Q$2,'R.WEALTH-Cummulative'!$A:$FG,$A91,FALSE)^(1/(Q$2/12)))-1,"") | R91: =IFERROR((VLOOKUP(R$2,'R.WEALTH-Cummulative'!$A:$FG,$A91,FALSE)^(1/(R$2/12)))-1,"") | ... X91: =IFERROR((VLOOKUP(X$2,'R.WEALTH-Cummulative'!$A:$FG,$A91,FALSE)^(1/(X$2/12)))-1,"") | Y91: =VLOOKUP(Y$2,'Since Inception Returns'!$B:$AAB,Summary!A91-1,FALSE) -> 0.17841695 | Z91: =VLOOKUP(Z$2,'Since Inception Returns'!$B:$AAB,Summary!A91-1,FALSE) -> 0.095229966
B92: 53 | C92: HRVO | D92: HBIE | E92: Blended Benchmark | F92: =IFERROR(VLOOKUP(F$2,'R.WEALTH-Cummulative (BM)'!$A:$FH,$B92,FALSE)-1,"") -> 0.0070084015 | G92: =IFERROR(VLOOKUP(G$2,'R.WEALTH-Cummulative (BM)'!$A:$FH,$B92,FALSE)-1,"") -> 0.0053055571 | H92: =IFERROR(VLOOKUP(H$2,'R.WEALTH-Cummulative (BM)'!$A:$FH,$B92,FALSE)-1,"") -> 0.066456296 | I92: =IFERROR(VLOOKUP(I$2,'R.WEALTH-Cummulative (BM)'!$A:$FH,$B92,FALSE)-1,"") -> 0.0070084015 | J92: =IFERROR(VLOOKUP(J$2,'R.WEALTH-Cummulative (BM)'!$A:$FH,$B92,FALSE)-1,"") -> 0.11458818 | K92: =IFERROR((VLOOKUP(K$2,'R.WEALTH-Cummulative (BM)'!$A:$FH,$B92,FALSE)^(1/(K$2/12)))-1,"") | L92: =IFERROR((VLOOKUP(L$2,'R.WEALTH-Cummulative (BM)'!$A:$FH,$B92,FALSE)^(1/(L$2/12)))-1,"") | M92: =IFERROR((VLOOKUP(M$2,'R.WEALTH-Cummulative (BM)'!$A:$FH,$B92,FALSE)^(1/(M$2/12)))-1,"") | N92: =IFERROR((VLOOKUP(N$2,'R.WEALTH-Cummulative (BM)'!$A:$FH,$B92,FALSE)^(1/(N$2/12)))-1,"") | O92: =IFERROR((VLOOKUP(O$2,'R.WEALTH-Cummulative (BM)'!$A:$FH,$B92,FALSE)^(1/(O$2/12)))-1,"") | P92: =IFERROR((VLOOKUP(P$2,'R.WEALTH-Cummulative (BM)'!$A:$FH,$B92,FALSE)^(1/(P$2/12)))-1,"") | Q92: =IFERROR((VLOOKUP(Q$2,'R.WEALTH-Cummulative (BM)'!$A:$FH,$B92,FALSE)^(1/(Q$2/12)))-1,"") | R92: =IFERROR((VLOOKUP(R$2,'R.WEALTH-Cummulative (BM)'!$A:$FH,$B92,FALSE)^(1/(R$2/12)))-1,"") | ... X92: =IFERROR((VLOOKUP(X$2,'R.WEALTH-Cummulative (BM)'!$A:$FH,$B92,FALSE)^(1/(X$2/12)))-1,"") | Y92: =VLOOKUP(Y$2,'Since Inception (BM)'!$B:$AAC,Summary!B92-1,FALSE) -> 0.25033253 | Z92: =VLOOKUP(Z$2,'Since Inception (BM)'!$B:$AAC,Summary!B92-1,FALSE) -> 0.13177443
A93: 53 | C93: HRVP | D93: HIND | E93: Harvest Industrial Leaders Income ETF | F93: =IFERROR(VLOOKUP(F$2,'R.WEALTH-Cummulative'!$A:$FG,$A93,FALSE)-1,"") -> 0.04903791 | G93: =IFERROR(VLOOKUP(G$2,'R.WEALTH-Cummulative'!$A:$FG,$A93,FALSE)-1,"") -> 0.052665158 | H93: =IFERROR(VLOOKUP(H$2,'R.WEALTH-Cummulative'!$A:$FG,$A93,FALSE)-1,"") -> 0.10288778 | I93: =IFERROR(VLOOKUP(I$2,'R.WEALTH-Cummulative'!$A:$FG,$A93,FALSE)-1,"") -> 0.04903791 | J93: =IFERROR(VLOOKUP(J$2,'R.WEALTH-Cummulative'!$A:$FG,$A93,FALSE)-1,"") -> 0.10413092 | K93: =IFERROR((VLOOKUP(K$2,'R.WEALTH-Cummulative'!$A:$FG,$A93,FALSE)^(1/(K$2/12)))-1,"") | L93: =IFERROR((VLOOKUP(L$2,'R.WEALTH-Cummulative'!$A:$FG,$A93,FALSE)^(1/(L$2/12)))-1,"") | M93: =IFERROR((VLOOKUP(M$2,'R.WEALTH-Cummulative'!$A:$FG,$A93,FALSE)^(1/(M$2/12)))-1,"") | N93: =IFERROR((VLOOKUP(N$2,'R.WEALTH-Cummulative'!$A:$FG,$A93,FALSE)^(1/(N$2/12)))-1,"") | O93: =IFERROR((VLOOKUP(O$2,'R.WEALTH-Cummulative'!$A:$FG,$A93,FALSE)^(1/(O$2/12)))-1,"") | P93: =IFERROR((VLOOKUP(P$2,'R.WEALTH-Cummulative'!$A:$FG,$A93,FALSE)^(1/(P$2/12)))-1,"") | Q93: =IFERROR((VLOOKUP(Q$2,'R.WEALTH-Cummulative'!$A:$FG,$A93,FALSE)^(1/(Q$2/12)))-1,"") | R93: =IFERROR((VLOOKUP(R$2,'R.WEALTH-Cummulative'!$A:$FG,$A93,FALSE)^(1/(R$2/12)))-1,"") | ... X93: =IFERROR((VLOOKUP(X$2,'R.WEALTH-Cummulative'!$A:$FG,$A93,FALSE)^(1/(X$2/12)))-1,"") | Y93: =VLOOKUP(Y$2,'Since Inception Returns'!$B:$AAB,Summary!A93-1,FALSE) -> 0.20016677 | Z93: =VLOOKUP(Z$2,'Since Inception Returns'!$B:$AAB,Summary!A93-1,FALSE) -> 0.1063847
B94: 54 | C94: HRVP | D94: HIND | E94: MSCI USA IMI Industrials Gross Total Return USD Index | F94: =IFERROR(VLOOKUP(F$2,'R.WEALTH-Cummulative (BM)'!$A:$FH,$B94,FALSE)-1,"") -> 0.075872894 | G94: =IFERROR(VLOOKUP(G$2,'R.WEALTH-Cummulative (BM)'!$A:$FH,$B94,FALSE)-1,"") -> 0.069612157 | H94: =IFERROR(VLOOKUP(H$2,'R.WEALTH-Cummulative (BM)'!$A:$FH,$B94,FALSE)-1,"") -> 0.11040822 | I94: =IFERROR(VLOOKUP(I$2,'R.WEALTH-Cummulative (BM)'!$A:$FH,$B94,FALSE)-1,"") -> 0.075872894 | J94: =IFERROR(VLOOKUP(J$2,'R.WEALTH-Cummulative (BM)'!$A:$FH,$B94,FALSE)-1,"") -> 0.22016406 | K94: =IFERROR((VLOOKUP(K$2,'R.WEALTH-Cummulative (BM)'!$A:$FH,$B94,FALSE)^(1/(K$2/12)))-1,"") | L94: =IFERROR((VLOOKUP(L$2,'R.WEALTH-Cummulative (BM)'!$A:$FH,$B94,FALSE)^(1/(L$2/12)))-1,"") | M94: =IFERROR((VLOOKUP(M$2,'R.WEALTH-Cummulative (BM)'!$A:$FH,$B94,FALSE)^(1/(M$2/12)))-1,"") | N94: =IFERROR((VLOOKUP(N$2,'R.WEALTH-Cummulative (BM)'!$A:$FH,$B94,FALSE)^(1/(N$2/12)))-1,"") | O94: =IFERROR((VLOOKUP(O$2,'R.WEALTH-Cummulative (BM)'!$A:$FH,$B94,FALSE)^(1/(O$2/12)))-1,"") | P94: =IFERROR((VLOOKUP(P$2,'R.WEALTH-Cummulative (BM)'!$A:$FH,$B94,FALSE)^(1/(P$2/12)))-1,"") | Q94: =IFERROR((VLOOKUP(Q$2,'R.WEALTH-Cummulative (BM)'!$A:$FH,$B94,FALSE)^(1/(Q$2/12)))-1,"") | R94: =IFERROR((VLOOKUP(R$2,'R.WEALTH-Cummulative (BM)'!$A:$FH,$B94,FALSE)^(1/(R$2/12)))-1,"") | ... X94: =IFERROR((VLOOKUP(X$2,'R.WEALTH-Cummulative (BM)'!$A:$FH,$B94,FALSE)^(1/(X$2/12)))-1,"") | Y94: =VLOOKUP(Y$2,'Since Inception (BM)'!$B:$AAC,Summary!B94-1,FALSE) -> 0.36464107 | Z94: =VLOOKUP(Z$2,'Since Inception (BM)'!$B:$AAC,Summary!B94-1,FALSE) -> 0.18798505
A95: 54 | C95: HRQB_A | D95: AMZH | E95: Harvest Amazon High Income Shares ETF | F95: =IFERROR(VLOOKUP(F$2,'R.WEALTH-Cummulative'!$A:$FG,$A95,FALSE)-1,"") -> 0.024365923 | G95: =IFERROR(VLOOKUP(G$2,'R.WEALTH-Cummulative'!$A:$FG,$A95,FALSE)-1,"") -> -0.031897614 | H95: =IFERROR(VLOOKUP(H$2,'R.WEALTH-Cummulative'!$A:$FG,$A95,FALSE)-1,"") -> 0.028565488 | I95: =IFERROR(VLOOKUP(I$2,'R.WEALTH-Cummulative'!$A:$FG,$A95,FALSE)-1,"") -> 0.024365923 | J95: =IFERROR(VLOOKUP(J$2,'R.WEALTH-Cummulative'!$A:$FG,$A95,FALSE)-1,"") -> -0.034304617 | K95: =IFERROR((VLOOKUP(K$2,'R.WEALTH-Cummulative'!$A:$FG,$A95,FALSE)^(1/(K$2/12)))-1,"") | L95: =IFERROR((VLOOKUP(L$2,'R.WEALTH-Cummulative'!$A:$FG,$A95,FALSE)^(1/(L$2/12)))-1,"") | M95: =IFERROR((VLOOKUP(M$2,'R.WEALTH-Cummulative'!$A:$FG,$A95,FALSE)^(1/(M$2/12)))-1,"") | N95: =IFERROR((VLOOKUP(N$2,'R.WEALTH-Cummulative'!$A:$FG,$A95,FALSE)^(1/(N$2/12)))-1,"") | O95: =IFERROR((VLOOKUP(O$2,'R.WEALTH-Cummulative'!$A:$FG,$A95,FALSE)^(1/(O$2/12)))-1,"") | P95: =IFERROR((VLOOKUP(P$2,'R.WEALTH-Cummulative'!$A:$FG,$A95,FALSE)^(1/(P$2/12)))-1,"") | Q95: =IFERROR((VLOOKUP(Q$2,'R.WEALTH-Cummulative'!$A:$FG,$A95,FALSE)^(1/(Q$2/12)))-1,"") | R95: =IFERROR((VLOOKUP(R$2,'R.WEALTH-Cummulative'!$A:$FG,$A95,FALSE)^(1/(R$2/12)))-1,"") | ... X95: =IFERROR((VLOOKUP(X$2,'R.WEALTH-Cummulative'!$A:$FG,$A95,FALSE)^(1/(X$2/12)))-1,"") | Y95: =VLOOKUP(Y$2,'Since Inception Returns'!$B:$AAB,Summary!A95-1,FALSE) -> 0.32701027 | Z95: =VLOOKUP(Z$2,'Since Inception Returns'!$B:$AAB,Summary!A95-1,FALSE) -> 0.21563662
A96: 55 | C96: HRQB_U | D96: AMZH.U | E96: Harvest Amazon High Income Shares ETF | F96: =IFERROR(VLOOKUP(F$2,'R.WEALTH-Cummulative'!$A:$FG,$A96,FALSE)-1,"") -> 0.032568804 | G96: =IFERROR(VLOOKUP(G$2,'R.WEALTH-Cummulative'!$A:$FG,$A96,FALSE)-1,"") -> -0.0027228421 | H96: =IFERROR(VLOOKUP(H$2,'R.WEALTH-Cummulative'!$A:$FG,$A96,FALSE)-1,"") -> 0.046778666 | I96: =IFERROR(VLOOKUP(I$2,'R.WEALTH-Cummulative'!$A:$FG,$A96,FALSE)-1,"") -> 0.032568804 | J96: =IFERROR(VLOOKUP(J$2,'R.WEALTH-Cummulative'!$A:$FG,$A96,FALSE)-1,"") -> 0.030858835 | K96: =IFERROR((VLOOKUP(K$2,'R.WEALTH-Cummulative'!$A:$FG,$A96,FALSE)^(1/(K$2/12)))-1,"") | L96: =IFERROR((VLOOKUP(L$2,'R.WEALTH-Cummulative'!$A:$FG,$A96,FALSE)^(1/(L$2/12)))-1,"") | M96: =IFERROR((VLOOKUP(M$2,'R.WEALTH-Cummulative'!$A:$FG,$A96,FALSE)^(1/(M$2/12)))-1,"") | N96: =IFERROR((VLOOKUP(N$2,'R.WEALTH-Cummulative'!$A:$FG,$A96,FALSE)^(1/(N$2/12)))-1,"") | O96: =IFERROR((VLOOKUP(O$2,'R.WEALTH-Cummulative'!$A:$FG,$A96,FALSE)^(1/(O$2/12)))-1,"") | P96: =IFERROR((VLOOKUP(P$2,'R.WEALTH-Cummulative'!$A:$FG,$A96,FALSE)^(1/(P$2/12)))-1,"") | Q96: =IFERROR((VLOOKUP(Q$2,'R.WEALTH-Cummulative'!$A:$FG,$A96,FALSE)^(1/(Q$2/12)))-1,"") | R96: =IFERROR((VLOOKUP(R$2,'R.WEALTH-Cummulative'!$A:$FG,$A96,FALSE)^(1/(R$2/12)))-1,"") | ... X96: =IFERROR((VLOOKUP(X$2,'R.WEALTH-Cummulative'!$A:$FG,$A96,FALSE)^(1/(X$2/12)))-1,"") | Y96: =VLOOKUP(Y$2,'Since Inception Returns'!$B:$AAB,Summary!A96-1,FALSE) -> 0.32919062 | Z96: =VLOOKUP(Z$2,'Since Inception Returns'!$B:$AAB,Summary!A96-1,FALSE) -> 0.21701477
B97: 56 | C97: HRQB_A | D97: AMZH | E97: Cboe NASDAQ-100 Half BuyWrite V2 Index | F97: =IFERROR(VLOOKUP(F$2,'R.WEALTH-Cummulative (BM)'!$A:$FH,$B97,FALSE)-1,"") -> 0.014375281 | G97: =IFERROR(VLOOKUP(G$2,'R.WEALTH-Cummulative (BM)'!$A:$FH,$B97,FALSE)-1,"") -> 0.020253635 | H97: =IFERROR(VLOOKUP(H$2,'R.WEALTH-Cummulative (BM)'!$A:$FH,$B97,FALSE)-1,"") -> 0.11780947 | I97: =IFERROR(VLOOKUP(I$2,'R.WEALTH-Cummulative (BM)'!$A:$FH,$B97,FALSE)-1,"") -> 0.014375281 | J97: =IFERROR(VLOOKUP(J$2,'R.WEALTH-Cummulative (BM)'!$A:$FH,$B97,FALSE)-1,"") -> 0.14705767 | K97: =IFERROR((VLOOKUP(K$2,'R.WEALTH-Cummulative (BM)'!$A:$FH,$B97,FALSE)^(1/(K$2/12)))-1,"") | L97: =IFERROR((VLOOKUP(L$2,'R.WEALTH-Cummulative (BM)'!$A:$FH,$B97,FALSE)^(1/(L$2/12)))-1,"") | M97: =IFERROR((VLOOKUP(M$2,'R.WEALTH-Cummulative (BM)'!$A:$FH,$B97,FALSE)^(1/(M$2/12)))-1,"") | N97: =IFERROR((VLOOKUP(N$2,'R.WEALTH-Cummulative (BM)'!$A:$FH,$B97,FALSE)^(1/(N$2/12)))-1,"") | O97: =IFERROR((VLOOKUP(O$2,'R.WEALTH-Cummulative (BM)'!$A:$FH,$B97,FALSE)^(1/(O$2/12)))-1,"") | P97: =IFERROR((VLOOKUP(P$2,'R.WEALTH-Cummulative (BM)'!$A:$FH,$B97,FALSE)^(1/(P$2/12)))-1,"") | Q97: =IFERROR((VLOOKUP(Q$2,'R.WEALTH-Cummulative (BM)'!$A:$FH,$B97,FALSE)^(1/(Q$2/12)))-1,"") | R97: =IFERROR((VLOOKUP(R$2,'R.WEALTH-Cummulative (BM)'!$A:$FH,$B97,FALSE)^(1/(R$2/12)))-1,"") | ... X97: =IFERROR((VLOOKUP(X$2,'R.WEALTH-Cummulative (BM)'!$A:$FH,$B97,FALSE)^(1/(X$2/12)))-1,"") | Y97: =VLOOKUP(Y$2,'Since Inception (BM)'!$B:$AAC,Summary!B97-1,FALSE) -> 0.26311249 | Z97: =VLOOKUP(Z$2,'Since Inception (BM)'!$B:$AAC,Summary!B97-1,FALSE) -> 0.17492985
A98: 56 | C98: HRQD_A | D98: AMHE | E98: Harvest Amazon Enhanced High Income Shares ETF | F98: =IFERROR(VLOOKUP(F$2,'R.WEALTH-Cummulative'!$A:$FG,$A98,FALSE)-1,"") -> 0.031456806 | G98: =IFERROR(VLOOKUP(G$2,'R.WEALTH-Cummulative'!$A:$FG,$A98,FALSE)-1,"") -> -0.037092338 | H98: =IFERROR(VLOOKUP(H$2,'R.WEALTH-Cummulative'!$A:$FG,$A98,FALSE)-1,"") -> 0.031856719 | I98: =IFERROR(VLOOKUP(I$2,'R.WEALTH-Cummulative'!$A:$FG,$A98,FALSE)-1,"") -> 0.031456806 | J98: =IFERROR(VLOOKUP(J$2,'R.WEALTH-Cummulative'!$A:$FG,$A98,FALSE)-1,"") -> -0.050924399 | K98: =IFERROR((VLOOKUP(K$2,'R.WEALTH-Cummulative'!$A:$FG,$A98,FALSE)^(1/(K$2/12)))-1,"") | L98: =IFERROR((VLOOKUP(L$2,'R.WEALTH-Cummulative'!$A:$FG,$A98,FALSE)^(1/(L$2/12)))-1,"") | M98: =IFERROR((VLOOKUP(M$2,'R.WEALTH-Cummulative'!$A:$FG,$A98,FALSE)^(1/(M$2/12)))-1,"") | N98: =IFERROR((VLOOKUP(N$2,'R.WEALTH-Cummulative'!$A:$FG,$A98,FALSE)^(1/(N$2/12)))-1,"") | O98: =IFERROR((VLOOKUP(O$2,'R.WEALTH-Cummulative'!$A:$FG,$A98,FALSE)^(1/(O$2/12)))-1,"") | P98: =IFERROR((VLOOKUP(P$2,'R.WEALTH-Cummulative'!$A:$FG,$A98,FALSE)^(1/(P$2/12)))-1,"") | Q98: =IFERROR((VLOOKUP(Q$2,'R.WEALTH-Cummulative'!$A:$FG,$A98,FALSE)^(1/(Q$2/12)))-1,"") | R98: =IFERROR((VLOOKUP(R$2,'R.WEALTH-Cummulative'!$A:$FG,$A98,FALSE)^(1/(R$2/12)))-1,"") | ... X98: =IFERROR((VLOOKUP(X$2,'R.WEALTH-Cummulative'!$A:$FG,$A98,FALSE)^(1/(X$2/12)))-1,"") | Y98: =VLOOKUP(Y$2,'Since Inception Returns'!$B:$AAB,Summary!A98-1,FALSE) -> 0.39289943 | Z98: =VLOOKUP(Z$2,'Since Inception Returns'!$B:$AAB,Summary!A98-1,FALSE) -> 0.25698087
A99: 57 | C99: HRQD_U | D99: AMHE.U | E99: Harvest Amazon Enhanced High Income Shares ETF | F99: =IFERROR(VLOOKUP(F$2,'R.WEALTH-Cummulative'!$A:$FG,$A99,FALSE)-1,"") -> 0.039738544 | G99: =IFERROR(VLOOKUP(G$2,'R.WEALTH-Cummulative'!$A:$FG,$A99,FALSE)-1,"") -> -0.0082798088 | H99: =IFERROR(VLOOKUP(H$2,'R.WEALTH-Cummulative'!$A:$FG,$A99,FALSE)-1,"") -> 0.049874356 | I99: =IFERROR(VLOOKUP(I$2,'R.WEALTH-Cummulative'!$A:$FG,$A99,FALSE)-1,"") -> 0.039738544 | J99: =IFERROR(VLOOKUP(J$2,'R.WEALTH-Cummulative'!$A:$FG,$A99,FALSE)-1,"") -> 0.012674702 | K99: =IFERROR((VLOOKUP(K$2,'R.WEALTH-Cummulative'!$A:$FG,$A99,FALSE)^(1/(K$2/12)))-1,"") | L99: =IFERROR((VLOOKUP(L$2,'R.WEALTH-Cummulative'!$A:$FG,$A99,FALSE)^(1/(L$2/12)))-1,"") | M99: =IFERROR((VLOOKUP(M$2,'R.WEALTH-Cummulative'!$A:$FG,$A99,FALSE)^(1/(M$2/12)))-1,"") | N99: =IFERROR((VLOOKUP(N$2,'R.WEALTH-Cummulative'!$A:$FG,$A99,FALSE)^(1/(N$2/12)))-1,"") | O99: =IFERROR((VLOOKUP(O$2,'R.WEALTH-Cummulative'!$A:$FG,$A99,FALSE)^(1/(O$2/12)))-1,"") | P99: =IFERROR((VLOOKUP(P$2,'R.WEALTH-Cummulative'!$A:$FG,$A99,FALSE)^(1/(P$2/12)))-1,"") | Q99: =IFERROR((VLOOKUP(Q$2,'R.WEALTH-Cummulative'!$A:$FG,$A99,FALSE)^(1/(Q$2/12)))-1,"") | R99: =IFERROR((VLOOKUP(R$2,'R.WEALTH-Cummulative'!$A:$FG,$A99,FALSE)^(1/(R$2/12)))-1,"") | ... X99: =IFERROR((VLOOKUP(X$2,'R.WEALTH-Cummulative'!$A:$FG,$A99,FALSE)^(1/(X$2/12)))-1,"") | Y99: =VLOOKUP(Y$2,'Since Inception Returns'!$B:$AAB,Summary!A99-1,FALSE) -> 0.39481552 | Z99: =VLOOKUP(Z$2,'Since Inception Returns'!$B:$AAB,Summary!A99-1,FALSE) -> 0.25817399
B100: 58 | C100: HRQD | D100: AMHE | E100: Cboe NASDAQ-100 Half BuyWrite V2 Index | F100: =IFERROR(VLOOKUP(F$2,'R.WEALTH-Cummulative (BM)'!$A:$FH,$B100,FALSE)-1,"") -> 0.014375281 | G100: =IFERROR(VLOOKUP(G$2,'R.WEALTH-Cummulative (BM)'!$A:$FH,$B100,FALSE)-1,"") -> 0.020253635 | H100: =IFERROR(VLOOKUP(H$2,'R.WEALTH-Cummulative (BM)'!$A:$FH,$B100,FALSE)-1,"") -> 0.11780947 | I100: =IFERROR(VLOOKUP(I$2,'R.WEALTH-Cummulative (BM)'!$A:$FH,$B100,FALSE)-1,"") -> 0.014375281 | J100: =IFERROR(VLOOKUP(J$2,'R.WEALTH-Cummulative (BM)'!$A:$FH,$B100,FALSE)-1,"") -> 0.14705767 | K100: =IFERROR((VLOOKUP(K$2,'R.WEALTH-Cummulative (BM)'!$A:$FH,$B100,FALSE)^(1/(K$2/12)))-1,"") | L100: =IFERROR((VLOOKUP(L$2,'R.WEALTH-Cummulative (BM)'!$A:$FH,$B100,FALSE)^(1/(L$2/12)))-1,"") | M100: =IFERROR((VLOOKUP(M$2,'R.WEALTH-Cummulative (BM)'!$A:$FH,$B100,FALSE)^(1/(M$2/12)))-1,"") | N100: =IFERROR((VLOOKUP(N$2,'R.WEALTH-Cummulative (BM)'!$A:$FH,$B100,FALSE)^(1/(N$2/12)))-1,"") | O100: =IFERROR((VLOOKUP(O$2,'R.WEALTH-Cummulative (BM)'!$A:$FH,$B100,FALSE)^(1/(O$2/12)))-1,"") | P100: =IFERROR((VLOOKUP(P$2,'R.WEALTH-Cummulative (BM)'!$A:$FH,$B100,FALSE)^(1/(P$2/12)))-1,"") | Q100: =IFERROR((VLOOKUP(Q$2,'R.WEALTH-Cummulative (BM)'!$A:$FH,$B100,FALSE)^(1/(Q$2/12)))-1,"") | R100: =IFERROR((VLOOKUP(R$2,'R.WEALTH-Cummulative (BM)'!$A:$FH,$B100,FALSE)^(1/(R$2/12)))-1,"") | ... X100: =IFERROR((VLOOKUP(X$2,'R.WEALTH-Cummulative (BM)'!$A:$FH,$B100,FALSE)^(1/(X$2/12)))-1,"") | Y100: =VLOOKUP(Y$2,'Since Inception (BM)'!$B:$AAC,Summary!B100-1,FALSE) -> 0.26311249 | Z100: =VLOOKUP(Z$2,'Since Inception (BM)'!$B:$AAC,Summary!B100-1,FALSE) -> 0.17492985
...

Sheet Calendar Year Return
A2: Columns | B2: Helper column for Benchmark | C2: 2025 | D2: Tickers | E2: Fund Name | F2: 46022 | G2: 45657 | H2: 45291 | I2: 44926 | J2: 44561 | K2: 44196 | L2: 43830 | M2: 43465 | N2: 43100 | O2: 42735 | P2: 42369 | Q2: 42004
A4: 3 | C4: HR21_A | D4: HTA | E4: Harvest Tech Achievers Growth & Income ETF | F4: {=IF(INDEX('Since Inception Returns'!$B$188:$AAA$188,1,A4-1)="",PRODUCT(OFFSET('Since Inception Returns'!$B$199,0,A4-2,-12),VLOOKUP("First Wealth Relative",'Since Inception Returns'!$B:$AAA,'Calendar Year Return'!A4-1,FALSE))-1,PRODUCT(OFFSET('Since Inception Returns'!$B$199,0,A4-2,-12))-1)} -> 0.12376203 | G4: {=IF(INDEX('Since Inception Returns'!$B$188:$AAA$188,1,A4-1)="","",IF(INDEX('Since Inception Returns'!$B$176:$AAA$176,1,A4-1)="",PRODUCT(OFFSET('Since Inception Returns'!$B$187,0,A4-2,-12),VLOOKUP("First Wealth Relative",'Since Inception Returns'!$B:$AAA,'Calendar Year Return'!A4-1,FALSE))-1,PRODUCT(OFFSET('Since Inception Returns'!$B$187,0,A4-2,-12))-1))} -> 0.23619016 | H4: {=IF(INDEX('Since Inception Returns'!$B$176:$AAA$176,1,A4-1)="","",IF(INDEX('Since Inception Returns'!$B$164:$AAA$164,1,A4-1)="",PRODUCT(OFFSET('Since Inception Returns'!$B$175,0,A4-2,-12),VLOOKUP("First Wealth Relative",'Since Inception Returns'!$B:$AAA,'Calendar Year Return'!A4-1,FALSE))-1,PRODUCT(OFFSET('Since Inception Returns'!$B$175,0,A4-2,-12))-1))} -> 0.52787878 | I4: {=IF(INDEX('Since Inception Returns'!$B$164:$AAA$164,1,A4-1)="","",IF(INDEX('Since Inception Returns'!$B$152:$AAA$152,1,A4-1)="",PRODUCT(OFFSET('Since Inception Returns'!$B$163,0,A4-2,-12),VLOOKUP("First Wealth Relative",'Since Inception Returns'!$B:$AAA,'Calendar Year Return'!A4-1,FALSE))-1,PRODUCT(OFFSET('Since Inception Returns'!$B$163,0,A4-2,-12))-1))} -> -0.32168238 | J4: {=IF(INDEX('Since Inception Returns'!$B$152:$AAA$152,1,A4-1)="","",IF(INDEX('Since Inception Returns'!$B$140:$AAA$140,1,A4-1)="",PRODUCT(OFFSET('Since Inception Returns'!$B$151,0,A4-2,-12),VLOOKUP("First Wealth Relative",'Since Inception Returns'!$B:$AAA,'Calendar Year Return'!A4-1,FALSE))-1,PRODUCT(OFFSET('Since Inception Returns'!$B$151,0,A4-2,-12))-1))} -> 0.42797401 | K4: {=IF(INDEX('Since Inception Returns'!$B$140:$AAA$140,1,A4-1)="","",IF(INDEX('Since Inception Returns'!$B$128:$AAA$128,1,A4-1)="",PRODUCT(OFFSET('Since Inception Returns'!$B$139,0,A4-2,-12),VLOOKUP("First Wealth Relative",'Since Inception Returns'!$B:$AAA,'Calendar Year Return'!A4-1,FALSE))-1,PRODUCT(OFFSET('Since Inception Returns'!$B$139,0,A4-2,-12))-1))} -> 0.29586797 | L4: {=IF(INDEX('Since Inception Returns'!$B$128:$AAA$128,1,A4-1)="","",IF(INDEX('Since Inception Returns'!$B$116:$AAA$116,1,A4-1)="",PRODUCT(OFFSET('Since Inception Returns'!$B$127,0,A4-2,-12),VLOOKUP("First Wealth Relative",'Since Inception Returns'!$B:$AAA,'Calendar Year Return'!A4-1,FALSE))-1,PRODUCT(OFFSET('Since Inception Returns'!$B$127,0,A4-2,-12))-1))} -> 0.32275462 | M4: {=IF(INDEX('Since Inception Returns'!$B$116:$AAA$116,1,A4-1)="","",IF(INDEX('Since Inception Returns'!$B$104:$AAA$104,1,A4-1)="",PRODUCT(OFFSET('Since Inception Returns'!$B$115,0,A4-2,-12),VLOOKUP("First Wealth Relative",'Since Inception Returns'!$B:$AAA,'Calendar Year Return'!A4-1,FALSE))-1,PRODUCT(OFFSET('Since Inception Returns'!$B$115,0,A4-2,-12))-1))} -> -0.0020500439 | N4: {=IF(INDEX('Since Inception Returns'!$B$104:$AAA$104,1,A4-1)="","",IF(INDEX('Since Inception Returns'!$B$92:$AAA$92,1,A4-1)="",PRODUCT(OFFSET('Since Inception Returns'!$B$103,0,A4-2,-12),VLOOKUP("First Wealth Relative",'Since Inception Returns'!$B:$AAA,'Calendar Year Return'!A4-1,FALSE))-1,PRODUCT(OFFSET('Since Inception Returns'!$B$103,0,A4-2,-12))-1))} -> 0.30996062 | O4: {=IF(INDEX('Since Inception Returns'!$B$92:$AAA$92,1,A4-1)="","",IF(INDEX('Since Inception Returns'!$B$80:$AAA$80,1,A4-1)="",PRODUCT(OFFSET('Since Inception Returns'!$B$91,0,A4-2,-12),VLOOKUP("First Wealth Relative",'Since Inception Returns'!$B:$AAA,'Calendar Year Return'!A4-1,FALSE))-1,PRODUCT(OFFSET('Since Inception Returns'!$B$91,0,A4-2,-12))-1))} -> 0.072801971 | P4: {=IF(INDEX('Since Inception Returns'!$B$80:$AAA$80,1,A4-1)="","",IF(INDEX('Since Inception Returns'!$B$68:$AAA$68,1,A4-1)="",PRODUCT(OFFSET('Since Inception Returns'!$B$79,0,A4-2,-12),VLOOKUP("First Wealth Relative",'Since Inception Returns'!$B:$AAA,'Calendar Year Return'!A4-1,FALSE))-1,PRODUCT(OFFSET('Since Inception Returns'!$B$79,0,A4-2,-12))-1))} -> -0.06804033 | Q4: {=IF(INDEX('Since Inception Returns'!$B$68:$AAA$68,1,A4-1)="","",IF(INDEX('Since Inception Returns'!$B$56:$AAA$56,1,A4-1)="",PRODUCT(OFFSET('Since Inception Returns'!$B$67,0,A4-2,-12),VLOOKUP("First Wealth Relative",'Since Inception Returns'!$B:$AAA,'Calendar Year Return'!A4-1,FALSE))-1,PRODUCT(OFFSET('Since Inception Returns'!$B$67,0,A4-2,-12))-1))}
